Workbook

Sheet Main
R2: all values in millions except per share numbers
B4: Company Overview
B6: Price | G6: Key Stats | M6: Valuation | R6: Notes
B7: Ticker | E7: ETN | G7: Employees | I7: 94443 | M7: PV of FCF | P7: =SUM(J91:R91) -> 42995.515 | R7: WACC | U7: 0.0915
B8: Implied Share Price | E8: =P12/P11 -> 334.00838 | G8: Founded | I8: 1911 | M8: Terminal Value | P8: =R86*(1+U8)/(U7-U8) -> 174844.82 | R8: TGR | U8: 0.03
B9: Current Share Price | E9: 351.42 | G9: CEO | I9: Paulo Ruiz | M9: PV of Terminal Value | P9: =P8*R90 -> 83071.294
B10: Implied Upside / (Downside) | G10: Headquarters | I10: Dublin, Ireland | M10: Net Debt | P10: =-328-327+761+8802+568 -> 9476 | R10: WACC
G11: Primary Industry | M11: Shares Outstanding | P11: 390.31 | R11: Market Cap
B12: Last Updated | E12: 46064 | G12: Fiscal Year End | M12: Implied Market Cap | P12: =P7+P9+4300 -> 130366.81 | R12: % of Equity
R13: Cost of Equity | U13: =U14+U15*(U17) -> 0.092542
R14: Risk Free Rate | U14: 0.0428
B15: Key Statistics | E15: 2021 | F15: =E15+1 -> 2022 | G15: =F15+1 -> 2023 | H15: =G15+1 -> 2024 | I15: =H15+1 -> 2025 | J15: 2026E | K15: 2027E | M15: Financial Ratios | R15: Beta | U15: 1.19
M16: PV of FCF | P16: =SUM(J99:N99) -> 0
B17: Stock Price | M17: Market Cap | R17: Market Risk Premium | U17: 0.0418
B18: shares outstanding diluted | M18: Enterprise Value | R18: Debt
M19: P/E (LTM) | P19: =E9/12.06 -> 29.139303 | R19: % of Debt
B20: Market Cap | M20: P/E (NTM) | P20: =E9/13.49 -> 26.050408 | R20: Cost of Debt
B21: Cash | M21: EV/S (LTM) | P21: =E9/(I27/P11) -> 4.9937285 | R21: Tax Rate
B22: Debt | M22: EV/EBIT (LTM) | P22: =E8/(I42/P11) -> 23.660038 | R22: Total
B23: Enterprise Value | R23: WACC
B25: Income Statement | E25: 2021 | F25: =E25+1 -> 2022 | G25: =F25+1 -> 2023 | H25: =G25+1 -> 2024 | I25: =H25+1 -> 2025 | J25: 2026E | K25: 2027E | L25: 2028E | M25: 2029E | N25: 2030E
B27: Revenue | E27: 19628 | F27: 20752 | G27: 23196 | H27: 24878 | I27: 27467 | J27: 30011 | K27: 32665 | L27: 36875 | M27: 39180 | N27: =M27*1.1 -> 43098
B28: % growth
B30: COGS
B31: % of sales | I31: 0.537
B33: Gross Income
B34: % of sales
B36: SG&A
B37: % of sales | I37: 0.134
B39: R&D
B40: % of sales
B42: EBIT | E42: 3706 | F42: 4196 | G42: 3978 | H42: 4870 | I42: 5510 | J42: =Segments!L80 -> 7252.387 | K42: =Segments!M80 -> 8055.5737 | L42: =Segments!N80 -> 8841.7612 | M42: =Segments!O80 -> 9741.8671 | N42: =Segments!P80 -> 10688.807
B43: % of sales
B45: Taxes
B46: Tax rate
B48: Cash Flow Items | E48: 2021 | F48: =E48+1 -> 2022 | G48: =F48+1 -> 2023 | H48: =G48+1 -> 2024 | I48: =H48+1 -> 2025 | J48: 2026E | K48: 2027E | L48: 2028E | M48: 2029E | N48: 2030E
B50: D&A | E50: 929 | F50: 956 | G50: 926 | H50: 924 | I50: 992 | J50: =J27*$I$51 -> 1050.385 | K50: =K27*$I$51 -> 1143.275 | L50: =L27*$I$51 -> 1290.625 | M50: =M27*$I$51 -> 1371.3 | N50: =N27*$I$51 -> 1508.43
B51: % of sales | E51: =E50/E27 -> 0.047330344 | F51: =F50/F27 -> 0.046067849 | G51: =G50/G27 -> 0.039920676 | H51: =H50/H27 -> 0.037141249 | I51: 0.035 | J51: =J50/J27 -> 0.035 | K51: =K50/K27 -> 0.035 | L51: =L50/L27 -> 0.035 | M51: =M50/M27 -> 0.035 | N51: =N50/N27 -> 0.035
B52: % of capex | E52: =E50/E54 -> 1.6156522 | F52: =F50/F54 -> 1.5986622 | G52: =G50/G54 -> 1.2232497 | H52: =H50/H54 -> 1.1435644 | I52: =I50/I54 -> 30523.077 | J52: =J50/J54 -> 1.0769231 | K52: =K50/K54 -> 1.0769231 | L52: =L50/L54 -> 1.0769231 | ... N52: =N50/N54 -> 1.0769231
B54: CapEx | E54: 575 | F54: 598 | G54: 757 | H54: 808 | I54: 0.0325 | J54: =J27*$I$54 -> 975.3575 | K54: =K27*$I$54 -> 1061.6125 | L54: =L27*$I$54 -> 1198.4375 | M54: =M27*$I$54 -> 1273.35 | N54: =N27*$I$54 -> 1400.685
B55: % of fcf | E55: =E54/E27 -> 0.029294885 | F55: =F54/F27 -> 0.0288165 | G55: =G54/G27 -> 0.032634937 | H55: =H54/H27 -> 0.032478495 | I55: 0.0325 | J55: =J54/J27 -> 0.0325 | K55: =K54/K27 -> 0.0325 | L55: =L54/L27 -> 0.0325 | M55: =M54/M27 -> 0.0325 | N55: =N54/N27 -> 0.0325
B57: Changes in NWC | E57: -540 | F57: -599 | G57: -757 | H57: -809 | I57: -1104 | J57: =(J27-I27)*$I$58 -> -127.2 | K57: =(K27-J27)*$I$58 -> -132.7 | L57: =(L27-K27)*$I$58 -> -210.5 | M57: =(M27-L27)*$I$58 -> -115.25 | N57: =(N27-M27)*$I$58 -> -195.9
B58: % of sales | E58: =E57/E27 -> -0.027511718 | F58: =F57/F27 -> -0.028864688 | G58: =G57/G27 -> -0.032634937 | H58: =H57/H27 -> -0.032518691 | I58: -0.05 | J58: =J57/J27 -> -0.0042384459 | K58: =K57/K27 -> -0.0040624522 | L58: =L57/L27 -> -0.0057084746 | M58: =M57/M27 -> -0.0029415518 | N58: =N57/N27 -> -0.0045454545
B59: % of changes in sales | E59: =E57/(E27-0) -> -0.027511718 | F59: =F57/(F27-E27) -> -0.53291815 | G59: =G57/(G27-F27) -> -0.30973813 | H59: =H57/(H27-G27) -> -0.48097503 | I59: =I57/(I27-H27) -> -0.42641947 | J59: =J57/(J27-I27) -> -0.05 | K59: =K57/(K27-J27) -> -0.05 | L59: =L57/(L27-K27) -> -0.05 | M59: =M57/(M27-L27) -> -0.05 | N59: =N57/(N27-M27) -> -0.05
B61: DCF | E61: 2021 | F61: =E61+1 -> 2022 | G61: =F61+1 -> 2023 | H61: =G61+1 -> 2024 | I61: =H61+1 -> 2025 | J61: 2026E | K61: 2027E | L61: 2028E | M61: 2029E | N61: 2030E | O61: 2031E | P61: 2032E | Q61: 2033E | R61: 2034E
B63: Revenue | E63: 19628 | F63: 20752 | G63: 23196 | H63: 24878 | I63: 27467.4 | J63: =I63*1.106 -> 30378.944 | K63: =J63*1.096 -> 33295.323 | L63: =K63*1.063 -> 35392.928 | M63: =L63*1.09 -> 38578.292 | N63: =M63*1.1 -> 42436.121 | O63: =N63*1.09 -> 46255.372 | P63: =O63*1.08 -> 49955.802 | Q63: =P63*1.08 -> 53952.266 | R63: =Q63*1.075 -> 57998.686
B64: % growth | F64: =(F63-E63)/E63 -> 0.057265131 | G64: =(G63-F63)/F63 -> 0.11777178 | H64: =(H63-G63)/G63 -> 0.072512502 | I64: =(I63-H63)/H63 -> 0.10408393 | J64: =(J63-I63)/I63 -> 0.106 | K64: =(K63-J63)/J63 -> 0.096 | L64: =(L63-K63)/K63 -> 0.063 | M64: =(M63-L63)/L63 -> 0.09 | ... R64: =(R63-Q63)/Q63 -> 0.075
B66: EBIT | E66: =E42 -> 3706 | F66: =F42 -> 4196 | G66: =G42 -> 3978 | H66: =H42 -> 4870 | I66: =I42 -> 5510 | J66: =J42 -> 7252.387 | K66: =K42 -> 8055.5737 | L66: =L42 -> 8841.7612 | ... N66: =N42 -> 10688.807
B67: % of sales | E67: =E66/E63 -> 0.1888119 | F67: =F66/F63 -> 0.20219738 | G67: =G66/G63 -> 0.17149509 | H67: =H66/H63 -> 0.19575529 | I67: =I66/I63 -> 0.20060144 | J67: =J66/J63 -> 0.23873071 | K67: =K66/K63 -> 0.2419431 | L67: =L66/L63 -> 0.24981717 | ... N67: =N66/N63 -> 0.25187992
B69: Taxes | E69: =E45 -> 0 | F69: =F45 -> 0 | G69: =G45 -> 0 | H69: =H45 -> 0 | I69: =I45 -> 0 | J69: =J45 -> 0 | K69: =K45 -> 0 | L69: =L45 -> 0 | ... N69: =N45 -> 0
B70: Tax rate | E70: =E69/E66 -> 0 | F70: =F69/F66 -> 0 | G70: =G69/G66 -> 0 | H70: =H69/H66 -> 0 | I70: =I69/I66 -> 0 | J70: =J69/J66 -> 0 | K70: =K69/K66 -> 0 | L70: =L69/L66 -> 0 | ... N70: =N69/N66 -> 0
B72: EBIAT | E72: =E66-E69 -> 3706 | F72: =F66-F69 -> 4196 | G72: =G66-G69 -> 3978 | H72: =H66-H69 -> 4870 | I72: =I66-I69 -> 5510 | J72: =J66-J69 -> 7252.387 | K72: =K66-K69 -> 8055.5737 | L72: =L66-L69 -> 8841.7612 | ... N72: =N66-N69 -> 10688.807
B74: D&A | E74: =E50 -> 929 | F74: =F50 -> 956 | G74: =G50 -> 926 | H74: =H50 -> 924 | I74: =I50 -> 992 | J74: =J50 -> 1050.385 | K74: =K50 -> 1143.275 | L74: =L50 -> 1290.625 | ... N74: =N50 -> 1508.43
B75: % of sales | E75: =E74/E63 -> 0.047330344 | F75: =F74/F63 -> 0.046067849 | G75: =G74/G63 -> 0.039920676 | H75: =H74/H63 -> 0.037141249 | I75: =I74/I63 -> 0.036115541 | J75: =J74/J63 -> 0.034576086 | K75: =K74/K63 -> 0.034337405 | L75: =L74/L63 -> 0.036465618 | ... N75: =N74/N63 -> 0.035545897
B77: CapEx | E77: =E54 -> 575 | F77: =F54 -> 598 | G77: =G54 -> 757 | H77: =H54 -> 808 | I77: =I54 -> 0.0325 | J77: =J54 -> 975.3575 | K77: =K54 -> 1061.6125 | L77: =L54 -> 1198.4375 | ... N77: =N54 -> 1400.685
B78: % of sales | E78: =E77/E63 -> 0.029294885 | F78: =F77/F63 -> 0.0288165 | G78: =G77/G63 -> 0.032634937 | H78: =H77/H63 -> 0.032478495 | I78: =I77/I63 -> 1.1832208e-06 | J78: =J77/J63 -> 0.032106366 | K78: =K77/K63 -> 0.031884733 | L78: =L77/L63 -> 0.033860931 | ... N78: =N77/N63 -> 0.033006905
B80: Changes in NWC | E80: =E57 -> -540 | F80: =F57 -> -599 | G80: =G57 -> -757 | H80: =H57 -> -809 | I80: =I57 -> -1104 | J80: =J57 -> -127.2 | K80: =K57 -> -132.7 | L80: =L57 -> -210.5 | ... N80: =N57 -> -195.9
B81: % of sales | E81: =E80/E63 -> -0.027511718 | F81: =F80/F63 -> -0.028864688 | G81: =G80/G63 -> -0.032634937 | H81: =H80/H63 -> -0.032518691 | I81: =I80/I63 -> -0.040193102 | J81: =J80/J63 -> -0.0041871106 | K81: =K80/K63 -> -0.0039855447 | L81: =L80/L63 -> -0.0059475158 | ... N81: =N80/N63 -> -0.0046163503
B83: Stock Based Compensation | E83: 0 | F83: 0 | G83: 0 | H83: 0 | I83: 0 | J83: =J63*$I$84 -> 0 | K83: =K63*$I$84 -> 0 | L83: =L63*$I$84 -> 0 | M83: =M63*$I$84 -> 0 | N83: =N63*$I$84 -> 0
B84: % of sales | E84: =E83/E63 -> 0 | F84: =F83/F63 -> 0 | G84: =G83/G63 -> 0 | H84: =H83/H63 -> 0 | I84: 0 | J84: =J83/J63 -> 0 | K84: =K83/K63 -> 0 | L84: =L83/L63 -> 0 | M84: =M83/M63 -> 0 | N84: =N83/N63 -> 0
B86: Free Cash Flow | E86: 2128 | F86: 1935 | G86: 2867 | H86: 3518 | I86: 3761.44 | J86: 4334.07 | K86: 5150.88 | L86: =L63*0.16 -> 5662.8685 | M86: =M63*0.165 -> 6365.4182 | N86: =N63*0.17 -> 7214.1406 | O86: =O63*0.18 -> 8325.967 | P86: =P63*0.18 -> 8992.0443 | Q86: =Q63*0.18 -> 9711.4079 | R86: =R63*0.18 -> 10439.763
B87: % of sales | E87: =E86/E63 -> 0.10841655 | F87: =F86/F63 -> 0.093244025 | G87: =G86/G63 -> 0.1235989 | H87: =H86/H63 -> 0.14141008 | I87: =I86/I63 -> 0.13694197 | J87: =J86/J63 -> 0.14266691 | K87: =K86/K63 -> 0.15470281 | L87: =L86/L63 -> 0.16 | ... R87: =R86/R63 -> 0.18
B89: Discount Period | J89: 0.5 | K89: =J89+1 -> 1.5 | L89: =K89+1 -> 2.5 | M89: =L89+1 -> 3.5 | N89: =M89+1 -> 4.5 | O89: =N89+1 -> 5.5 | P89: =O89+1 -> 6.5 | Q89: =P89+1 -> 7.5 | R89: =Q89+1 -> 8.5
B90: Discount Factor | J90: =1/(1+$U$7)^J89 -> 0.95716791 | K90: =1/(1+$U$7)^K89 -> 0.87692891 | L90: =1/(1+$U$7)^L89 -> 0.80341632 | M90: =1/(1+$U$7)^M89 -> 0.73606626 | N90: =1/(1+$U$7)^N89 -> 0.67436212 | O90: =1/(1+$U$7)^O89 -> 0.61783062 | P90: =1/(1+$U$7)^P89 -> 0.56603813 | Q90: =1/(1+$U$7)^Q89 -> 0.51858739 | R90: =1/(1+$U$7)^R89 -> 0.47511442
B91: Present Value of FCF | J91: =J86*J90 -> 4148.4327 | K91: =K86*K90 -> 4516.9556 | L91: =L86*L90 -> 4549.641 | M91: =M86*M90 -> 4685.3695 | N91: =N86*N90 -> 4864.9432 | O91: =O86*O90 -> 5144.0374 | P91: =P86*P90 -> 5089.84 | Q91: =Q86*Q90 -> 5036.2136 | R91: =R86*R90 -> 4960.0821
B93: KEY MODEL ASSUMPTIONS
B95: Revenue Growth Drivers:
B96: • Electrical Americas: Data center AI infrastructure demand driving 10-12% growth
B97: • Electrical Global: EU Green Deal + Asia manufacturing recovery driving 5-8% growth
B98: • Aerospace: Commercial aviation ramp + defense spending driving 7-11% growth
B99: • Vehicle: ICE decline offset by content per vehicle, flat to low single-digit growth
B100: • E-Mobility: Scale inflection in 2026E, accelerating to 10-28% growth through 2030
B101: Enterprise Value
B102: • COGS: 53.7% of revenue | SG&A: 13.4% | R&D: 2.6% | D&A: 3.5% | CapEx: 3.25% | NWC: -5% of Δ revenue

Sheet Segments
A4: x | B4: Electrical Americas | G4: 2021 | H4: 2022 | I4: 2023 | J4: 2024 | K4: 2025 | L4: 2026E | M4: 2027E | N4: 2028E | O4: 2029E | P4: 2030E | Q4: Notes
B5: ELECTRICAL AMERICAS
B6: Data Center & Community | G6: =G15*0.45 -> 3258.9 | H6: =H15*0.47 -> 3993.59 | I6: =I15*0.5 -> 5049 | J6: =J15*0.52 -> 5946.72 | K6: =K15*0.55 -> 7347.175 | L6: =K6*1.22 -> 8963.5535 | M6: =L6*1.18 -> 10576.993 | N6: =M6*1.15 -> 12163.542 | O6: =N6*1.12 -> 13623.167 | P6: =O6*1.1 -> 14985.484 | Q6: Data centers, housing starts
B7: % YoY Growth | H7: =(H6-G6)/G6 -> 0.2254411 | I7: =(I6-H6)/H6 -> 0.264276 | J7: =(J6-I6)/I6 -> 0.17780154 | K7: =(K6-J6)/J6 -> 0.23550041 | L7: =(L6-K6)/K6 -> 0.22 | M7: =(M6-L6)/L6 -> 0.18 | N7: =(N6-M6)/M6 -> 0.15 | O7: =(O6-N6)/N6 -> 0.12 | P7: =(P6-O6)/O6 -> 0.1
B9: Utility & Industrial | G9: =G15*0.35 -> 2534.7 | H9: =H15*0.35 -> 2973.95 | I9: =I15*0.35 -> 3534.3 | J9: =J15*0.36 -> 4116.96 | K9: =K15*0.37 -> 4942.645 | L9: =K9*1.11 -> 5486.3359 | M9: =L9*1.1 -> 6034.9695 | N9: =M9*1.108 -> 6686.7463 | O9: =N9*1.07 -> 7154.8185 | P9: =O9*1.06 -> 7584.1076
B10: % YoY Growth | H10: =(H9-G9)/G9 -> 0.17329467 | I10: =(I9-H9)/H9 -> 0.18841944 | J10: =(J9-I9)/I9 -> 0.16485867 | K10: =(K9-J9)/J9 -> 0.20055696 | L10: =(L9-K9)/K9 -> 0.11 | M10: =(M9-L9)/L9 -> 0.1 | N10: =(N9-M9)/M9 -> 0.108 | O10: =(O9-N9)/N9 -> 0.07 | P10: =(P9-O9)/O9 -> 0.06
B12: Residential | G12: =G15*0.2 -> 1448.4 | H12: =H15*0.18 -> 1529.46 | I12: =I15*0.15 -> 1514.7 | J12: =J15*0.12 -> 1372.32 | K12: =K15*0.08 -> 1068.68 | L12: =K12*0.98 -> 1047.3064 | M12: =L12*1.03 -> 1078.7256 | N12: =M12*1.05 -> 1132.6619 | O12: =N12*1.05 -> 1189.295 | P12: =O12*1.05 -> 1248.7597 | Q12: Grid modernization, renewables
B13: % YoY Growth | H13: =(H12-G12)/G12 -> 0.055965203 | I13: =(I12-H12)/H12 -> -0.0096504649 | J13: =(J12-I12)/I12 -> -0.093998812 | K13: =(K12-J12)/J12 -> -0.22126035 | L13: =(L12-K12)/K12 -> -0.02 | M13: =(M12-L12)/L12 -> 0.03 | N13: =(N12-M12)/M12 -> 0.05 | O13: =(O12-N12)/N12 -> 0.05 | P13: =(P12-O12)/O12 -> 0.05
B15: Total Electrical Americas | G15: 7242 | H15: 8497 | I15: 10098 | J15: 11436 | K15: 13358.5 | L15: 15025.9 | M15: 16619.5 | N15: 18145 | O15: =N15*1.085 -> 19687.325 | P15: =O15*1.08 -> 21262.311
B16: % YoY Growth | H16: =(H15-G15)/G15 -> 0.17329467 | I16: =(I15-H15)/H15 -> 0.18841944 | J16: =(J15-I15)/I15 -> 0.13250149 | K16: =(K15-J15)/J15 -> 0.16810948 | L16: =(L15-K15)/K15 -> 0.1248194 | M16: =(M15-L15)/L15 -> 0.10605688 | N16: =(N15-M15)/M15 -> 0.091789765 | O16: =(O15-N15)/N15 -> 0.085 | P16: =(P15-O15)/O15 -> 0.08
B18: Operating Income | G18: 1495 | H18: 1912 | I18: 2676 | J18: 3454 | K18: 3985.89 | L18: 4512.41 | M18: 5088.5 | N18: =N15*0.31 -> 5624.95 | O18: =O15*0.313 -> 6162.1327 | P18: =P15*0.315 -> 6697.628
B19: Operating Margin % | G19: =G18/G15 -> 0.20643469 | H19: =H18/H15 -> 0.2250206 | I19: =I18/I15 -> 0.26500297 | J19: =J18/J15 -> 0.30202868 | K19: =K18/K15 -> 0.29837856 | L19: =L18/L15 -> 0.3003088 | M19: =M18/M15 -> 0.30617648 | N19: =N18/N15 -> 0.31 | ... P19: =P18/P15 -> 0.315
B20: Key Drivers:
B21: • Data center growth rate | G21: - | H21: - | I21: - | J21: - | K21: - | L21: 25-30% | M21: 20-25% | N21: 15-20% | O21: 12-15% | P21: 10-12% | Q21: AI infrastructure demand
B22: • Grid modernization spending | G22: - | H22: - | I22: - | J22: - | K22: - | L22: 15-18% | M22: 12-15% | N22: 10-12% | O22: 8-10% | P22: 7-9% | Q22: IRA/infrastructure bill impact
A23: x | B23: Electrical Global | G23: 2021 | H23: 2022 | I23: 2023 | J23: 2024 | K23: 2025 | L23: 2026E | M23: 2027E | N23: 2028E | O23: 2029E | P23: 2030E
B25: Europe | G25: 2758 | H25: 2924 | I25: 3042 | J25: 3124 | K25: 3390 | L25: =G25*1.058 -> 2917.964 | M25: =L25*1.11 -> 3238.94 | N25: =M25*1.125 -> 3643.8075 | O25: =N25*1.1 -> 4008.1883 | P25: =O25*1.085 -> 4348.8843 | Q25: Electrification trends, EV charging
B26: Asia Pacific | G26: 1379 | H26: 1462 | I26: 1521 | J26: 1562 | K26: 1695 | L26: =G26*1.058 -> 1458.982 | M26: =L26*1.055 -> 1539.226 | N26: =M26*1.08 -> 1662.3641 | O26: =N26*1.115 -> 1853.536 | P26: =O26*1.12 -> 2075.9603 | Q26: China manufacturing, India growth
B27: Rest of World | G27: 1379 | H27: 1462 | I27: 1521 | J27: 1562 | K27: 1695 | L27: =G27*1.058 -> 1458.982 | M27: =L27*1.055 -> 1539.226 | N27: =M27*1.07 -> 1646.9718 | O27: =N27*1.095 -> 1803.4342 | P27: =O27*1.105 -> 1992.7947 | Q27: Emerging markets infrastructure
B28: Total Electrical Global | G28: =SUM(G25:G27) -> 5516 | H28: =SUM(H25:H27) -> 5848 | I28: =SUM(I25:I27) -> 6084 | J28: =SUM(J25:J27) -> 6248 | K28: =SUM(K25:K27) -> 6780 | L28: =SUM(L25:L27) -> 5835.928 | M28: =SUM(M25:M27) -> 6317.3921 | N28: =SUM(N25:N27) -> 6953.1435 | ... P28: =SUM(P25:P27) -> 8417.6393
B29: % YoY Growth | H29: =(H28-G28)/G28 -> 0.060188542 | I29: =(I28-H28)/H28 -> 0.040355677 | J29: =(J28-I28)/I28 -> 0.02695595 | K29: =(K28-J28)/J28 -> 0.085147247 | L29: =(L28-K28)/K28 -> -0.13924366 | M29: =(M28-L28)/L28 -> 0.0825 | N29: =(N28-M28)/M28 -> 0.1006351 | O29: =(O28-N28)/N28 -> 0.10240188 | P29: =(P28-O28)/O28 -> 0.098168996
B31: Operating Income | G31: 1034 | H31: 1134 | I31: 1176 | J31: 1150 | K31: 1318 | L31: =G31*1.08 -> 1116.72 | M31: =L31*1.083 -> 1209.4078 | N31: =M31*1.115 -> 1348.4897 | O31: =N31*1.12 -> 1510.3084 | P31: =O31*1.115 -> 1683.9939
B32: Operating Margin % | G32: =G31/G28 -> 0.18745468 | H32: =H31/H28 -> 0.19391245 | I32: =I31/I28 -> 0.19329389 | J32: =J31/J28 -> 0.1840589 | K32: =K31/K28 -> 0.19439528 | L32: =L31/L28 -> 0.1913526 | M32: =M31/M28 -> 0.19144099 | N32: =N31/N28 -> 0.19393957 | ... P32: =P31/P28 -> 0.20005536
B33: Key Drivers:
B34: • Asia manufacturing PMI | G34: - | H34: - | I34: - | J34: - | K34: - | L34: 52-54 | M34: 53-55 | N34: 54-56 | O34: 55-57 | P34: 56-58 | Q34: Industrial capex recovery
A36: x | B36: Vehicle | G36: 2021 | H36: 2022 | I36: 2023 | J36: 2024 | K36: 2025 | L36: 2026E | M36: 2027E | N36: 2028E | O36: 2029E | P36: 2030E
B37: ELECTRICAL AMERICAS
B38: Light Vehicle | G38: 1547 | H38: 1698 | I38: 1779 | J38: 1674 | K38: 1506 | L38: =G38*0.95 -> 1469.65 | M38: =L38*1.015 -> 1491.6947 | N38: =M38*1.045 -> 1558.821 | O38: =N38*1.065 -> 1660.1444 | P38: =O38*1.065 -> 1768.0538 | Q38: ICE powertrain decline
B39: Commercial Vehicle | G39: 1032 | H39: 1132 | I39: 1186 | J39: 1116 | K39: 1004 | L39: =G39*0.95 -> 980.4 | M39: =L39*1.015 -> 995.106 | N39: =M39*1.045 -> 1039.8858 | O39: =N39*1.065 -> 1107.4783 | P39: =O39*1.065 -> 1179.4644 | Q39: Freight cycle sensitivity
B40: Total Vehicle | G40: =SUM(G38:G39) -> 2579 | H40: =SUM(H38:H39) -> 2830 | I40: =SUM(I38:I39) -> 2965 | J40: =SUM(J38:J39) -> 2790 | K40: =SUM(K38:K39) -> 2510 | L40: =SUM(L38:L39) -> 2450.05 | M40: =SUM(M38:M39) -> 2486.8007 | N40: =SUM(N38:N39) -> 2598.7068 | ... P40: =SUM(P38:P39) -> 2947.5182
B41: % YoY Growth | H41: =(H40-G40)/G40 -> 0.097324544 | I41: =(I40-H40)/H40 -> 0.04770318 | J41: =(J40-I40)/I40 -> -0.059021922 | K41: =(K40-J40)/J40 -> -0.10035842 | L41: =(L40-K40)/K40 -> -0.023884462 | M41: =(M40-L40)/L40 -> 0.015 | N41: =(N40-M40)/M40 -> 0.045 | O41: =(O40-N40)/N40 -> 0.065 | P41: =(P40-O40)/O40 -> 0.065
B43: Operating Income | G43: 449 | H43: 453 | I43: 482 | J43: 503 | K43: 408 | L43: =G43*1.013 -> 454.837 | M43: =L43*1.09 -> 495.77233 | N43: =M43*1.09 -> 540.39184 | O43: =N43*1.117 -> 603.61768 | P43: =O43*1.12 -> 676.05181
B44: Operating Margin % | G44: =G43/G40 -> 0.17409849 | H44: =H43/H40 -> 0.16007067 | I44: =I43/I40 -> 0.16256324 | J44: =J43/J40 -> 0.18028674 | K44: =K43/K40 -> 0.1625498 | L44: =L43/L40 -> 0.18564397 | M44: =M43/M40 -> 0.1993615 | N44: =N43/N40 -> 0.20794645 | ... P44: =P43/P40 -> 0.22936306
B45: Key Drivers:
B46: • ICE penetration decline rate | G46: - | H46: - | I46: - | J46: - | K46: - | L46: 5-7% | M46: 3-5% | N46: 2-4% | O46: 1-3% | P46: 1-3% | Q46: EV transition impact
B47: • Content per vehicle premium | G47: - | H47: - | I47: - | J47: - | K47: - | L47: $180-220 | M47: $200-240 | N47: $220-260 | O47: $240-280 | P47: $260-300 | Q47: Complexity offset to volume
A50: x | B50: E-Mobility | G50: 2021 | H50: 2022 | I50: 2023 | J50: 2024 | K50: 2025 | L50: 2026E | M50: 2027E | N50: 2028E | O50: 2029E | P50: 2030E
B51: ELECTRICAL AMERICAS
B52: EV Powertrain Components | G52: 172 | H52: 269 | I52: 318 | J52: 331 | K52: 314 | L52: =G52*1.075 -> 184.9 | M52: =L52*1.125 -> 208.0125 | N52: =M52*1.19 -> 247.53487 | O52: =N52*1.26 -> 311.89394 | P52: =O52*1.28 -> 399.22425 | Q52: Inverters, motors, breakers
B53: Charging Infrastructure | G53: 171 | H53: 269 | I53: 318 | J53: 331 | K53: 314 | L53: =G53*1.075 -> 183.825 | M53: =L53*1.075 -> 197.61187 | N53: =M53*1.115 -> 220.33724 | O53: =N53*1.145 -> 252.28614 | P53: =O53*1.175 -> 296.43622 | Q53: DC fast charging expansion
B54: Total E-Mobility | G54: =SUM(G52:G53) -> 343 | H54: =SUM(H52:H53) -> 538 | I54: =SUM(I52:I53) -> 636 | J54: =SUM(J52:J53) -> 662 | K54: =SUM(K52:K53) -> 628 | L54: =SUM(L52:L53) -> 368.725 | M54: =SUM(M52:M53) -> 405.62437 | N54: =SUM(N52:N53) -> 467.87212 | ... P54: =SUM(P52:P53) -> 695.66046
B55: % YoY Growth | H55: =(H54-G54)/G54 -> 0.56851312 | I55: =(I54-H54)/H54 -> 0.18215613 | J55: =(J54-I54)/I54 -> 0.040880503 | K55: =(K54-J54)/J54 -> -0.051359517 | L55: =(L54-K54)/K54 -> -0.41285828 | M55: =(M54-L54)/L54 -> 0.10007289 | N55: =(N54-M54)/M54 -> 0.15346154 | O55: =(O54-N54)/N54 -> 0.2058425 | P55: =(P54-O54)/O54 -> 0.23304683
B57: Operating Income | G57: -29 | H57: -9 | I57: -21 | J57: -6 | K57: -20 | L57: 0 | M57: =L57*1.5 -> 0 | N57: =M57*3.5 -> 0 | O57: =N57*2.85 -> 0 | P57: =O57*2.1 -> 0
B58: Operating Margin % | G58: =G57/G54 -> -0.084548105 | H58: =H57/H54 -> -0.016728625 | I58: =I57/I54 -> -0.033018868 | J58: =J57/J54 -> -0.0090634441 | K58: =K57/K54 -> -0.031847134 | L58: =L57/L54 -> 0 | M58: =M57/M54 -> 0 | N58: =N57/N54 -> 0 | ... P58: =P57/P54 -> 0
B59: Key Drivers:
B60: • Global EV adoption rate | G60: - | H60: - | I60: - | J60: - | K60: - | L60: 14-16% | M60: 18-20% | N60: 22-25% | O60: 28-32% | P60: 35-40% | Q60: Regulatory mandates accelerating
B61: • Scale/profitability inflection | G61: - | H61: - | I61: - | J61: - | K61: - | L61: 2026E | M61: Margin + | N61: Margin ++ | O61: Margin +++ | P61: Mature | Q61: Investment phase transitioning
A64: x | B64: Total Revenue | G64: 2021 | H64: 2022 | I64: 2023 | J64: 2024 | K64: 2025 | L64: 2026E | M64: 2027E | N64: 2028E | O64: 2029E | P64: 2030E
B66: Electrical Americas | G66: =G15 -> 7242 | H66: =H15 -> 8497 | I66: =I15 -> 10098 | J66: =J15 -> 11436 | K66: =K15 -> 13358.5 | L66: =L15 -> 15025.9 | M66: =M15 -> 16619.5 | N66: =N15 -> 18145 | ... P66: =P15 -> 21262.311
B67: Electrical Global | G67: =G28 -> 5516 | H67: =H28 -> 5848 | I67: =I28 -> 6084 | J67: =J28 -> 6248 | K67: =K28 -> 6780 | L67: =L28 -> 5835.928 | M67: =M28 -> 6317.3921 | N67: =N28 -> 6953.1435 | ... P67: =P28 -> 8417.6393
B68: Aerospace | G68: 2648 | H68: 3039 | I68: 3413 | J68: 3744 | K68: 4220 | L68: =G68*1.127 -> 2984.296 | M68: =L68*1.11 -> 3312.5686 | N68: =M68*1.074 -> 3557.6986 | O68: =N68*1.072 -> 3813.8529 | P68: =O68*1.07 -> 4080.8226
B69: Vehicle | G69: =G40 -> 2579 | H69: =H40 -> 2830 | I69: =I40 -> 2965 | J69: =J40 -> 2790 | K69: =K40 -> 2510 | L69: =L40 -> 2450.05 | M69: =M40 -> 2486.8007 | N69: =N40 -> 2598.7068 | ... P69: =P40 -> 2947.5182
B70: E-Mobility | G70: =G54 -> 343 | H70: =H54 -> 538 | I70: =I54 -> 636 | J70: =J54 -> 662 | K70: =K54 -> 628 | L70: =L54 -> 368.725 | M70: =M54 -> 405.62437 | N70: =N54 -> 467.87212 | ... P70: =P54 -> 695.66046
B71: Total Revenue | G71: =SUM(G66:G70) -> 18328 | H71: =SUM(H66:H70) -> 20752 | I71: =SUM(I66:I70) -> 23196 | J71: =SUM(J66:J70) -> 24880 | K71: =SUM(K66:K70) -> 27496.5 | L71: =SUM(L66:L70) -> 26664.899 | M71: =SUM(M66:M70) -> 29141.886 | N71: =SUM(N66:N70) -> 31722.421 | ... P71: =SUM(P66:P70) -> 37403.952
A73: x | B73: Total Operating Income | G73: 2021 | H73: 2022 | I73: 2023 | J73: 2024 | K73: 2025 | L73: 2026E | M73: 2027E | N73: 2028E | O73: 2029E | P73: 2030E
B75: Electrical Americas | G75: =G18 -> 1495 | H75: =H18 -> 1912 | I75: =I18 -> 2676 | J75: =J18 -> 3454 | K75: =K18 -> 3985.89 | L75: =L18 -> 4512.41 | M75: =M18 -> 5088.5 | N75: =N18 -> 5624.95 | ... P75: =P18 -> 6697.628
B76: Electrical Global | G76: =G31 -> 1034 | H76: =H31 -> 1134 | I76: =I31 -> 1176 | J76: =J31 -> 1150 | K76: =K31 -> 1318 | L76: =L31 -> 1116.72 | M76: =M31 -> 1209.4078 | N76: =N31 -> 1348.4897 | ... P76: =P31 -> 1683.9939
B77: Aerospace | G77: 580 | H77: 706 | I77: 780 | J77: 859 | K77: 1004 | L77: =G76*1.13 -> 1168.42 | M77: =L76*1.13 -> 1261.8936 | N77: =M76*1.098 -> 1327.9297 | O77: =N76*1.087 -> 1465.8083 | P77: =O76*1.08 -> 1631.1331
B78: Vehicle | G78: =G43 -> 449 | H78: =H43 -> 453 | I78: =I43 -> 482 | J78: =J43 -> 503 | K78: =K43 -> 408 | L78: =L43 -> 454.837 | M78: =M43 -> 495.77233 | N78: =N43 -> 540.39184 | ... P78: =P43 -> 676.05181
B79: E-Mobility | G79: =G57 -> -29 | H79: =H57 -> -9 | I79: =I57 -> -21 | J79: =J57 -> -6 | K79: =K57 -> -20 | L79: =L57 -> 0 | M79: =M57 -> 0 | N79: =N57 -> 0 | ... P79: =P57 -> 0
B80: Total Operating Income | G80: =SUM(G75:G79) -> 3529 | H80: =SUM(H75:H79) -> 4196 | I80: =SUM(I75:I79) -> 5093 | J80: =SUM(J75:J79) -> 5960 | K80: =SUM(K75:K79) -> 6695.89 | L80: =SUM(L75:L79) -> 7252.387 | M80: =SUM(M75:M79) -> 8055.5737 | N80: =SUM(N75:N79) -> 8841.7612 | ... P80: =SUM(P75:P79) -> 10688.807

Sheet Extras
