Workbook

Sheet Main
A4: x | B4: Company Overview | W4: 10 Year DCF | Y4: 2032 | Z4: =Y4+1 -> 2033 | AA4: =Z4+1 -> 2034 | AB4: =AA4+1 -> 2035 | AC4: =AB4+1 -> 2036
B6: Price | G6: Key Stats | M6: Valuation | R6: Notes | W6: Revenue | Y6: =P96*1.11 -> 160392.58 | Z6: =Y6*1.1 -> 176431.84 | AA6: =Z6*1.09 -> 192310.71 | AB6: =AA6*1.08 -> 207695.56 | AC6: =AB6*1.07 -> 222234.25
B7: Ticker | E7: INTC | G7: Employees | I7: 85100 | M7: PV of FCF | P7: =SUM(K108:P108) -> 67691.076 | R7: WACC | U7: 0.105 | W7: % growth | Y7: 0.095 | Z7: 0.09 | AA7: 0.085 | AB7: =(AB6-AA6)/AA6 -> 0.08 | AC7: =(AC6-AB6)/AB6 -> 0.07
B8: Implied Share Price | E8: =AVERAGE((P13/P12),(T23)) -> 93.304565 | G8: Founded | I8: 1968 | M8: Terminal Value | P8: =(P49*U8) -> 779654.26 | R8: EV/EBITDA Multiple | U8: 12
B9: Current Share Price | E9: =Extras!N3 -> 123 | G9: CEO | I9: Lip-Bu Tan | M9: PV of Terminal Value | P9: =-(PV(U7,(DATE(2031,12,31)-$E$12)/365,0,P8)) -> 443057.08 | R9: TGR | U9: 0.03
B10: Implied Upside / (Downside) | E10: =E8/E9-1 -> -0.2414263 | G10: Headquarters | I10: Santa Clara, California | M10: Net Debt | P10: =-32789+43027+2004 -> 12242 | W10: Free Cash Flow | Y10: =Y6*0.22 -> 35286.368 | Z10: =Z6*0.23 -> 40579.323 | AA10: =AA6*0.24 -> 46154.569 | AB10: =AB6*0.25 -> 51923.891 | AC10: =AC6*0.25 -> 55558.563
B11: IRR | E11: =(K17/E9)^(1/2)-1 -> -0.043046169 | G11: Primary Industry | I11: Semiconductors | M11: Strategic Investments | P11: =6000+4300 -> 10300 | W11: % of sales | Y11: =P106+0.003 -> 0.24961501 | Z11: =Y11+0.0004 -> 0.25001501 | AA11: =Z11 -> 0.25001501 | AB11: =AA11+0.0004 -> 0.25041501 | AC11: =AB11+0.0004 -> 0.25081501
B12: Last Updated | E12: 46147 | G12: Fiscal Year End | I12: 46387 | M12: Shares Outstanding | P12: 5026
M13: Implied Market Cap | P13: =P9+P7-P10+P11 -> 508806.16 | R13: Share Price | U13: =P13/P12 -> 101.23481 | W13: Present Value of FCF | Y13: =Y10/(1+$U$7)^((DATE(2032,7,1)-$E$12)/365) -> 19073.221 | Z13: =Z10/(1+$U$7)^((DATE(2033,7,1)-$E$12)/365) -> 19849.959 | AA13: =AA10/(1+$U$7)^((DATE(2034,7,1)-$E$12)/365) -> 20431.829 | AB13: =AB10/(1+$U$7)^((DATE(2035,7,1)-$E$12)/365) -> 20801.635 | AC13: =AC10/(1+$U$7)^((DATE(2036,7,1)-$E$12)/365) -> 20137.251
A15: x | B15: Key Statistics | E15: 2021 | F15: =E15+1 -> 2022 | G15: =F15+1 -> 2023 | H15: =G15+1 -> 2024 | I15: =H15+1 -> 2025 | J15: 2026E | K15: 2027E | M15: Financial Ratios | R15: Gordon Growth Method | W15: Probability Weighted | Z15: 46165
M16: PV of FCF | P16: =SUM(J111:N111) -> 0
B17: Stock Price | E17: 51.5 | F17: 26.43 | G17: 50.25 | H17: 20.05 | I17: 36.9 | J17: =AVERAGE($U$13*(1+$U$7)-K105/J18,$T$23*(1+$U$7)-K105/J18) -> 102.74639 | K17: =AVERAGE($U$13*(1+$U$7)^2-(K105/J18)*(1+$U$7)-L105/K18,$T$23*(1+$U$7)^2-(K105/J18)*(1+$U$7)-L105/K18) -> 112.63856 | M17: Market Cap | P17: =E9*P12 -> 618198 | R17: FCF Value | T17: =SUM(K108:P108)+SUM((Y13:AC13)) -> 167984.97 | W17: Bear | X17: 63 | Y17: 0.2 | Z17: 58
B18: shares outstanding | E18: 4059 | F18: 4108 | G18: 4190 | H18: 4280 | I18: 4530 | J18: =K70 -> 5237 | K18: =L70 -> 5446.48 | M18: Enterprise Value | P18: =P17+P10 -> 630440 | R18: Terminal Value | T18: =(AC10*(1+U9)/($U$7-U9))/(1+$U$7)^((DATE(2036,12,31)-$E$12)/365) -> 263048.36 | W18: Base | X18: 103 | Y18: 0.55 | Z18: 93
M19: P/E (LTM) | P19: =$P$17/J67 -> -2315.3483 | R19: Net Debt | T19: =P10 -> 12242 | W19: Bull | X19: 273 | Y19: 0.25 | Z19: 248
B20: Market Cap | E20: =E18*E17 -> 209038.5 | F20: =F18*F17 -> 108574.44 | G20: =G18*G17 -> 210547.5 | H20: =H18*H17 -> 85814 | I20: =I18*I17 -> 167157 | J20: =J17*J18 -> 538082.85 | K20: =K17*K18 -> 613483.65 | M20: P/E (NTM) | P20: =$P$17/K67 -> 177.86086 | R20: Strategic Investments | T20: =P11 -> 10300
B21: Cash | E21: 29253 | F21: 28338 | G21: 25034 | H21: 22062 | I21: 37416 | J21: 30859 | K21: 45000 | M21: EV/EBITDA (LTM) | P21: =P18/(J46+J78) -> 66.418036 | R21: Total | T21: =T17+T18-T19+T20 -> 429091.33 | W21: Total | X21: =SUMPRODUCT(X17:X19,Y17:Y19) -> 137.5 | Z21: =SUMPRODUCT(Z17:Z19,Y17:Y19) -> 124.75
B22: Debt | E22: =33510+4591 -> 38101 | F22: =37684+4367 -> 42051 | G22: =46978+2288 -> 49266 | H22: =46282+3729 -> 50011 | I22: =44086+2499 -> 46585 | J22: =42509+2066 -> 44575 | K22: =J22*1.01 -> 45020.75 | M22: EV/EBITDA (NTM) | P22: =P18/(K46+K78) -> 40.805206 | W22: Current | X22: =E9 -> 123
B23: Enterprise Value | E23: =E20-E21+E22 -> 217886.5 | F23: =F20-F21+F22 -> 122287.44 | G23: =G20-G21+G22 -> 234779.5 | H23: =H20-H21+H22 -> 113763 | I23: =I20-I21+I22 -> 176326 | J23: =J20-J21+J22 -> 551798.85 | K23: =K20-K21+K22 -> 613504.4 | M23: EV/EBIT (LTM) | P23: =P18/J46 -> -284.75158 | R23: Share Price | T23: =T21/P12 -> 85.37432 | W23: Upside | X23: =(X21-X22)/X22 -> 0.11788618
A26: x | B26: Income Statement ($M) | E26: 2020 | F26: 2021 | G26: 2022 | H26: 2023 | I26: 2024 | J26: 2025 | K26: 2026E | L26: 2027E | M26: 2028E | N26: 2029E | O26: 2030E | P26: 2031E | R26: $ mm, except per share | U26: 2026E | V26: 2027E | W26: 2028E | X26: 2029E | Y26: 2030E | Z26: 2031E
B28: Revenue | E28: 77867 | F28: 79024 | G28: 63054 | H28: 54228 | I28: 53101 | J28: 52853 | K28: =Segments!I20 -> 58495.857 | L28: =Segments!J20 -> 74214.818 | M28: =Segments!K20 -> 92740.819 | N28: =Segments!L20 -> 114902.73 | O28: =Segments!M20 -> 131644.53 | P28: =Segments!N20 -> 144497.82 | R28: =B28 -> Revenue | U28: =K28 -> 58495.857 | V28: =L28 -> 74214.818 | W28: =M28 -> 92740.819 | X28: =N28 -> 114902.73 | Y28: =O28 -> 131644.53 | Z28: =P28 -> 144497.82
B29: % growth | F29: =(F28-E28)/E28 -> 0.014858669 | G29: =(G28-F28)/F28 -> -0.2020905 | H29: =(H28-G28)/G28 -> -0.13997526 | I29: =(I28-H28)/H28 -> -0.020782622 | J29: =(J28-I28)/I28 -> -0.0046703452 | K29: =(K28-J28)/J28 -> 0.10676513 | L29: =(L28-K28)/K28 -> 0.2687192 | M29: =(M28-L28)/L28 -> 0.24962671 | ... P29: =(P28-O28)/O28 -> 0.097636347 | R29: Revenue Growth | U29: =K29 -> 0.10676513 | V29: =L29 -> 0.2687192 | W29: =M29 -> 0.24962671 | X29: =N29 -> 0.23896606 | Y29: =O29 -> 0.14570415 | Z29: =P29 -> 0.097636347
R30: =B34 -> Gross Profit | U30: =K34 -> 22228.426 | V30: =L34 -> 30799.149 | W30: =M34 -> 44051.889 | X30: =N34 -> 58600.39 | Y30: =O34 -> 70429.824 | Z30: =P34 -> 79473.802
B31: COGS | E31: 34255 | F31: 35209 | G31: 36188 | H31: 32517 | I31: 35756 | J31: 34478 | K31: =K28*0.62 -> 36267.432 | L31: =L28*0.585 -> 43415.668 | M31: =M28*0.525 -> 48688.93 | N31: =N28*0.49 -> 56302.336 | O31: =O28*0.465 -> 61214.707 | P31: =P28*0.45 -> 65024.02 | R31: Gross Margin | U31: =K35 -> 0.38 | V31: =L35 -> 0.415 | W31: =M35 -> 0.475 | X31: =N35 -> 0.51 | Y31: =O35 -> 0.535 | Z31: =P35 -> 0.55
B32: % of sales | E32: =E31/E28 -> 0.43991678 | F32: =F31/F28 -> 0.44554819 | G32: =G31/G28 -> 0.57392077 | H32: =H31/H28 -> 0.59963487 | I32: =I31/I28 -> 0.67335832 | J32: =J31/J28 -> 0.65233762 | K32: =K31/K28 -> 0.62 | L32: =L31/L28 -> 0.585 | ... P32: =P31/P28 -> 0.45 | R32: EBITDA | U32: =K49 -> 15449.989 | V32: =L49 -> 21720.518 | W32: =M49 -> 31100.006 | X32: =N49 -> 44484.956 | Y32: =O49 -> 56181.4 | Z32: =P49 -> 64971.189
R33: EBITDA Margin | U33: =K50 -> 0.26412109 | V33: =L50 -> 0.29267091 | W33: =M50 -> 0.33534323 | X33: =N50 -> 0.38715318 | Y33: =O50 -> 0.42676592 | Z33: =P50 -> 0.44963438
B34: Gross Profit | E34: =E28-E31 -> 43612 | F34: =F28-F31 -> 43815 | G34: =G28-G31 -> 26866 | H34: =H28-H31 -> 21711 | I34: =I28-I31 -> 17345 | J34: =J28-J31 -> 18375 | K34: =K28-K31 -> 22228.426 | L34: =L28-L31 -> 30799.149 | ... P34: =P28-P31 -> 79473.802 | R34: Operating Income | U34: =K46 -> 3657.2246 | V34: =L46 -> 7827.5043 | W34: =M46 -> 16029.623 | X34: =N46 -> 29317.796 | Y34: =O46 -> 40384.056 | Z34: =P46 -> 49365.424
B35: % of sales | E35: =E34/E28 -> 0.56008322 | F35: =F34/F28 -> 0.55445181 | G35: =G34/G28 -> 0.42607923 | H35: =H34/H28 -> 0.40036513 | I35: =I34/I28 -> 0.32664168 | J35: =J34/J28 -> 0.34766238 | K35: =K34/K28 -> 0.38 | L35: =L34/L28 -> 0.415 | ... P35: =P34/P28 -> 0.55 | R35: EBIT Margin | U35: =K47 -> 0.062521086 | V35: =L47 -> 0.10547091 | W35: =M47 -> 0.17284323 | X35: =N47 -> 0.25515318 | Y35: =O47 -> 0.30676592 | Z35: =P47 -> 0.34163438
R36: =B67 -> Net Income | U36: =K67 -> 3475.7394 | V36: =L67 -> 7108.8182 | W36: =M67 -> 14187.825 | X36: =N67 -> 25558.675 | Y36: =O67 -> 34843.503 | Z36: =P67 -> 41960.61
B37: Research & Development | E37: 13556 | F37: 15190 | G37: 17528 | H37: 16046 | I37: 16546 | J37: 13774 | K37: =K34-K40-N(K43)-K46 -> 13482.062 | L37: =L34-N(L43)-L46-L40 -> 18251.583 | M37: =M34-N(M43)-M46-M40 -> 22439.269 | N37: =N34-N(N43)-N46-N40 -> 22756.119 | O37: =O34-N(O43)-O46-O40 -> 23015.95 | P37: =P34-N(P43)-P46-P40 -> 22883.487 | R37: Net Margin | U37: =K68 -> 0.059418556 | V37: =L68 -> 0.095787046 | W37: =M68 -> 0.15298361 | X37: =N68 -> 0.2224375 | Y37: =O68 -> 0.2646787 | Z37: =P68 -> 0.29038922
B38: % of sales | E38: =E37/E$28 -> 0.17409172 | F38: =F37/F$28 -> 0.19222009 | G38: =G37/G$28 -> 0.27798395 | H38: =H37/H$28 -> 0.2958988 | I38: =I37/I$28 -> 0.31159489 | J38: =J37/J$28 -> 0.26060962 | K38: =K37/K$28 -> 0.23047891 | L38: =L37/L$28 -> 0.24592909 | ... P38: =P37/P$28 -> 0.15836562 | R38: Shares Outstanding | U38: =K70 -> 5237 | V38: =L70 -> 5446.48 | W38: =M70 -> 5555.4096 | X38: =N70 -> 5666.5178 | Y38: =O70 -> 5779.8481 | Z38: =P70 -> 5895.4451
R39: EPS | U39: =K73 -> 0.66368902 | V39: =L73 -> 1.3052133 | W39: =M73 -> 2.5538756 | X39: =N73 -> 4.510473 | Y39: =O73 -> 6.028446 | Z39: =P73 -> 7.1174626
B40: SG&A | E40: 6180 | F40: 6543 | G40: 7002 | H40: 5634 | I40: 5507 | J40: 4624 | K40: =K28*K41 -> 3919.2225 | L40: =L28*L41 -> 4720.0624 | M40: =M28*M41 -> 5582.9973 | N40: =N28*N41 -> 6526.4748 | O40: =O28*O41 -> 7029.8179 | P40: =P28*P41 -> 7224.8911 | R40: EPS Growth | U40: N/A | V40: =L74 -> 0.96660374 | W40: =M74 -> 0.95667299 | X40: =N74 -> 0.76612868 | Y40: =O74 -> 0.3365441 | Z40: =P74 -> 0.18064632
B41: % of sales | E41: =E40/E$28 -> 0.079366099 | F41: =F40/F$28 -> 0.082797631 | G41: =G40/G$28 -> 0.11104767 | H41: =H40/H$28 -> 0.10389467 | I41: =I40/I$28 -> 0.10370803 | J41: =J40/J$28 -> 0.087487938 | K41: 0.067 | L41: =$K$41+($P$41-$K$41)*(COLUMNS($K$41:L41)-1)/(COLUMNS($K$41:$P$41)-1) -> 0.0636 | M41: =$K$41+($P$41-$K$41)*(COLUMNS($K$41:M41)-1)/(COLUMNS($K$41:$P$41)-1) -> 0.0602 | N41: =$K$41+($P$41-$K$41)*(COLUMNS($K$41:N41)-1)/(COLUMNS($K$41:$P$41)-1) -> 0.0568 | O41: =$K$41+($P$41-$K$41)*(COLUMNS($K$41:O41)-1)/(COLUMNS($K$41:$P$41)-1) -> 0.0534 | P41: 0.05 | R41: Free Cash Flow | U41: =K105 -> 1859.9427 | V41: =L105 -> 4881.154 | W41: =M105 -> 9482.0986 | X41: =N105 -> 19127.583 | Y41: =O105 -> 28210.333 | Z41: =P105 -> 35635.331
R42: FCF Margin | U42: =K106 -> 0.031796144 | V42: =L106 -> 0.065770612 | W42: =M106 -> 0.10224299 | X42: =N106 -> 0.16646762 | Y42: =O106 -> 0.21429172 | Z42: =P106 -> 0.24661501
B43: Restructuring and Other Changes | E43: 198 | F43: 2626 | G43: 2 | H43: -62 | I43: 6970 | J43: 2191 | K43: =K28*0.02 -> 1169.9171 | L43: 0 | M43: 0 | N43: 0 | O43: 0 | P43: 0 | R43: CapEx | U43: =K81 -> 16378.84 | V43: =L81 -> 19295.853 | W43: =M81 -> 23185.205 | X43: =N81 -> 25278.6 | Y43: =O81 -> 26328.906 | Z43: =P81 -> 26009.608
B44: % of sales | E44: =E43/E$28 -> 0.0025427973 | F44: =F43/F$28 -> 0.033230411 | G44: =G43/G$28 -> 3.1718844e-05 | H44: =H43/H$28 -> -0.0011433208 | I44: =I43/I$28 -> 0.1312593 | J44: =J43/J$28 -> 0.0414546 | K44: =K43/K$28 -> 0.02 | L44: =L43/L$28 -> 0 | ... P44: =P43/P$28 -> 0 | R44: CapEx % of Sales | U44: =K103 -> 0.28 | V44: =L103 -> 0.26 | W44: =M103 -> 0.25 | X44: =N103 -> 0.22 | Y44: =O103 -> 0.2 | Z44: =P103 -> 0.18
B46: Operating Income (EBIT) | E46: =E34-E37-E40-E43 -> 23678 | F46: =F34-F37-F40-F43 -> 19456 | G46: =G34-G37-G40-G43 -> 2334 | H46: =H34-H37-H40-H43 -> 93 | I46: =I34-I37-I40-I43 -> -11678 | J46: =J34-J37-J40-J43 -> -2214 | K46: =Segments!I57 -> 3657.2246 | L46: =Segments!J57 -> 7827.5043 | M46: =Segments!K57 -> 16029.623 | N46: =Segments!L57 -> 29317.796 | O46: =Segments!M57 -> 40384.056 | P46: =Segments!N57 -> 49365.424
B47: % of sales | E47: =E46/E$28 -> 0.3040826 | F47: =F46/F$28 -> 0.24620368 | G47: =G46/G$28 -> 0.037015891 | H47: =H46/H$28 -> 0.0017149812 | I47: =I46/I$28 -> -0.21992053 | J47: =J46/J$28 -> -0.04188977 | K47: =K46/K$28 -> 0.062521086 | L47: =L46/L$28 -> 0.10547091 | ... P47: =P46/P$28 -> 0.34163438
B49: EBITDA | E49: =E46+E78 -> 35917 | F49: =F46+F78 -> 31248 | G49: =G46+G78 -> 15369 | H49: =H46+H78 -> 9695 | I49: =I46+I78 -> -299 | J49: =J46+J78 -> 9492 | K49: =K46+K78 -> 15449.989 | L49: =L46+L78 -> 21720.518 | ... P49: =P46+P78 -> 64971.189
B50: % of sales | E50: =E49/E$28 -> 0.46126087 | F50: =F49/F$28 -> 0.39542417 | G50: =G49/G$28 -> 0.24374346 | H50: =H49/H$28 -> 0.17878218 | I50: =I49/I$28 -> -0.0056307791 | J50: =J49/J$28 -> 0.17959245 | K50: =K49/K$28 -> 0.26412109 | L50: =L49/L$28 -> 0.29267091 | ... P50: =P49/P$28 -> 0.44963438
B52: Gains on Equity Investments | E52: 1904 | F52: 2729 | G52: 4268 | H52: 40 | I52: 242 | J52: 514 | K52: 0 | L52: 0 | M52: 0 | N52: 0 | O52: 0 | P52: 0
B53: % of sales | E53: =E52/E$28 -> 0.02445195 | F53: =F52/F$28 -> 0.034533813 | G53: =G52/G$28 -> 0.067688013 | H53: =H52/H$28 -> 0.00073762632 | I53: =I52/I$28 -> 0.004557353 | J53: =J52/J$28 -> 0.0097250866 | K53: =K52/K$28 -> 0 | L53: =L52/L$28 -> 0 | ... P53: =P52/P$28 -> 0
B55: Interest Income | E55: -504 | F55: -482 | G55: 1166 | H55: 629 | I55: 226 | J55: 3257 | K55: =K28*0.005 -> 292.47929 | L55: =L28*0.004 -> 296.85927 | M55: =M28*0.003 -> 278.22246 | N55: =N28*0.002 -> 229.80545 | O55: =O28*0.001 -> 131.64453 | P55: 0
B56: % of sales | E56: =E55/E$28 -> -0.006472575 | F56: =F55/F$28 -> -0.0060994128 | G56: =G55/G$28 -> 0.018492086 | H56: =H55/H$28 -> 0.011599174 | I56: =I55/I$28 -> 0.0042560404 | J56: =J55/J$28 -> 0.061623749 | K56: =K55/K$28 -> 0.005 | L56: =L55/L$28 -> 0.004 | ... P56: =P55/P$28 -> 0
B58: Pre-Tax Income | E58: =E46+E52+E55 -> 25078 | F58: =F46+F52+F55 -> 21703 | G58: =G46+G52+G55 -> 7768 | H58: =H46+H52+H55 -> 762 | I58: =I46+I52+I55 -> -11210 | J58: =J46+J52+J55 -> 1557 | K58: =K46+K52+K55 -> 3949.7038 | L58: =L46+L52+L55 -> 8124.3636 | ... P58: =P46+P52+P55 -> 49365.424
B59: % of sales | E59: =E58/E$28 -> 0.32206198 | F59: =F58/F$28 -> 0.27463808 | G59: =G58/G$28 -> 0.12319599 | H59: =H58/H$28 -> 0.014051781 | I59: =I58/I$28 -> -0.21110714 | J59: =J58/J$28 -> 0.029459066 | K59: =K58/K$28 -> 0.067521086 | L59: =L58/L$28 -> 0.10947091 | ... P59: =P58/P$28 -> 0.34163438
B61: Tax Expense | E61: 4179 | F61: 1835 | G61: -249 | H61: -913 | I61: 8023 | J61: 1531 | K61: =K58*0.12 -> 473.96446 | L61: =L58*0.125 -> 1015.5455 | M61: =M58*0.13 -> 2120.0198 | N61: =N58*0.135 -> 3988.9262 | O61: =O58*0.14 -> 5672.1981 | P61: =P58*0.15 -> 7404.8136
B62: Tax Rate % | E62: =E61/E58 -> 0.16664008 | F62: =F61/F58 -> 0.084550523 | G62: =G61/G58 -> -0.032054583 | H62: =H61/H58 -> -1.1981627 | I62: =I61/I58 -> -0.71570027 | J62: =J61/J58 -> 0.98330122 | K62: =K61/K58 -> 0.12 | L62: =L61/L58 -> 0.125 | ... P62: =P61/P58 -> 0.15
B64: Non Controlling Stake Income | E64: 0 | F64: 0 | G64: 3 | H64: -14 | I64: -477 | J64: 293 | K64: 0 | L64: 0 | M64: 0 | N64: 0 | O64: 0 | P64: 0
B65: Tax Rate % | E65: =E64/E$28 -> 0 | F65: =F64/F$28 -> 0 | G65: =G64/G$28 -> 4.7578266e-05 | H65: =H64/H$28 -> -0.00025816921 | I65: =I64/I$28 -> -0.0089828817 | J65: =J64/J$28 -> 0.0055436777 | K65: =K64/K$28 -> 0 | L65: =L64/L$28 -> 0 | ... P65: =P64/P$28 -> 0
B67: Net Income | E67: =E58-E61-E64 -> 20899 | F67: =F58-F61-F64 -> 19868 | G67: =G58-G61-G64 -> 8014 | H67: =H58-H61-H64 -> 1689 | I67: =I58-I61-I64 -> -18756 | J67: =J58-J61-J64 -> -267 | K67: =K58-K61-K64 -> 3475.7394 | L67: =L58-L61-L64 -> 7108.8182 | ... P67: =P58-P61-P64 -> 41960.61
B68: % of sales | E68: =E67/E$28 -> 0.26839354 | F68: =F67/F$28 -> 0.25141729 | G68: =G67/G$28 -> 0.12709741 | H68: =H67/H$28 -> 0.031146271 | I68: =I67/I$28 -> -0.35321369 | J68: =J67/J$28 -> -0.0050517473 | K68: =K67/K$28 -> 0.059418556 | L68: =L67/L$28 -> 0.095787046 | ... P68: =P67/P$28 -> 0.29038922
B70: Shares Outstanding | E70: 4199 | F70: 4059 | G70: 4108 | H70: 4190 | I70: 4280 | J70: 4530 | K70: 5237 | L70: =K70*1.04 -> 5446.48 | M70: =L70*1.02 -> 5555.4096 | N70: =M70*1.02 -> 5666.5178 | O70: =N70*1.02 -> 5779.8481 | P70: =O70*1.02 -> 5895.4451
B71: % growth | F71: =(F70-E70)/E70 -> -0.033341272 | G71: =(G70-F70)/F70 -> 0.012071939 | H71: =(H70-G70)/G70 -> 0.019961052 | I71: =(I70-H70)/H70 -> 0.021479714 | J71: =(J70-I70)/I70 -> 0.058411215 | K71: =(K70-J70)/J70 -> 0.15607064 | L71: =(L70-K70)/K70 -> 0.04 | M71: =(M70-L70)/L70 -> 0.02 | ... P71: =(P70-O70)/O70 -> 0.02
B73: EPS | E73: =E67/E70 -> 4.9771374 | F73: =F67/F70 -> 4.8948017 | G73: =G67/G70 -> 1.9508277 | H73: =H67/H70 -> 0.40310263 | I73: =I67/I70 -> -4.382243 | J73: =J67/J70 -> -0.058940397 | K73: =K67/K70 -> 0.66368902 | L73: =L67/L70 -> 1.3052133 | ... P73: =P67/P70 -> 7.1174626
B74: % growth | F74: =(F73-E73)/E73 -> -0.01654279 | G74: =(G73-F73)/F73 -> -0.60144909 | H74: =(H73-G73)/G73 -> -0.79336841 | I74: =(I73-H73)/H73 -> -11.871284 | J74: =(J73-I73)/I73 -> -0.98655018 | K74: =(-K73-J73)/J73 -> 10.260342 | L74: =(L73-K73)/K73 -> 0.96660374 | M74: =(M73-L73)/L73 -> 0.95667299 | N74: =(N73-M73)/M73 -> 0.76612868 | O74: =(O73-N73)/N73 -> 0.3365441 | P74: =(P73-O73)/O73 -> 0.18064632
A76: x | B76: Cash Flow Items | E76: 2020 | F76: 2021 | G76: 2022 | H76: 2023 | I76: 2024 | J76: 2025 | K76: 2026E | L76: 2027E | M76: 2028E | N76: 2029E | O76: 2030E | P76: 2031E
B77: % of sales
B78: D&A | E78: 12239 | F78: 11792 | G78: 13035 | H78: 9602 | I78: 11379 | J78: 11706 | K78: =K81*0.72 -> 11792.765 | L78: =L81*0.72 -> 13893.014 | M78: =M81*0.65 -> 15070.383 | N78: =N81*0.6 -> 15167.16 | O78: =O81*0.6 -> 15797.344 | P78: =P81*0.6 -> 15605.765
B79: % of capex | E79: =E78/E81 -> 0.85839529 | F79: =F78/F81 -> 0.62947739 | G79: =G78/G81 -> 0.52494865 | H79: =H78/H81 -> 0.3728932 | I79: =I78/I81 -> 0.47523388 | J79: =J78/J81 -> 0.80931969 | K79: =K78/K81 -> 0.72 | L79: =L78/L81 -> 0.72 | ... P79: =P78/P81 -> 0.6
B81: CapEx | E81: 14258 | F81: 18733 | G81: 24831 | H81: 25750 | I81: 23944 | J81: 14464 | K81: =K28*0.28 -> 16378.84 | L81: =L28*0.26 -> 19295.853 | M81: =M28*0.25 -> 23185.205 | N81: =N28*0.22 -> 25278.6 | O81: =O28*0.2 -> 26328.906 | P81: =P28*0.18 -> 26009.608
B82: % of sales | E82: =E81/E28 -> 0.18310709 | F82: =F81/F28 -> 0.23705457 | G82: =G81/G28 -> 0.39380531 | H82: =H81/H28 -> 0.47484694 | I82: =I81/I28 -> 0.4509143 | J82: =J81/J28 -> 0.27366469 | K82: =K81/K28 -> 0.28 | L82: =L81/L28 -> 0.26 | ... P82: =P81/P28 -> 0.18
B83: % of ocf
B85: Change in NWC | E85: 1192 | F85: -1498 | G85: -4351 | H85: -569 | I85: 1103 | J85: -1747 | K85: =K28*0.01 -> 584.95857 | L85: =L28*0.01 -> 742.14818 | M85: =M28*0.01 -> 927.40819 | N85: =N28*0.01 -> 1149.0273 | O85: =O28*0.01 -> 1316.4453 | P85: =P28*0.01 -> 1444.9782
B86: % of sales | E86: =E85/E28 -> 0.015308154 | F86: =F85/F28 -> -0.018956266 | G86: =G85/G28 -> -0.069004345 | H86: =H85/H28 -> -0.010492734 | I86: =I85/I28 -> 0.020771737 | J86: =J85/J28 -> -0.033053942 | K86: =K85/K28 -> 0.01 | L86: =L85/L28 -> 0.01 | ... P86: =P85/P28 -> 0.01
B87: % of changes in sales
B89: Stock Based Compensation | E89: 1911 | F89: 2143 | G89: 3071 | H89: 3229 | I89: 3410 | J89: 2434 | K89: =J89*0.98 -> 2385.32 | L89: =K89*1.02 -> 2433.0264 | M89: =L89*1.02 -> 2481.6869 | N89: =M89*1.02 -> 2531.3207 | O89: =N89*1.02 -> 2581.9471 | P89: =O89*1.02 -> 2633.586
B90: % of sales | E90: =E89/E28 -> 0.024541847 | F90: =F89/F28 -> 0.027118344 | G90: =G89/G28 -> 0.048704285 | H90: =H89/H28 -> 0.059544885 | I90: =I89/I28 -> 0.064217246 | J90: =J89/J28 -> 0.046052258 | K90: =K89/K28 -> 0.040777588 | L90: =L89/L28 -> 0.032783566 | ... P90: =P89/P28 -> 0.018225784
B92: Cash Flow from Operations | E92: =E67+E78+E85+E89 -> 36241 | F92: =F67+F78+F85+F89 -> 32305 | G92: =G67+G78+G85+G89 -> 19769 | H92: =H67+H78+H85+H89 -> 13951 | I92: =I67+I78+I85+I89 -> -2864 | J92: =J67+J78+J85+J89 -> 12126 | K92: =K67+K78+K85+K89 -> 18238.783 | L92: =L67+L78+L85+L89 -> 24177.007 | ... P92: =P67+P78+P85+P89 -> 61644.939
A94: x | B94: DCF | E94: 2020 | F94: 2021 | G94: 2022 | H94: 2023 | I94: 2024 | J94: 2025 | K94: 2026E | L94: 2027E | M94: 2028E | N94: 2029E | O94: 2030E | P94: 2031E
B95: % growth
B96: Revenue | E96: =E28 -> 77867 | F96: =F28 -> 79024 | G96: =G28 -> 63054 | H96: =H28 -> 54228 | I96: =I28 -> 53101 | J96: =J28 -> 52853 | K96: =K28 -> 58495.857 | L96: =L28 -> 74214.818 | ... P96: =P28 -> 144497.82
B97: % growth | F97: =(F96-E96)/E96 -> 0.014858669 | G97: =(G96-F96)/F96 -> -0.2020905 | H97: =(H96-G96)/G96 -> -0.13997526 | I97: =(I96-H96)/H96 -> -0.020782622 | J97: =(J96-I96)/I96 -> -0.0046703452 | K97: =(K96-J96)/J96 -> 0.10676513 | L97: =(L96-K96)/K96 -> 0.2687192 | M97: =(M96-L96)/L96 -> 0.24962671 | ... P97: =(P96-O96)/O96 -> 0.097636347
B99: Operating Cash Flow | E99: =E92 -> 36241 | F99: =F92 -> 32305 | G99: =G92 -> 19769 | H99: =H92 -> 13951 | I99: =I92 -> -2864 | J99: =J92 -> 12126 | K99: =K92 -> 18238.783 | L99: =L92 -> 24177.007 | ... P99: =P92 -> 61644.939
B100: % of sales | E100: =E99/E96 -> 0.46542181 | F100: =F99/F96 -> 0.40879986 | G100: =G99/G96 -> 0.31352492 | H100: =H99/H96 -> 0.25726562 | I100: =I99/I96 -> -0.053934954 | J100: =J99/J96 -> 0.22942879 | K100: =K99/K96 -> 0.31179614 | L100: =L99/L96 -> 0.32577061 | ... P100: =P99/P96 -> 0.42661501
B102: CapEx | E102: =E81 -> 14258 | F102: =F81 -> 18733 | G102: =G81 -> 24831 | H102: =H81 -> 25750 | I102: =I81 -> 23944 | J102: =J81 -> 14464 | K102: =K81 -> 16378.84 | L102: =L81 -> 19295.853 | ... P102: =P81 -> 26009.608
B103: % of sales | E103: =E102/E96 -> 0.18310709 | F103: =F102/F96 -> 0.23705457 | G103: =G102/G96 -> 0.39380531 | H103: =H102/H96 -> 0.47484694 | I103: =I102/I96 -> 0.4509143 | J103: =J102/J96 -> 0.27366469 | K103: =K102/K96 -> 0.28 | L103: =L102/L96 -> 0.26 | ... P103: =P102/P96 -> 0.18
B105: Free Cash Flow | E105: =E99-E102 -> 21983 | F105: =F99-F102 -> 13572 | G105: =G99-G102 -> -5062 | H105: =H99-H102 -> -11799 | I105: =I99-I102 -> -26808 | J105: =J99-J102 -> -2338 | K105: =K99-K102 -> 1859.9427 | L105: =L99-L102 -> 4881.154 | ... P105: =P99-P102 -> 35635.331
B106: % of sales | E106: =E105/E96 -> 0.28231472 | F106: =F105/F96 -> 0.17174529 | G106: =G105/G96 -> -0.080280395 | H106: =H105/H96 -> -0.21758132 | I106: =I105/I96 -> -0.50484925 | J106: =J105/J96 -> -0.0442359 | K106: =K105/K96 -> 0.031796144 | L106: =L105/L96 -> 0.065770612 | ... P106: =P105/P96 -> 0.24661501
B108: Present Value of FCF | K108: =K105/(1+$U$7)^((DATE(2026,7,1)-$E$12)/365) -> 1831.1669 | L108: =L105/(1+$U$7)^((DATE(2027,7,1)-$E$12)/365) -> 4348.9918 | M108: =M105/(1+$U$7)^((DATE(2028,7,1)-$E$12)/365) -> 7643.4507 | N108: =N105/(1+$U$7)^((DATE(2029,7,1)-$E$12)/365) -> 13953.489 | O108: =O105/(1+$U$7)^((DATE(2030,7,1)-$E$12)/365) -> 18623.815 | P108: =P105/(1+$U$7)^((DATE(2031,7,1)-$E$12)/365) -> 21290.162
A110: x | B110: Per Share | E110: 2020 | F110: 2021 | G110: =F110+1 -> 2022 | H110: =G110+1 -> 2023 | I110: =H110+1 -> 2024 | J110: =I110+1 -> 2025 | K110: 2026E | L110: 2027E | M110: 2028E | N110: 2029E | O110: 2030E | P110: 2031E
B112: EPS | E112: =E73 -> 4.9771374 | F112: =F73 -> 4.8948017 | G112: =G73 -> 1.9508277 | H112: =H73 -> 0.40310263 | I112: =I73 -> -4.382243 | J112: =J73 -> -0.058940397 | K112: =K73 -> 0.66368902 | L112: =L73 -> 1.3052133 | ... P112: =P73 -> 7.1174626
B113: % change | F113: =(F112-E112)/E112 -> -0.01654279 | G113: =(G112-F112)/F112 -> -0.60144909 | H113: =(H112-G112)/G112 -> -0.79336841 | I113: =(I112-H112)/H112 -> -11.871284 | J113: =(J112-I112)/I112 -> -0.98655018 | K113: =(K112-J112)/J112 -> -12.260342 | L113: =(L112-K112)/K112 -> 0.96660374 | M113: =(M112-L112)/L112 -> 0.95667299 | ... P113: =(P112-O112)/O112 -> 0.18064632
B115: Shares Outstanding | E115: 4199 | F115: =E18 -> 4059 | G115: =F18 -> 4108 | H115: =G18 -> 4190 | I115: =H18 -> 4280 | J115: =I18 -> 4530 | K115: =K70 -> 5237 | L115: =L70 -> 5446.48 | M115: =M70 -> 5555.4096 | N115: =N70 -> 5666.5178 | O115: =O70 -> 5779.8481 | P115: =P70 -> 5895.4451
B116: % change | F116: =(F115-E115)/E115 -> -0.033341272 | G116: =(G115-F115)/F115 -> 0.012071939 | H116: =(H115-G115)/G115 -> 0.019961052 | I116: =(I115-H115)/H115 -> 0.021479714 | J116: =(J115-I115)/I115 -> 0.058411215 | K116: =(K115-J115)/J115 -> 0.15607064 | L116: =(L115-K115)/K115 -> 0.04 | M116: =(M115-L115)/L115 -> 0.02 | ... P116: =(P115-O115)/O115 -> 0.02
B118: P/E | F118: =E17/F112 -> 10.521366 | G118: =F17/G112 -> 13.548096 | H118: =G17/H112 -> 124.65808 | I118: =H17/I112 -> -4.5752826 | J118: =I17/J112 -> -626.05618 | K118: =$E$9/K112 -> 185.32776 | L118: =$E$9/L112 -> 94.23747 | M118: =$E$9/M112 -> 48.162095 | N118: =$E$9/N112 -> 27.269867 | O118: =$E$9/O112 -> 20.403268 | P118: =$E$9/P112 -> 17.28144
B119: P/EBIT | F119: =E17*F115/F46 -> 10.744166 | G119: =F17*G115/G46 -> 46.518612 | H119: =G17*H115/H46 -> 2263.9516 | I119: =H17*I115/I46 -> -7.3483473 | J119: =I17*J115/J46 -> -75.5 | K119: =$E$9*K115/K46 -> 176.1311 | L119: =$E$9*L115/L46 -> 85.58501 | M119: =$E$9*M115/M46 -> 42.628289 | N119: =$E$9*N115/N46 -> 23.773332 | O119: =$E$9*O115/O46 -> 17.60401 | P119: =$E$9*P115/P46 -> 14.689224
B120: P/EBITDA | F120: =E17*F115/(F46+F78) -> 6.6896601 | G120: =F17*G115/(G46+G78) -> 7.0645091 | H120: =G17*H115/(H46+H78) -> 21.717122 | I120: =H17*I115/(I46+I78) -> -287.00334 | J120: =I17*J115/(J46+J78) -> 17.610303 | K120: =$E$9*K115/(K46+K78) -> 41.69265 | L120: =$E$9*L115/(L46+L78) -> 30.84259 | M120: =$E$9*M115/(M46+M78) -> 21.971552 | N120: =$E$9*N115/(N46+N78) -> 15.667807 | O120: =$E$9*O115/(O46+O78) -> 12.654034 | P120: =$E$9*P115/(P46+P78) -> 11.160943
B121: P/S | F121: =E17*F115/F28 -> 2.6452533 | G121: =F17*G115/G28 -> 1.7219279 | H121: =G17*H115/H28 -> 3.8826344 | I121: =H17*I115/I28 -> 1.6160524 | J121: =I17*J115/J28 -> 3.1626776 | K121: =$E$9*K115/K28 -> 11.011908 | L121: =$E$9*L115/L28 -> 9.0267289 | M121: =$E$9*M115/M28 -> 7.3680111 | N121: =$E$9*N115/N28 -> 6.0658412 | O121: =$E$9*O115/O28 -> 5.4003104 | P121: =$E$9*P115/P28 -> 5.0183438
B122: P/FCF | F122: =E17*F115/F105 -> 15.402188 | G122: =F17*G115/G105 -> -21.448921 | H122: =G17*H115/H105 -> -17.844521 | I122: =H17*I115/I105 -> -3.2010594 | J122: =I17*J115/J105 -> -71.495723 | K122: =$E$9*K115/K105 -> 346.32841 | L122: =$E$9*L115/L105 -> 137.24563 | M122: =$E$9*M115/M105 -> 72.063729 | N122: =$E$9*N115/N105 -> 36.438565 | O122: =$E$9*O115/O105 -> 25.200742 | P122: =$E$9*P115/P105 -> 20.348899
B123: P/OCF | F123: =E17*F115/F99 -> 6.4707785 | G123: =F17*G115/G99 -> 5.4921564 | H123: =G17*H115/H99 -> 15.091929 | I123: =H17*I115/I99 -> -29.962989 | J123: =I17*J115/J99 -> 13.785007 | K123: =$E$9*K115/K99 -> 35.317653 | L123: =$E$9*L115/L99 -> 27.70885 | M123: =$E$9*M115/M99 -> 20.91741 | N123: =$E$9*N115/N99 -> 15.6956 | O123: =$E$9*O115/O99 -> 13.035043 | P123: =$E$9*P115/P99 -> 11.763168

Sheet Segments
K2: all values in millions except per share numbers
A4: x | B4: Levers | D4: 2026 | E4: 2031 | I4: 2026 | J4: 2031
B6: GPU/XPU Units | D6: 13 | E6: 50 | G6: Usable Capacity % | I6: 0.5 | J6: 0.85 | L6: ASIC Probability 2028 | N6: 0.2
B7: CPU Attach | D7: 0.25 | E7: 1 | G7: Foundry Rev / Wafer | I7: 22 | J7: 28 | L7: ASIC Probability 2031 | N7: 0.4
B8: Intel AI Share | D8: 0.35 | E8: 0.3 | G8: Internal Foundry Rev | I8: 18500 | J8: 25000
B9: AI CPU ASP | D9: 2000 | E9: 3000 | G9: EMIB / Packaging Rev | I9: 2000 | J9: 12000
B10: Good Dies / Wafer Eq. | D10: 80 | E10: 130 | G10: TeraFab Gross Rev | I10: 0 | J10: 8000
B12: TeraFab Probability | D12: 0.4 | E12: 0.4 | G12: Foundry Margin | I12: -0.4 | J12: 0.25
B13: ZAM Gross Rev (2029) | D13: 500 | E13: 5000 | G13: CCG Growth | I13: -0.01 | J13: 0.03
B14: HBM/ZAM Probability | D14: 0.2 | E14: 0.2 | G14: Non-AI DCAI Growth | I14: 0.05 | J14: 0.03
B15: CCG Margin | D15: 0.3 | E15: 0.35 | G15: ASIC Rev/Wafer (2028) | I15: 50 | J15: 100
B16: DCAI Margin | D16: 0.3 | E16: 0.35 | G16: ASIC Margin | I16: 0.1 | J16: 0.35
A18: x | B18: Product Segments ($M) | F18: 2023 | G18: 2024 | H18: 2025 | I18: 2026E | J18: 2027E | K18: 2028E | L18: 2029E | M18: 2030E | N18: 2031E
B20: Revenue | F20: =SUM(F23+F38+F50+F53) -> 54228 | G20: =SUM(G23+G38+G50+G53) -> 53101 | H20: =SUM(H23+H38+H50+H53) -> 52853 | I20: =I23+I38+I50+I53 -> 58495.857 | J20: =J23+J38+J50+J53 -> 74214.818 | K20: =K23+K38+K50+K53 -> 92740.819 | L20: =L23+L38+L50+L53 -> 114902.73 | M20: =M23+M38+M50+M53 -> 131644.53 | N20: =N23+N38+N50+N53 -> 144497.82
B21: % growth | F21: =(F20-63054)/63054 -> -0.13997526 | G21: =(G20-F20)/F20 -> -0.020782622 | H21: =(H20-G20)/G20 -> -0.0046703452 | I21: =(I20-H20)/H20 -> 0.10676513 | J21: =(J20-I20)/I20 -> 0.2687192 | K21: =(K20-J20)/J20 -> 0.24962671 | L21: =(L20-K20)/K20 -> 0.23896606 | M21: =(M20-L20)/L20 -> 0.14570415 | N21: =(N20-M20)/M20 -> 0.097636347
B23: Intel Products | F23: =F26+F29 -> 48285 | G23: =G26+G29 -> 49471 | H23: =H26+H29 -> 49147 | I23: =I26+I29 -> 51945.67 | J23: =J26+J29 -> 57862.134 | K23: =K26+K29 -> 67527.819 | L23: =L26+L29 -> 81405.333 | M23: =M26+M29 -> 92866.935 | N23: =N26+N29 -> 101976.39
B24: % growth | G24: =(G23-F23)/F23 -> 0.024562494 | H24: =(H23-G23)/G23 -> -0.0065492915 | I24: =(I23-H23)/H23 -> 0.05694488 | J24: =(J23-I23)/I23 -> 0.11389715 | K24: =(K23-J23)/J23 -> 0.16704681 | L24: =(L23-K23)/K23 -> 0.20550811 | M24: =(M23-L23)/L23 -> 0.1407967 | N24: =(N23-M23)/M23 -> 0.098091496
B26: Client Computing | F26: 32305 | G26: 33346 | H26: 32228 | I26: =H26*(1+I112) -> 31905.72 | J26: =I26*(1+J112) -> 31905.72 | K26: =J26*(1+K112) -> 32224.777 | L26: =K26*(1+L112) -> 32869.273 | M26: =L26*(1+M112) -> 33723.874 | N26: =M26*(1+N112) -> 34735.59
B27: % growth | G27: =(G26-F26)/F26 -> 0.032224114 | H27: =(H26-G26)/G26 -> -0.03352726 | I27: =(I26-H26)/H26 -> -0.01 | J27: =(J26-I26)/I26 -> 0 | K27: =(K26-J26)/J26 -> 0.01 | L27: =(L26-K26)/K26 -> 0.02 | M27: =(M26-L26)/L26 -> 0.026 | N27: =(N26-M26)/M26 -> 0.03
B29: DCAI | F29: 15980 | G29: 16125 | H29: 16919 | I29: =I148+I180+I123*I124 -> 20039.95 | J29: =J148+J180+J123*J124 -> 25956.414 | K29: =K148+K180+K123*K124 -> 35303.041 | L29: =L148+L180+L123*L124 -> 48536.06 | M29: =M148+M180+M123*M124 -> 59143.061 | N29: =N148+N180+N123*N124 -> 67240.801
B30: % growth | G30: =(G29-F29)/F29 -> 0.0090738423 | H30: =(H29-G29)/G29 -> 0.04924031 | I30: =(I29-H29)/H29 -> 0.18446421 | J30: =(J29-I29)/I29 -> 0.29523346 | K30: =(K29-J29)/J29 -> 0.36008933 | L30: =(L29-K29)/K29 -> 0.37484075 | M30: =(M29-L29)/L29 -> 0.21853856 | N30: =(N29-M29)/M29 -> 0.13691784
B32: AI Data Center | I32: =I29-I35 -> 2275 | J32: =J29-J35 -> 7392.041 | K32: =K29-K35 -> 15996.094 | L32: =L29-L35 -> 28553.369 | M32: =M29-M35 -> 38520.924 | N32: =N29-N35 -> 46000
B33: % growth | J33: =(J32-I32)/I32 -> 2.2492488 | K33: =(K32-J32)/J32 -> 1.1639617 | L33: =(L32-K32)/K32 -> 0.78502137 | M33: =(M32-L32)/L32 -> 0.34908506 | N33: =(N32-M32)/M32 -> 0.1941562
B35: Traditional Data Center | I35: =I180 -> 17764.95 | J35: =J180 -> 18564.373 | K35: =K180 -> 19306.948 | L35: =L180 -> 19982.691 | M35: =M180 -> 20622.137 | N35: =N180 -> 21240.801
B36: % growth | J36: =(J35-I35)/I35 -> 0.045 | K36: =(K35-J35)/J35 -> 0.04 | L36: =(L35-K35)/K35 -> 0.035 | M36: =(M35-L35)/L35 -> 0.032 | N36: =(N35-M35)/M35 -> 0.03
B38: Intel Foundry | F38: 18504 | G38: 17317 | H38: 17826 | I38: =I118+I44 -> 21487.188 | J38: =J118+J44 -> 32914.684 | K38: =K118+K44 -> 43400 | L38: =L118+L44 -> 53309.394 | M38: =M118+M44 -> 59564.596 | N38: =N118+N44 -> 63958.431
B39: % growth | G39: =(G38-F38)/F38 -> -0.064148292 | H39: =(H38-G38)/G38 -> 0.029393082 | I39: =(I38-H38)/H38 -> 0.20538469 | J39: =(J38-I38)/I38 -> 0.5318284 | K39: =(K38-J38)/J38 -> 0.31856043 | L39: =(L38-K38)/K38 -> 0.22832704 | M39: =(M38-L38)/L38 -> 0.11733772 | N39: =(N38-M38)/M38 -> 0.073765874
B41: Internal Foundry | F41: =F38-F44 -> 18024 | G41: =G38-G44 -> 17288 | H41: =H38-H44 -> 17683 | I41: =I118 -> 18500 | J41: =J118 -> 20125 | K41: =K118 -> 21750 | L41: =L118 -> 23375 | M41: =M118 -> 24350 | N41: =N118 -> 25000
B42: % growth | G42: =(G41-F41)/F41 -> -0.040834443 | H42: =(H41-G41)/G41 -> 0.022848218 | I42: =(I41-H41)/H41 -> 0.046202567 | J42: =(J41-I41)/I41 -> 0.087837838 | K42: =(K41-J41)/J41 -> 0.080745342 | L42: =(L41-K41)/K41 -> 0.074712644 | M42: =(M41-L41)/L41 -> 0.04171123 | N42: =(N41-M41)/M41 -> 0.026694045
B44: External Foundry | F44: =F38+F53 -> 480 | G44: =G38+G53 -> 29 | H44: =H38+H53 -> 143 | I44: =I174*12*I116+I117+I121*I122 -> 2987.1875 | J44: =J174*12*J116+J117+J121*J122 -> 12789.684 | K44: =K174*12*K116+K117+K121*K122 -> 21650 | L44: =L174*12*L116+L117+L121*L122 -> 29934.394 | M44: =M174*12*M116+M117+M121*M122 -> 35214.596 | N44: =N174*12*N116+N117+N121*N122 -> 38958.431
B45: % growth | G45: =(G44-F44)/F44 -> -0.93958333 | H45: =(H44-G44)/G44 -> 3.9310345 | I45: =(I44-H44)/H44 -> 19.889423 | J45: =(J44-I44)/I44 -> 3.2815136 | K45: =(K44-J44)/J44 -> 0.69277051 | L45: =(L44-K44)/K44 -> 0.38265097 | M45: =(M44-L44)/L44 -> 0.17639251 | N45: =(N44-M44)/M44 -> 0.10631485
B47: ASIC Silicon | K47: =K125*K126 -> 366.75 | L47: =L125*L126 -> 1569.1197 | M47: =M125*M126 -> 2849.6344 | N47: =N125*N126 -> 4615.3846
B48: % growth | L48: =(L47-K47)/K47 -> 3.278445 | M48: =(M47-L47)/L47 -> 0.816072 | N48: =(N47-M47)/M47 -> 0.61964098
B50: Other | F50: 5463 | G50: 3601 | H50: 3563 | I50: =H50 -> 3563 | J50: =I50 -> 3563 | K50: =J50 -> 3563 | L50: =K50 -> 3563 | M50: =L50 -> 3563 | N50: =M50 -> 3563
B51: % growth | G51: =(G50-F50)/F50 -> -0.34083837 | H51: =(H50-G50)/G50 -> -0.010552624 | I51: =(I50-H50)/H50 -> 0 | J51: =(J50-I50)/I50 -> 0 | K51: =(K50-J50)/J50 -> 0 | L51: =(L50-K50)/K50 -> 0 | M51: =(M50-L50)/L50 -> 0 | N51: =(N50-M50)/M50 -> 0
B53: Inter Segment Eliminations | F53: -18024 | G53: -17288 | H53: -17683 | I53: =-I118 -> -18500 | J53: =-J118 -> -20125 | K53: =-K118 -> -21750 | L53: =-L118 -> -23375 | M53: =-M118 -> -24350 | N53: =-N118 -> -25000
A55: x | B55: Operating Income by Segment | F55: 2023 | G55: 2024 | H55: 2025 | I55: 2026E | J55: 2027E | K55: 2028E | L55: 2029E | M55: 2030E | N55: 2031E
B57: Operating Income | F57: =SUM(F60,F69,F75,F78,F82) -> 93 | G57: =SUM(G60,G69,G75,G78,G82) -> -11678 | H57: =SUM(H60,H69,H75,H78,H82) -> -2214 | I57: =I80+I82 -> 3657.2246 | J57: =J80+J82 -> 7827.5043 | K57: =K80+K82 -> 16029.623 | L57: =L80+L82 -> 29317.796 | M57: =M80+M82 -> 40384.056 | N57: =N80+N82 -> 49365.424
B58: % of sales | F58: =F57/F20 -> 0.0017149812 | G58: =G57/G20 -> -0.21992053 | H58: =H57/H20 -> -0.04188977 | I58: =I57/I20 -> 0.062521086 | J58: =J57/J20 -> 0.10547091 | K58: =K57/K20 -> 0.17284323 | L58: =L57/L20 -> 0.25515318 | M58: =M57/M20 -> 0.30676592 | N58: =N57/N20 -> 0.34163438
B60: Intel Products | F60: =F63+F66 -> 11073 | G60: =G63+G66 -> 13008 | H60: =H63+H66 -> 12739 | I60: =I63+I66 -> 15583.701 | J60: =J63+J66 -> 18081.917 | K60: =K63+K66 -> 21946.541 | L60: =L63+L66 -> 27474.3 | M60: =M63+M66 -> 32039.092 | N60: =N63+N66 -> 35691.737
B61: % of sales | F61: =F60/F23 -> 0.22932588 | G61: =G60/G23 -> 0.26294193 | H61: =H60/H23 -> 0.25920199 | I61: =I60/I23 -> 0.3 | J61: =J60/J23 -> 0.3125 | K61: =K60/K23 -> 0.325 | L61: =L60/L23 -> 0.3375 | M61: =M60/M23 -> 0.345 | N61: =N60/N23 -> 0.35
B63: Client Computing | F63: 10128 | G63: 11594 | H63: 9317 | I63: =I26*I129 -> 9571.716 | J63: =J26*J129 -> 9970.5375 | K63: =K26*K129 -> 10473.053 | L63: =L26*L129 -> 11093.38 | M63: =M26*M129 -> 11634.736 | N63: =N26*N129 -> 12157.457
B64: % of sales | F64: =F63/F26 -> 0.31351184 | G64: =G63/G26 -> 0.34768788 | H64: =H63/H26 -> 0.28909644 | I64: =I63/I26 -> 0.3 | J64: =J63/J26 -> 0.3125 | K64: =K63/K26 -> 0.325 | L64: =L63/L26 -> 0.3375 | M64: =M63/M26 -> 0.345 | N64: =N63/N26 -> 0.35
B66: DCAI | F66: 945 | G66: 1414 | H66: 3422 | I66: =I29*I130 -> 6011.985 | J66: =J29*J130 -> 8111.3793 | K66: =K29*K130 -> 11473.488 | L66: =L29*L130 -> 16380.92 | M66: =M29*M130 -> 20404.356 | N66: =N29*N130 -> 23534.28
B67: % of sales | F67: =F66/F29 -> 0.059136421 | G67: =G66/G29 -> 0.087689922 | H67: =H66/H29 -> 0.20225782 | I67: =I66/I29 -> 0.3 | J67: =J66/J29 -> 0.3125 | K67: =K66/K29 -> 0.325 | L67: =L66/L29 -> 0.3375 | M67: =M66/M29 -> 0.345 | N67: =N66/N29 -> 0.35
B69: Intel Foundry | F69: -7083 | G69: -13291 | H69: -10318 | I69: =I38*I131 -> -8594.875 | J69: =J38*J131 -> -7817.2375 | K69: =K38*K131 -> -3255 | L69: =L38*L131 -> 4664.5719 | M69: =M38*M131 -> 11019.45 | N69: =N38*N131 -> 15989.608
B70: % of sales | F70: =F69/F38 -> -0.3827821 | G70: =G69/G38 -> -0.76751169 | H70: =H69/H38 -> -0.57881746 | I70: =I69/I38 -> -0.4 | J70: =J69/J38 -> -0.2375 | K70: =K69/K38 -> -0.075 | L70: =L69/L38 -> 0.0875 | M70: =M69/M38 -> 0.185 | N70: =N69/N38 -> 0.25
B72: Custom ASIC | K72: =K47*K132 -> 36.675 | L72: =L47*L132 -> 294.20995 | M72: =M47*M132 -> 748.02902 | N72: =N47*N132 -> 1615.3846
B73: % growth | L73: =(L72-K72)/K72 -> 7.0220844 | M73: =(M72-L72)/L72 -> 1.5425008 | N73: =(N72-M72)/M72 -> 1.1595213
B75: Other | F75: 1507 | G75: -57 | H75: 264 | I75: =I50*I133 -> 178.15 | J75: =J50*J133 -> 204.8725 | K75: =K50*K133 -> 231.595 | L75: =L50*L133 -> 258.3175 | M75: =M50*M133 -> 274.351 | N75: =N50*N133 -> 285.04
B76: % of sales | F76: =F75/F50 -> 0.27585576 | G76: =G75/G50 -> -0.015828936 | H76: =H75/H50 -> 0.074094864 | I76: =I75/I50 -> 0.05 | J76: =J75/J50 -> 0.0575 | K76: =K75/K50 -> 0.065 | L76: =L75/L50 -> 0.0725 | M76: =M75/M50 -> 0.077 | N76: =N75/N50 -> 0.08
B78: Intersegment Eliminations | F78: -205 | G78: -161 | H78: 619 | I78: 0 | J78: 0 | K78: 0 | L78: 0 | M78: 0 | N78: 0
B80: Segment Operating Income | F80: =F60+F69+F75+F78 -> 5292 | G80: =G60+G69+G75+G78 -> -501 | H80: =H60+H69+H75+H78 -> 3304 | I80: =I60+I69+I75+I78 -> 7166.976 | J80: =J60+J69+J75+J78 -> 10469.552 | K80: =K60+K69+K75+K78 -> 18923.136 | L80: =L60+L69+L75+L78 -> 32397.189 | M80: =M60+M69+M75+M78 -> 43332.894 | N80: =N60+N69+N75+N78 -> 51966.385
B82: Corporate Unallocated | F82: =SUM(F85,F88,F91,F94) -> -5199 | G82: =SUM(G85,G88,G91,G94) -> -11177 | H82: =SUM(H85,H88,H91,H94) -> -5518 | I82: =SUM(I85,I88,I91,I94) -> -3509.7514 | J82: =SUM(J85,J88,J91,J94) -> -2642.0475 | K82: =SUM(K85,K88,K91,K94) -> -2893.5135 | L82: =SUM(L85,L88,L91,L94) -> -3079.3931 | M82: =SUM(M85,M88,M91,M94) -> -2948.8375 | N82: =SUM(N85,N88,N91,N94) -> -2600.9608
B83: % of sales | F83: =F82/F20 -> -0.095872981 | G83: =G82/G20 -> -0.21048568 | H83: =H82/H20 -> -0.10440278 | I83: =I82/I20 -> -0.06 | J83: =J82/J20 -> -0.0356 | K83: =K82/K20 -> -0.0312 | L83: =L82/L20 -> -0.0268 | M83: =M82/M20 -> -0.0224 | N83: =N82/N20 -> -0.018
B85: Share-based compensation | F85: -3229 | G85: -3410 | H85: -2434 | I85: =I261*I20 -> -2339.8343 | J85: =J261*J20 -> -2642.0475 | K85: =K261*K20 -> -2893.5135 | L85: =L261*L20 -> -3079.3931 | M85: =M261*M20 -> -2948.8375 | N85: =N261*N20 -> -2600.9608
B86: % of sales | F86: =F85/F20 -> -0.059544885 | G86: =G85/G20 -> -0.064217246 | H86: =H85/H20 -> -0.046052258 | I86: =I85/I20 -> -0.04 | J86: =J85/J20 -> -0.0356 | K86: =K85/K20 -> -0.0312 | L86: =L85/L20 -> -0.0268 | M86: =M85/M20 -> -0.0224 | N86: =N85/N20 -> -0.018
B88: Restructuring and other charges | F88: =Main!H43*-1 -> 62 | G88: =Main!I43*-1 -> -6970 | H88: =Main!J43*-1 -> -2191 | I88: =Main!K43*-1 -> -1169.9171 | J88: =Main!L43*-1 -> 0 | K88: =Main!M43*-1 -> 0 | L88: =Main!N43*-1 -> 0 | M88: =Main!O43*-1 -> 0 | N88: =Main!P43*-1 -> 0
B89: % of sales | F89: =F88/F20 -> 0.0011433208 | G89: =G88/G20 -> -0.1312593 | H89: =H88/H20 -> -0.0414546 | I89: =I88/I20 -> -0.02 | J89: =J88/J20 -> 0 | K89: =K88/K20 -> 0 | L89: =L88/L20 -> 0 | M89: =M88/M20 -> 0 | N89: =N88/N20 -> 0
B91: Acquisition-related costs | F91: -1407 | G91: -1044 | H91: -505
B92: % of sales | F92: =F91/F20 -> -0.025946006 | G92: =G91/G20 -> -0.019660647 | H92: =H91/H20 -> -0.0095548029 | I92: =I91/I20 -> 0 | J92: =J91/J20 -> 0 | K92: =K91/K20 -> 0 | L92: =L91/L20 -> 0 | M92: =M91/M20 -> 0 | N92: =N91/N20 -> 0
B94: Other | F94: -625 | G94: 247 | H94: -388
B95: % of sales | F95: =F94/F20 -> -0.011525411 | G95: =G94/G20 -> 0.0046515132 | H95: =H94/H20 -> -0.0073411159 | I95: =I94/I20 -> 0 | J95: =J94/J20 -> 0 | K95: =K94/K20 -> 0 | L95: =L94/L20 -> 0 | M95: =M94/M20 -> 0 | N95: =N94/N20 -> 0
A97: x | B97: Core Levers | I97: 2026E | J97: 2027E | K97: 2028E | L97: 2029E | M97: 2030E | N97: 2031E | Q97: Optionality Revenue Build | U97: 2031E | V97: Probability | W97: Weighted Rev
B99: Ramp Weight | I99: 0 | J99: 0.25 | K99: 0.5 | L99: 0.75 | M99: 0.9 | N99: 1 | Q99: Gross Optionality Revenue | U99: =U100+U101+U102 -> 24538.462
Q100: =B121 -> TeraFab Gross Rev | U100: =N121 -> 8000 | V100: =N122 -> 0.4 | W100: =U100*V100 -> 3200
B101: AI CPU Demand | Q101: =B123 -> HBM/ZAM Gross Rev | U101: =N123 -> 5000 | V101: =N124 -> 0.2 | W101: =U101*V101 -> 1000
B102: GPU/XPU Units | I102: =D6 -> 13 | J102: =$I102+($N102-$I102)*J$99 -> 22.25 | K102: =$I102+($N102-$I102)*K$99 -> 31.5 | L102: =$I102+($N102-$I102)*L$99 -> 40.75 | M102: =$I102+($N102-$I102)*M$99 -> 46.3 | N102: =E6 -> 50 | Q102: =B125 -> Custom ASIC Gross Rev | U102: =N125 -> 11538.462 | V102: =N126 -> 0.4 | W102: =U102*V102 -> 4615.3846
B103: CPU Attach | I103: =D7 -> 0.25 | J103: =$I103+($N103-$I103)*J$99 -> 0.4375 | K103: =$I103+($N103-$I103)*K$99 -> 0.625 | L103: =$I103+($N103-$I103)*L$99 -> 0.8125 | M103: =$I103+($N103-$I103)*M$99 -> 0.925 | N103: =E7 -> 1 | Q103: Probability-Weighted Optionality Revenue | W103: =SUM(W100:W102) -> 8815.3846
B104: Intel AI CPU Share | I104: =D8 -> 0.35 | J104: =$I104+($N104-$I104)*J$99 -> 0.3375 | K104: =$I104+($N104-$I104)*K$99 -> 0.325 | L104: =$I104+($N104-$I104)*L$99 -> 0.3125 | M104: =$I104+($N104-$I104)*M$99 -> 0.305 | N104: =E8 -> 0.3
B105: AI CPU ASP | I105: =D9 -> 2000 | J105: =$I105+($N105-$I105)*J$99 -> 2250 | K105: =$I105+($N105-$I105)*K$99 -> 2500 | L105: =$I105+($N105-$I105)*L$99 -> 2750 | M105: =$I105+($N105-$I105)*M$99 -> 2900 | N105: =E9 -> 3000
B107: Wafer Economics
B108: Good Dies / Wafer Eq. | I108: =D10 -> 80 | J108: =$I108+($N108-$I108)*J$99 -> 92.5 | K108: =$I108+($N108-$I108)*K$99 -> 105 | L108: =$I108+($N108-$I108)*L$99 -> 117.5 | M108: =$I108+($N108-$I108)*M$99 -> 125 | N108: =E10 -> 130
B109: Usable Capacity % | I109: =I6 -> 0.5 | J109: =$I109+($N109-$I109)*J$99 -> 0.5875 | K109: =$I109+($N109-$I109)*K$99 -> 0.675 | L109: =$I109+($N109-$I109)*L$99 -> 0.7625 | M109: =$I109+($N109-$I109)*M$99 -> 0.815 | N109: =J6 -> 0.85
B111: Segment Growth
B112: CCG Growth | I112: =I13 -> -0.01 | J112: =$I112+($N112-$I112)*J$99 -> 0 | K112: =$I112+($N112-$I112)*K$99 -> 0.01 | L112: =$I112+($N112-$I112)*L$99 -> 0.02 | M112: =$I112+($N112-$I112)*M$99 -> 0.026 | N112: =J13 -> 0.03
B113: Non-AI DCAI Growth | I113: =I14 -> 0.05 | J113: =$I113+($N113-$I113)*J$99 -> 0.045 | K113: =$I113+($N113-$I113)*K$99 -> 0.04 | L113: =$I113+($N113-$I113)*L$99 -> 0.035 | M113: =$I113+($N113-$I113)*M$99 -> 0.032 | N113: =J14 -> 0.03
B115: Foundry
B116: Foundry Rev / Wafer | I116: =I7 -> 22 | J116: =$I116+($N116-$I116)*J$99 -> 23.5 | K116: =$I116+($N116-$I116)*K$99 -> 25 | L116: =$I116+($N116-$I116)*L$99 -> 26.5 | M116: =$I116+($N116-$I116)*M$99 -> 27.4 | N116: =J7 -> 28
B117: EMIB / Packaging Rev | I117: =I9 -> 2000 | J117: =$I117+($N117-$I117)*J$99 -> 4500 | K117: =$I117+($N117-$I117)*K$99 -> 7000 | L117: =$I117+($N117-$I117)*L$99 -> 9500 | M117: =$I117+($N117-$I117)*M$99 -> 11000 | N117: =J9 -> 12000
B118: Internal Foundry Rev | I118: =I8 -> 18500 | J118: =$I118+($N118-$I118)*J$99 -> 20125 | K118: =$I118+($N118-$I118)*K$99 -> 21750 | L118: =$I118+($N118-$I118)*L$99 -> 23375 | M118: =$I118+($N118-$I118)*M$99 -> 24350 | N118: =J8 -> 25000
B120: Optionality (Probability-Weighted)
B121: TeraFab Gross Rev | I121: =I10 -> 0 | J121: =$I121+($N121-$I121)*J$99 -> 2000 | K121: =$I121+($N121-$I121)*K$99 -> 4000 | L121: =$I121+($N121-$I121)*L$99 -> 6000 | M121: =$I121+($N121-$I121)*M$99 -> 7200 | N121: =J10 -> 8000
B122: TeraFab Probability | I122: =D12 -> 0.4 | J122: =$I122+($N122-$I122)*J$99 -> 0.4 | K122: =$I122+($N122-$I122)*K$99 -> 0.4 | L122: =$I122+($N122-$I122)*L$99 -> 0.4 | M122: =$I122+($N122-$I122)*M$99 -> 0.4 | N122: =E12 -> 0.4
B123: HBM/ZAM Gross Rev | L123: =D13 -> 500 | M123: =$L123+($N123-$L123)*0.6 -> 3200 | N123: =E13 -> 5000
B124: HBM/ZAM Probability | I124: =D14 -> 0.2 | J124: =$I124+($N124-$I124)*J$99 -> 0.2 | K124: =$I124+($N124-$I124)*K$99 -> 0.2 | L124: =$I124+($N124-$I124)*L$99 -> 0.2 | M124: =$I124+($N124-$I124)*M$99 -> 0.2 | N124: =E14 -> 0.2
B125: Custom ASIC Gross Rev | K125: =I15*((K175/2)*12) -> 1833.75 | L125: =$K125+($N125-$K125)*0.35 -> 5230.399 | M125: =$K125+($N125-$K125)*0.65 -> 8141.8125 | N125: =J15*(N175*12) -> 11538.462
B126: Custom ASIC Probability | K126: =N6 -> 0.2 | L126: =$K126+($N126-$K126)*K$99 -> 0.3 | M126: =$K126+($N126-$K126)*L$99 -> 0.35 | N126: =N7 -> 0.4
B128: Operating Margins
B129: CCG Margin | I129: =D15 -> 0.3 | J129: =$I129+($N129-$I129)*J$99 -> 0.3125 | K129: =$I129+($N129-$I129)*K$99 -> 0.325 | L129: =$I129+($N129-$I129)*L$99 -> 0.3375 | M129: =$I129+($N129-$I129)*M$99 -> 0.345 | N129: =E15 -> 0.35
B130: DCAI Margin | I130: =D16 -> 0.3 | J130: =$I130+($N130-$I130)*J$99 -> 0.3125 | K130: =$I130+($N130-$I130)*K$99 -> 0.325 | L130: =$I130+($N130-$I130)*L$99 -> 0.3375 | M130: =$I130+($N130-$I130)*M$99 -> 0.345 | N130: =E16 -> 0.35
B131: Foundry Margin | I131: =I12 -> -0.4 | J131: =$I131+($N131-$I131)*J$99 -> -0.2375 | K131: =$I131+($N131-$I131)*K$99 -> -0.075 | L131: =$I131+($N131-$I131)*L$99 -> 0.0875 | M131: =$I131+($N131-$I131)*M$99 -> 0.185 | N131: =J12 -> 0.25
B132: Custom ASIC Margin | K132: =I16 -> 0.1 | L132: =$K132+($N132-$K132)*0.35 -> 0.1875 | M132: =$K132+($N132-$K132)*0.65 -> 0.2625 | N132: =J16 -> 0.35
B133: Other Operating Margin | I133: 0.05 | J133: =$I133+($N133-$I133)*J$99 -> 0.0575 | K133: =$I133+($N133-$I133)*K$99 -> 0.065 | L133: =$I133+($N133-$I133)*L$99 -> 0.0725 | M133: =$I133+($N133-$I133)*M$99 -> 0.077 | N133: 0.08
A135: x | B135: AI CPU Demand vs Supply | I135: 2026E | J135: 2027E | K135: 2028E | L135: 2029E | M135: 2030E | N135: 2031E
B137: GPU/XPU Units | I137: =I102 -> 13 | J137: =J102 -> 22.25 | K137: =K102 -> 31.5 | L137: =L102 -> 40.75 | M137: =M102 -> 46.3 | N137: =N102 -> 50
B138: CPU Attach | I138: =I103 -> 0.25 | J138: =J103 -> 0.4375 | K138: =K103 -> 0.625 | L138: =L103 -> 0.8125 | M138: =M103 -> 0.925 | N138: =N103 -> 1
B139: AI CPU Demand | I139: =I137*I138 -> 3.25 | J139: =J137*J138 -> 9.734375 | K139: =K137*K138 -> 19.6875 | L139: =L137*L138 -> 33.109375 | M139: =M137*M138 -> 42.8275 | N139: =N137*N138 -> 50
B140: Intel AI Share | I140: =I104 -> 0.35 | J140: =J104 -> 0.3375 | K140: =K104 -> 0.325 | L140: =L104 -> 0.3125 | M140: =M104 -> 0.305 | N140: =N104 -> 0.3
B141: Intel AI Demand Units | I141: =I139*I140 -> 1.1375 | J141: =J139*J140 -> 3.2853516 | K141: =K139*K140 -> 6.3984375 | L141: =L139*L140 -> 10.34668 | M141: =M139*M140 -> 13.062388 | N141: =N139*N140 -> 15
...

Sheet Extras
G2: Management Team
G3: Lip Bu Tan | M3: #VALUE! | N3: {=_FV(M3,"Price")} -> 123
G11: Years | H11: =2031-2026 -> 5 | J11: Year | L11: 2031
G12: EPS | H12: =Main!P73 -> 7.1174626 | J12: Shares | L12: =Main!P70 -> 5895.4451
G13: Multiple | H13: 20 | J13: Market Cap | L13: =L15*L12 -> 1049015.3
G14: Price | H14: =H12*H13 -> 142.34925 | J14: Multiple | L14: 25
G15: WACC | H15: 0.105 | J15: Share Price | L15: =H12*25 -> 177.93657
G16: PV Today | H16: =H14/(1+H15)^H11 -> 86.40598
H18: Multiple
H19: 12 | I19: 15 | J19: 18 | K19: 20 | L19: 23 | M19: 25 | N19: 28 | O19: 30 | P19: 35 | Q19: 40
F20: Discount Rate | G20: =G21-0.01 -> 0.075 | H20: =($H$12*H$19)/(1+$G20)^$H$11 -> 59.49276 | I20: =($H$12*I$19)/(1+$G20)^$H$11 -> 74.36595 | J20: =($H$12*J$19)/(1+$G20)^$H$11 -> 89.239141 | K20: =($H$12*K$19)/(1+$G20)^$H$11 -> 99.154601 | L20: =($H$12*L$19)/(1+$G20)^$H$11 -> 114.02779 | M20: =($H$12*M$19)/(1+$G20)^$H$11 -> 123.94325 | N20: =($H$12*N$19)/(1+$G20)^$H$11 -> 138.81644 | O20: =($H$12*O$19)/(1+$G20)^$H$11 -> 148.7319 | ... Q20: =($H$12*Q$19)/(1+$G20)^$H$11 -> 198.3092
G21: =G22-0.01 -> 0.085 | H21: =($H$12*H$19)/(1+$G21)^$H$11 -> 56.801231 | I21: =($H$12*I$19)/(1+$G21)^$H$11 -> 71.001539 | J21: =($H$12*J$19)/(1+$G21)^$H$11 -> 85.201847 | K21: =($H$12*K$19)/(1+$G21)^$H$11 -> 94.668719 | L21: =($H$12*L$19)/(1+$G21)^$H$11 -> 108.86903 | M21: =($H$12*M$19)/(1+$G21)^$H$11 -> 118.3359 | N21: =($H$12*N$19)/(1+$G21)^$H$11 -> 132.53621 | O21: =($H$12*O$19)/(1+$G21)^$H$11 -> 142.00308 | ... Q21: =($H$12*Q$19)/(1+$G21)^$H$11 -> 189.33744
G22: =G23-0.01 -> 0.095 | H22: =($H$12*H$19)/(1+$G22)^$H$11 -> 54.25451 | I22: =($H$12*I$19)/(1+$G22)^$H$11 -> 67.818137 | J22: =($H$12*J$19)/(1+$G22)^$H$11 -> 81.381765 | K22: =($H$12*K$19)/(1+$G22)^$H$11 -> 90.424183 | L22: =($H$12*L$19)/(1+$G22)^$H$11 -> 103.98781 | M22: =($H$12*M$19)/(1+$G22)^$H$11 -> 113.03023 | N22: =($H$12*N$19)/(1+$G22)^$H$11 -> 126.59386 | O22: =($H$12*O$19)/(1+$G22)^$H$11 -> 135.63627 | ... Q22: =($H$12*Q$19)/(1+$G22)^$H$11 -> 180.84837
G23: 0.105 | H23: =($H$12*H$19)/(1+$G23)^$H$11 -> 51.843588 | I23: =($H$12*I$19)/(1+$G23)^$H$11 -> 64.804485 | J23: =($H$12*J$19)/(1+$G23)^$H$11 -> 77.765382 | K23: =($H$12*K$19)/(1+$G23)^$H$11 -> 86.40598 | L23: =($H$12*L$19)/(1+$G23)^$H$11 -> 99.366877 | M23: =($H$12*M$19)/(1+$G23)^$H$11 -> 108.00748 | N23: =($H$12*N$19)/(1+$G23)^$H$11 -> 120.96837 | O23: =($H$12*O$19)/(1+$G23)^$H$11 -> 129.60897 | ... Q23: =($H$12*Q$19)/(1+$G23)^$H$11 -> 172.81196
G24: =G23+0.01 -> 0.115 | H24: =($H$12*H$19)/(1+$G24)^$H$11 -> 49.560092 | I24: =($H$12*I$19)/(1+$G24)^$H$11 -> 61.950115 | J24: =($H$12*J$19)/(1+$G24)^$H$11 -> 74.340138 | K24: =($H$12*K$19)/(1+$G24)^$H$11 -> 82.600153 | L24: =($H$12*L$19)/(1+$G24)^$H$11 -> 94.990176 | M24: =($H$12*M$19)/(1+$G24)^$H$11 -> 103.25019 | N24: =($H$12*N$19)/(1+$G24)^$H$11 -> 115.64021 | O24: =($H$12*O$19)/(1+$G24)^$H$11 -> 123.90023 | ... Q24: =($H$12*Q$19)/(1+$G24)^$H$11 -> 165.20031
G25: =G24+0.01 -> 0.125 | H25: =($H$12*H$19)/(1+$G25)^$H$11 -> 47.396233 | I25: =($H$12*I$19)/(1+$G25)^$H$11 -> 59.245292 | J25: =($H$12*J$19)/(1+$G25)^$H$11 -> 71.09435 | K25: =($H$12*K$19)/(1+$G25)^$H$11 -> 78.993722 | L25: =($H$12*L$19)/(1+$G25)^$H$11 -> 90.842781 | M25: =($H$12*M$19)/(1+$G25)^$H$11 -> 98.742153 | N25: =($H$12*N$19)/(1+$G25)^$H$11 -> 110.59121 | O25: =($H$12*O$19)/(1+$G25)^$H$11 -> 118.49058 | ... Q25: =($H$12*Q$19)/(1+$G25)^$H$11 -> 157.98744
G26: =G25+0.01 -> 0.135 | H26: =($H$12*H$19)/(1+$G26)^$H$11 -> 45.344763 | I26: =($H$12*I$19)/(1+$G26)^$H$11 -> 56.680953 | J26: =($H$12*J$19)/(1+$G26)^$H$11 -> 68.017144 | K26: =($H$12*K$19)/(1+$G26)^$H$11 -> 75.574604 | L26: =($H$12*L$19)/(1+$G26)^$H$11 -> 86.910795 | M26: =($H$12*M$19)/(1+$G26)^$H$11 -> 94.468256 | N26: =($H$12*N$19)/(1+$G26)^$H$11 -> 105.80445 | O26: =($H$12*O$19)/(1+$G26)^$H$11 -> 113.36191 | ... Q26: =($H$12*Q$19)/(1+$G26)^$H$11 -> 151.14921

Sheet Quarterly Segments
H2: Sep '24 | I2: Dec '24 | J2: Mar '25 | K2: Jun '25 | L2: Sep '25 | M2: Dec '25 | N2: Mar '26E | O2: Jun '26E | P2: Sep '26E | Q2: Dec '26E | R2: Mar '27E
H3: FY 25 | L3: FY 26 | P3: FY 27
B4: Quarterly Product Segments | H4: Q1 | I4: Q2 | J4: Q3 | K4: Q4 | L4: Q1 | M4: Q2 | N4: Q3 | O4: Q4 | P4: Q1 | Q4: Q2 | R4: Q3
