Workbook

Sheet Main
A4: x | B4: Company Overview | W4: 10 Year DCF | Y4: 2032 | Z4: =Y4+1 -> 2033 | AA4: =Z4+1 -> 2034 | AB4: =AA4+1 -> 2035 | AC4: =AB4+1 -> 2036
B6: Price | G6: Key Stats | M6: Valuation | R6: Notes | W6: Revenue | Y6: =P96*1.11 -> 66138.778 | Z6: =Y6*1.1 -> 72752.656 | AA6: =Z6*1.09 -> 79300.395 | AB6: =AA6*1.08 -> 85644.427 | AC6: =AB6*1.07 -> 91639.536
B7: Ticker | E7: KO | G7: Employees | I7: 65900 | M7: PV of FCF | P7: =SUM(K108:P108) -> 64295.284 | R7: WACC | U7: 0.105 | W7: % growth | Y7: 0.095 | Z7: 0.09 | AA7: 0.085 | AB7: =(AB6-AA6)/AA6 -> 0.08 | AC7: =(AC6-AB6)/AB6 -> 0.07
B8: Implied Share Price | E8: =AVERAGE((P13/P12),(T23)) -> 45.54684 | G8: Founded | I8: 1886 | M8: Terminal Value | P8: =(P49*U8) -> 312074.25 | R8: EV/EBITDA Multiple | U8: 12
B9: Current Share Price | E9: =Extras!N3 -> 82.63 | G9: CEO | I9: James Quincey | M9: PV of Terminal Value | P9: =-(PV(U7,(DATE(2031,12,31)-$E$12)/365,0,P8)) -> 180574.5 | R9: TGR | U9: 0.03
B10: Implied Upside / (Downside) | E10: =E8/E9-1 -> -0.44878567 | G10: Headquarters | I10: Atlanta, Georgia | M10: Net Debt | P10: =-32789+43027+2004 -> 12242 | W10: Free Cash Flow | Y10: =Y6*0.22 -> 14550.531 | Z10: =Z6*0.23 -> 16733.111 | AA10: =AA6*0.24 -> 19032.095 | AB10: =AB6*0.25 -> 21411.107 | AC10: =AC6*0.25 -> 22909.884
B11: IRR | E11: =(K17/E9)^(1/2)-1 -> -0.21723471 | G11: Primary Industry | I11: Beverages (Non-Alcoholic) | M11: Strategic Investments | P11: =6000+4300 -> 10300 | W11: % of sales | Y11: =P106+0.003 -> 0.26438939 | Z11: =Y11+0.0004 -> 0.26478939 | AA11: =Z11 -> 0.26478939 | AB11: =AA11+0.0004 -> 0.26518939 | AC11: =AB11+0.0004 -> 0.26558939
B12: Last Updated | E12: =DATE(2026,7,10) -> 46213 | G12: Fiscal Year End | I12: 46387 | M12: Shares Outstanding | P12: 5026
M13: Implied Market Cap | P13: =P9+P7-P10+P11 -> 242927.78 | R13: Share Price | U13: =P13/P12 -> 48.334219 | W13: Present Value of FCF | Y13: =Y10/(1+$U$7)^((DATE(2032,7,1)-$E$12)/365) -> 8008.2346 | Z13: =Z10/(1+$U$7)^((DATE(2033,7,1)-$E$12)/365) -> 8334.3618 | AA13: =AA10/(1+$U$7)^((DATE(2034,7,1)-$E$12)/365) -> 8578.6702 | AB13: =AB10/(1+$U$7)^((DATE(2035,7,1)-$E$12)/365) -> 8733.9403 | AC13: =AC10/(1+$U$7)^((DATE(2036,7,1)-$E$12)/365) -> 8454.9865
A15: x | B15: Key Statistics | E15: 2021 | F15: =E15+1 -> 2022 | G15: =F15+1 -> 2023 | H15: =G15+1 -> 2024 | I15: =H15+1 -> 2025 | J15: 2026E | K15: 2027E | M15: Financial Ratios | R15: Gordon Growth Method | W15: Probability Weighted | Z15: 46165
M16: PV of FCF | P16: =SUM(J111:N111) -> 0
B17: Stock Price | E17: 59.21 | F17: 63.61 | G17: 58.93 | H17: 62.26 | I17: 82.63 | J17: =AVERAGE($U$13*(1+$U$7)-K105/J18,$T$23*(1+$U$7)-K105/J18) -> 48.001119 | K17: =AVERAGE($U$13*(1+$U$7)^2-(K105/J18)*(1+$U$7)-L105/K18,$T$23*(1+$U$7)^2-(K105/J18)*(1+$U$7)-L105/K18) -> 50.629177 | M17: Market Cap | P17: =E9*P12 -> 415298.38 | R17: FCF Value | T17: =SUM(K108:P108)+SUM((Y13:AC13)) -> 106405.48 | W17: Bear | X17: 63 | Y17: 0.2 | Z17: 58
B18: shares outstanding | E18: 4340 | F18: 4350 | G18: 4339 | H18: 4320 | I18: 4313 | J18: =K70 -> 5237 | K18: =L70 -> 5446.48 | M18: Enterprise Value | P18: =P17+P10 -> 427540.38 | R18: Terminal Value | T18: =(AC10*(1+U9)/($U$7-U9))/(1+$U$7)^((DATE(2036,12,31)-$E$12)/365) -> 110445.58 | W18: Base | X18: 103 | Y18: 0.55 | Z18: 93
M19: P/E (LTM) | P19: =$P$17/J67 -> -1555.4246 | R19: Net Debt | T19: =P10 -> 12242 | W19: Bull | X19: 273 | Y19: 0.25 | Z19: 248
B20: Market Cap | E20: =E18*E17 -> 256971.4 | F20: =F18*F17 -> 276703.5 | G20: =G18*G17 -> 255697.27 | H20: =H18*H17 -> 268963.2 | I20: =I18*I17 -> 356383.19 | J20: =J17*J18 -> 251381.86 | K20: =K17*K18 -> 275750.8 | M20: P/E (NTM) | P20: =$P$17/K67 -> 31.504117 | R20: Strategic Investments | T20: =P11 -> 10300
B21: Cash | E21: 9684 | F21: 9519 | G21: 9366 | H21: 10828 | I21: 10270 | J21: 13820 | K21: 14000 | M21: EV/EBITDA (LTM) | P21: =P18/(J46+J78) -> 45.042181 | R21: Total | T21: =T17+T18-T19+T20 -> 214909.06 | W21: Total | X21: =SUMPRODUCT(X17:X19,Y17:Y19) -> 137.5 | Z21: =SUMPRODUCT(Z17:Z19,Y17:Y19) -> 124.75
B22: Debt | E22: 42761 | F22: 39149 | G22: 43065 | H22: 45445 | I22: 46893 | J22: 43890 | K22: =J22*1.01 -> 44328.9 | M22: EV/EBITDA (NTM) | P22: =P18/(K46+K78) -> 17.322516 | W22: Current | X22: =E9 -> 82.63
B23: Enterprise Value | E23: =E20-E21+E22 -> 290048.4 | F23: =F20-F21+F22 -> 306333.5 | G23: =G20-G21+G22 -> 289396.27 | H23: =H20-H21+H22 -> 303580.2 | I23: =I20-I21+I22 -> 393006.19 | J23: =J20-J21+J22 -> 281451.86 | K23: =K20-K21+K22 -> 306079.7 | M23: EV/EBIT (LTM) | P23: =P18/J46 -> -193.10767 | R23: Share Price | T23: =T21/P12 -> 42.759462 | W23: Upside | X23: =(X21-X22)/X22 -> 0.66404454
A26: x | B26: Income Statement ($M) | E26: 2020 | F26: 2021 | G26: 2022 | H26: 2023 | I26: 2024 | J26: 2025 | K26: 2026E | L26: 2027E | M26: 2028E | N26: 2029E | O26: 2030E | P26: 2031E | R26: $ mm, except per share | U26: 2026E | V26: 2027E | W26: 2028E | X26: 2029E | Y26: 2030E | Z26: 2031E
B28: Revenue | E28: 77867 | F28: 79024 | G28: 63054 | H28: 54228 | I28: 53101 | J28: 52853 | K28: =Segments!I20 -> 49345.106 | L28: =Segments!J20 -> 51057.966 | M28: =Segments!K20 -> 52991.003 | N28: =Segments!L20 -> 55084.738 | O28: =Segments!M20 -> 57285.187 | P28: =Segments!N20 -> 59584.485 | R28: =B28 -> Revenue | U28: =K28 -> 49345.106 | V28: =L28 -> 51057.966 | W28: =M28 -> 52991.003 | X28: =N28 -> 55084.738 | Y28: =O28 -> 57285.187 | Z28: =P28 -> 59584.485
B29: % growth | F29: =(F28-E28)/E28 -> 0.014858669 | G29: =(G28-F28)/F28 -> -0.2020905 | H29: =(H28-G28)/G28 -> -0.13997526 | I29: =(I28-H28)/H28 -> -0.020782622 | J29: =(J28-I28)/I28 -> -0.0046703452 | K29: =(K28-J28)/J28 -> -0.06637076 | L29: =(L28-K28)/K28 -> 0.034711853 | M29: =(M28-L28)/L28 -> 0.037859646 | ... P29: =(P28-O28)/O28 -> 0.040137745 | R29: Revenue Growth | U29: =K29 -> -0.06637076 | V29: =L29 -> 0.034711853 | W29: =M29 -> 0.037859646 | X29: =N29 -> 0.039511147 | Y29: =O29 -> 0.039946608 | Z29: =P29 -> 0.040137745
R30: =B34 -> Gross Profit | U30: =K34 -> 18751.14 | V30: =L34 -> 21189.056 | W30: =M34 -> 25170.726 | X30: =N34 -> 28093.216 | Y30: =O34 -> 30647.575 | Z30: =P34 -> 32771.467
B31: COGS | E31: 34255 | F31: 35209 | G31: 36188 | H31: 32517 | I31: 35756 | J31: 34478 | K31: =K28*0.62 -> 30593.966 | L31: =L28*0.585 -> 29868.91 | M31: =M28*0.525 -> 27820.276 | N31: =N28*0.49 -> 26991.522 | O31: =O28*0.465 -> 26637.612 | P31: =P28*0.45 -> 26813.018 | R31: Gross Margin | U31: =K35 -> 0.38 | V31: =L35 -> 0.415 | W31: =M35 -> 0.475 | X31: =N35 -> 0.51 | Y31: =O35 -> 0.535 | Z31: =P35 -> 0.55
B32: % of sales | E32: =E31/E28 -> 0.43991678 | F32: =F31/F28 -> 0.44554819 | G32: =G31/G28 -> 0.57392077 | H32: =H31/H28 -> 0.59963487 | I32: =I31/I28 -> 0.67335832 | J32: =J31/J28 -> 0.65233762 | K32: =K31/K28 -> 0.62 | L32: =L31/L28 -> 0.585 | ... P32: =P31/P28 -> 0.45 | R32: EBITDA | U32: =K49 -> 24681.194 | V32: =L49 -> 25251.701 | W32: =M49 -> 25295.197 | X32: =N49 -> 24973.248 | Y32: =O49 -> 25521.725 | Z32: =P49 -> 26006.188
R33: EBITDA Margin | U33: =K50 -> 0.50017511 | V33: =L50 -> 0.49456927 | W33: =M50 -> 0.4773489 | X33: =N50 -> 0.45336057 | Y33: =O50 -> 0.4455205 | Z33: =P50 -> 0.43645905
B34: Gross Profit | E34: =E28-E31 -> 43612 | F34: =F28-F31 -> 43815 | G34: =G28-G31 -> 26866 | H34: =H28-H31 -> 21711 | I34: =I28-I31 -> 17345 | J34: =J28-J31 -> 18375 | K34: =K28-K31 -> 18751.14 | L34: =L28-L31 -> 21189.056 | ... P34: =P28-P31 -> 32771.467 | R34: Operating Income | U34: =K46 -> 14733.221 | V34: =L46 -> 15693.65 | W34: =M46 -> 16684.159 | X34: =N46 -> 17702.063 | Y34: =O46 -> 18647.502 | Z34: =P46 -> 19571.063
B35: % of sales | E35: =E34/E28 -> 0.56008322 | F35: =F34/F28 -> 0.55445181 | G35: =G34/G28 -> 0.42607923 | H35: =H34/H28 -> 0.40036513 | I35: =I34/I28 -> 0.32664168 | J35: =J34/J28 -> 0.34766238 | K35: =K34/K28 -> 0.38 | L35: =L34/L28 -> 0.415 | ... P35: =P34/P28 -> 0.55 | R35: EBIT Margin | U35: =K47 -> 0.29857511 | V35: =L47 -> 0.30736927 | W35: =M47 -> 0.3148489 | X35: =N47 -> 0.32136057 | Y35: =O47 -> 0.3255205 | Z35: =P47 -> 0.32845905
R36: =B67 -> Net Income | U36: =K67 -> 13182.353 | V36: =L67 -> 13910.646 | W36: =M67 -> 14653.525 | X36: =N67 -> 15407.581 | Y36: =O67 -> 16086.117 | Z36: =P67 -> 16635.404
B37: Research & Development | E37: 13556 | F37: 15190 | G37: 17528 | H37: 16046 | I37: 16546 | J37: 13774 | K37: =K34-K40-N(K43)-K46 -> -275.10461 | L37: =L34-N(L43)-L46-L40 -> 2248.1196 | M37: =M34-N(M43)-M46-M40 -> 5296.5089 | N37: =N34-N(N43)-N46-N40 -> 7262.3403 | O37: =O34-N(O43)-O46-O40 -> 8941.0434 | P37: =P34-N(P43)-P46-P40 -> 10221.179 | R37: Net Margin | U37: =K68 -> 0.2671461 | V37: =L68 -> 0.27244811 | W37: =M68 -> 0.27652854 | X37: =N68 -> 0.2797069 | Y37: =O68 -> 0.28080763 | Z37: =P68 -> 0.2791902
B38: % of sales | E38: =E37/E$28 -> 0.17409172 | F38: =F37/F$28 -> 0.19222009 | G38: =G37/G$28 -> 0.27798395 | H38: =H37/H$28 -> 0.2958988 | I38: =I37/I$28 -> 0.31159489 | J38: =J37/J$28 -> 0.26060962 | K38: =K37/K$28 -> -0.0055751144 | L38: =L37/L$28 -> 0.044030732 | ... P38: =P37/P$28 -> 0.17154095 | R38: Shares Outstanding | U38: =K70 -> 5237 | V38: =L70 -> 5446.48 | W38: =M70 -> 5555.4096 | X38: =N70 -> 5666.5178 | Y38: =O70 -> 5779.8481 | Z38: =P70 -> 5895.4451
R39: EPS | U39: =K73 -> 2.5171573 | V39: =L73 -> 2.5540618 | W39: =M73 -> 2.6377038 | X39: =N73 -> 2.7190563 | Y39: =O73 -> 2.7831384 | Z39: =P73 -> 2.8217384
B40: SG&A | E40: 6180 | F40: 6543 | G40: 7002 | H40: 5634 | I40: 5507 | J40: 4624 | K40: =K28*K41 -> 3306.1221 | L40: =L28*L41 -> 3247.2867 | M40: =M28*M41 -> 3190.0584 | N40: =N28*N41 -> 3128.8131 | O40: =O28*O41 -> 3059.029 | P40: =P28*P41 -> 2979.2242 | R40: EPS Growth | U40: N/A | V40: =L74 -> 0.014661178 | W40: =M74 -> 0.032748619 | X40: =N74 -> 0.030842188 | Y40: =O74 -> 0.023567766 | Z40: =P74 -> 0.013869236
B41: % of sales | E41: =E40/E$28 -> 0.079366099 | F41: =F40/F$28 -> 0.082797631 | G41: =G40/G$28 -> 0.11104767 | H41: =H40/H$28 -> 0.10389467 | I41: =I40/I$28 -> 0.10370803 | J41: =J40/J$28 -> 0.087487938 | K41: 0.067 | L41: =$K$41+($P$41-$K$41)*(COLUMNS($K$41:L41)-1)/(COLUMNS($K$41:$P$41)-1) -> 0.0636 | M41: =$K$41+($P$41-$K$41)*(COLUMNS($K$41:M41)-1)/(COLUMNS($K$41:$P$41)-1) -> 0.0602 | N41: =$K$41+($P$41-$K$41)*(COLUMNS($K$41:N41)-1)/(COLUMNS($K$41:$P$41)-1) -> 0.0568 | O41: =$K$41+($P$41-$K$41)*(COLUMNS($K$41:O41)-1)/(COLUMNS($K$41:$P$41)-1) -> 0.0534 | P41: 0.05 | R41: Free Cash Flow | U41: =K105 -> 12192.467 | V41: =L105 -> 13137.233 | W41: =M105 -> 13028.409 | X41: =N105 -> 13642.292 | Y41: =O105 -> 14658.101 | Z41: =P105 -> 15574.752
R42: FCF Margin | U42: =K106 -> 0.24708565 | V42: =L106 -> 0.25730035 | W42: =M106 -> 0.24586078 | X42: =N106 -> 0.24766011 | Y42: =O106 -> 0.25587944 | Z42: =P106 -> 0.26138939
B43: Restructuring and Other Changes | E43: 198 | F43: 2626 | G43: 2 | H43: -62 | I43: 6970 | J43: 2191 | K43: =K28*0.02 -> 986.90212 | L43: 0 | M43: 0 | N43: 0 | O43: 0 | P43: 0 | R43: CapEx | U43: =K81 -> 13816.63 | V43: =L81 -> 13275.071 | W43: =M81 -> 13247.751 | X43: =N81 -> 12118.642 | Y43: =O81 -> 11457.037 | Z43: =P81 -> 10725.207
B44: % of sales | E44: =E43/E$28 -> 0.0025427973 | F44: =F43/F$28 -> 0.033230411 | G44: =G43/G$28 -> 3.1718844e-05 | H44: =H43/H$28 -> -0.0011433208 | I44: =I43/I$28 -> 0.1312593 | J44: =J43/J$28 -> 0.0414546 | K44: =K43/K$28 -> 0.02 | L44: =L43/L$28 -> 0 | ... P44: =P43/P$28 -> 0 | R44: CapEx % of Sales | U44: =K103 -> 0.28 | V44: =L103 -> 0.26 | W44: =M103 -> 0.25 | X44: =N103 -> 0.22 | Y44: =O103 -> 0.2 | Z44: =P103 -> 0.18
B46: Operating Income (EBIT) | E46: =E34-E37-E40-E43 -> 23678 | F46: =F34-F37-F40-F43 -> 19456 | G46: =G34-G37-G40-G43 -> 2334 | H46: =H34-H37-H40-H43 -> 93 | I46: =I34-I37-I40-I43 -> -11678 | J46: =J34-J37-J40-J43 -> -2214 | K46: =Segments!I57 -> 14733.221 | L46: =Segments!J57 -> 15693.65 | M46: =Segments!K57 -> 16684.159 | N46: =Segments!L57 -> 17702.063 | O46: =Segments!M57 -> 18647.502 | P46: =Segments!N57 -> 19571.063
B47: % of sales | E47: =E46/E$28 -> 0.3040826 | F47: =F46/F$28 -> 0.24620368 | G47: =G46/G$28 -> 0.037015891 | H47: =H46/H$28 -> 0.0017149812 | I47: =I46/I$28 -> -0.21992053 | J47: =J46/J$28 -> -0.04188977 | K47: =K46/K$28 -> 0.29857511 | L47: =L46/L$28 -> 0.30736927 | ... P47: =P46/P$28 -> 0.32845905
B49: EBITDA | E49: =E46+E78 -> 35917 | F49: =F46+F78 -> 31248 | G49: =G46+G78 -> 15369 | H49: =H46+H78 -> 9695 | I49: =I46+I78 -> -299 | J49: =J46+J78 -> 9492 | K49: =K46+K78 -> 24681.194 | L49: =L46+L78 -> 25251.701 | ... P49: =P46+P78 -> 26006.188
B50: % of sales | E50: =E49/E$28 -> 0.46126087 | F50: =F49/F$28 -> 0.39542417 | G50: =G49/G$28 -> 0.24374346 | H50: =H49/H$28 -> 0.17878218 | I50: =I49/I$28 -> -0.0056307791 | J50: =J49/J$28 -> 0.17959245 | K50: =K49/K$28 -> 0.50017511 | L50: =L49/L$28 -> 0.49456927 | ... P50: =P49/P$28 -> 0.43645905
B52: Gains on Equity Investments | E52: 1904 | F52: 2729 | G52: 4268 | H52: 40 | I52: 242 | J52: 514 | K52: 0 | L52: 0 | M52: 0 | N52: 0 | O52: 0 | P52: 0
B53: % of sales | E53: =E52/E$28 -> 0.02445195 | F53: =F52/F$28 -> 0.034533813 | G53: =G52/G$28 -> 0.067688013 | H53: =H52/H$28 -> 0.00073762632 | I53: =I52/I$28 -> 0.004557353 | J53: =J52/J$28 -> 0.0097250866 | K53: =K52/K$28 -> 0 | L53: =L52/L$28 -> 0 | ... P53: =P52/P$28 -> 0
B55: Interest Income | E55: -504 | F55: -482 | G55: 1166 | H55: 629 | I55: 226 | J55: 3257 | K55: =K28*0.005 -> 246.72553 | L55: =L28*0.004 -> 204.23187 | M55: =M28*0.003 -> 158.97301 | N55: =N28*0.002 -> 110.16948 | O55: =O28*0.001 -> 57.285187 | P55: 0
B56: % of sales | E56: =E55/E$28 -> -0.006472575 | F56: =F55/F$28 -> -0.0060994128 | G56: =G55/G$28 -> 0.018492086 | H56: =H55/H$28 -> 0.011599174 | I56: =I55/I$28 -> 0.0042560404 | J56: =J55/J$28 -> 0.061623749 | K56: =K55/K$28 -> 0.005 | L56: =L55/L$28 -> 0.004 | ... P56: =P55/P$28 -> 0
B58: Pre-Tax Income | E58: =E46+E52+E55 -> 25078 | F58: =F46+F52+F55 -> 21703 | G58: =G46+G52+G55 -> 7768 | H58: =H46+H52+H55 -> 762 | I58: =I46+I52+I55 -> -11210 | J58: =J46+J52+J55 -> 1557 | K58: =K46+K52+K55 -> 14979.946 | L58: =L46+L52+L55 -> 15897.882 | ... P58: =P46+P52+P55 -> 19571.063
B59: % of sales | E59: =E58/E$28 -> 0.32206198 | F59: =F58/F$28 -> 0.27463808 | G59: =G58/G$28 -> 0.12319599 | H59: =H58/H$28 -> 0.014051781 | I59: =I58/I$28 -> -0.21110714 | J59: =J58/J$28 -> 0.029459066 | K59: =K58/K$28 -> 0.30357511 | L59: =L58/L$28 -> 0.31136927 | ... P59: =P58/P$28 -> 0.32845905
B61: Tax Expense | E61: 4179 | F61: 1835 | G61: -249 | H61: -913 | I61: 8023 | J61: 1531 | K61: =K58*0.12 -> 1797.5936 | L61: =L58*0.125 -> 1987.2352 | M61: =M58*0.13 -> 2189.6072 | N61: =N58*0.135 -> 2404.6514 | O61: =O58*0.14 -> 2618.6703 | P61: =P58*0.15 -> 2935.6595
B62: Tax Rate % | E62: =E61/E58 -> 0.16664008 | F62: =F61/F58 -> 0.084550523 | G62: =G61/G58 -> -0.032054583 | H62: =H61/H58 -> -1.1981627 | I62: =I61/I58 -> -0.71570027 | J62: =J61/J58 -> 0.98330122 | K62: =K61/K58 -> 0.12 | L62: =L61/L58 -> 0.125 | ... P62: =P61/P58 -> 0.15
B64: Non Controlling Stake Income | E64: 0 | F64: 0 | G64: 3 | H64: -14 | I64: -477 | J64: 293 | K64: 0 | L64: 0 | M64: 0 | N64: 0 | O64: 0 | P64: 0
B65: Tax Rate % | E65: =E64/E$28 -> 0 | F65: =F64/F$28 -> 0 | G65: =G64/G$28 -> 4.7578266e-05 | H65: =H64/H$28 -> -0.00025816921 | I65: =I64/I$28 -> -0.0089828817 | J65: =J64/J$28 -> 0.0055436777 | K65: =K64/K$28 -> 0 | L65: =L64/L$28 -> 0 | ... P65: =P64/P$28 -> 0
B67: Net Income | E67: =E58-E61-E64 -> 20899 | F67: =F58-F61-F64 -> 19868 | G67: =G58-G61-G64 -> 8014 | H67: =H58-H61-H64 -> 1689 | I67: =I58-I61-I64 -> -18756 | J67: =J58-J61-J64 -> -267 | K67: =K58-K61-K64 -> 13182.353 | L67: =L58-L61-L64 -> 13910.646 | ... P67: =P58-P61-P64 -> 16635.404
B68: % of sales | E68: =E67/E$28 -> 0.26839354 | F68: =F67/F$28 -> 0.25141729 | G68: =G67/G$28 -> 0.12709741 | H68: =H67/H$28 -> 0.031146271 | I68: =I67/I$28 -> -0.35321369 | J68: =J67/J$28 -> -0.0050517473 | K68: =K67/K$28 -> 0.2671461 | L68: =L67/L$28 -> 0.27244811 | ... P68: =P67/P$28 -> 0.2791902
B70: Shares Outstanding | E70: 4199 | F70: 4059 | G70: 4108 | H70: 4190 | I70: 4280 | J70: 4530 | K70: 5237 | L70: =K70*1.04 -> 5446.48 | M70: =L70*1.02 -> 5555.4096 | N70: =M70*1.02 -> 5666.5178 | O70: =N70*1.02 -> 5779.8481 | P70: =O70*1.02 -> 5895.4451
B71: % growth | F71: =(F70-E70)/E70 -> -0.033341272 | G71: =(G70-F70)/F70 -> 0.012071939 | H71: =(H70-G70)/G70 -> 0.019961052 | I71: =(I70-H70)/H70 -> 0.021479714 | J71: =(J70-I70)/I70 -> 0.058411215 | K71: =(K70-J70)/J70 -> 0.15607064 | L71: =(L70-K70)/K70 -> 0.04 | M71: =(M70-L70)/L70 -> 0.02 | ... P71: =(P70-O70)/O70 -> 0.02
B73: EPS | E73: =E67/E70 -> 4.9771374 | F73: =F67/F70 -> 4.8948017 | G73: =G67/G70 -> 1.9508277 | H73: =H67/H70 -> 0.40310263 | I73: =I67/I70 -> -4.382243 | J73: =J67/J70 -> -0.058940397 | K73: =K67/K70 -> 2.5171573 | L73: =L67/L70 -> 2.5540618 | ... P73: =P67/P70 -> 2.8217384
B74: % growth | F74: =(F73-E73)/E73 -> -0.01654279 | G74: =(G73-F73)/F73 -> -0.60144909 | H74: =(H73-G73)/G73 -> -0.79336841 | I74: =(I73-H73)/H73 -> -11.871284 | J74: =(J73-I73)/I73 -> -0.98655018 | K74: =(-K73-J73)/J73 -> 41.706826 | L74: =(L73-K73)/K73 -> 0.014661178 | M74: =(M73-L73)/L73 -> 0.032748619 | N74: =(N73-M73)/M73 -> 0.030842188 | O74: =(O73-N73)/N73 -> 0.023567766 | P74: =(P73-O73)/O73 -> 0.013869236
A76: x | B76: Cash Flow Items | E76: 2020 | F76: 2021 | G76: 2022 | H76: 2023 | I76: 2024 | J76: 2025 | K76: 2026E | L76: 2027E | M76: 2028E | N76: 2029E | O76: 2030E | P76: 2031E
B77: % of sales
B78: D&A | E78: 12239 | F78: 11792 | G78: 13035 | H78: 9602 | I78: 11379 | J78: 11706 | K78: =K81*0.72 -> 9947.9734 | L78: =L81*0.72 -> 9558.0513 | M78: =M81*0.65 -> 8611.038 | N78: =N81*0.6 -> 7271.1854 | O78: =O81*0.6 -> 6874.2224 | P78: =P81*0.6 -> 6435.1244
B79: % of capex | E79: =E78/E81 -> 0.85839529 | F79: =F78/F81 -> 0.62947739 | G79: =G78/G81 -> 0.52494865 | H79: =H78/H81 -> 0.3728932 | I79: =I78/I81 -> 0.47523388 | J79: =J78/J81 -> 0.80931969 | K79: =K78/K81 -> 0.72 | L79: =L78/L81 -> 0.72 | ... P79: =P78/P81 -> 0.6
B81: CapEx | E81: 14258 | F81: 18733 | G81: 24831 | H81: 25750 | I81: 23944 | J81: 14464 | K81: =K28*0.28 -> 13816.63 | L81: =L28*0.26 -> 13275.071 | M81: =M28*0.25 -> 13247.751 | N81: =N28*0.22 -> 12118.642 | O81: =O28*0.2 -> 11457.037 | P81: =P28*0.18 -> 10725.207
B82: % of sales | E82: =E81/E28 -> 0.18310709 | F82: =F81/F28 -> 0.23705457 | G82: =G81/G28 -> 0.39380531 | H82: =H81/H28 -> 0.47484694 | I82: =I81/I28 -> 0.4509143 | J82: =J81/J28 -> 0.27366469 | K82: =K81/K28 -> 0.28 | L82: =L81/L28 -> 0.26 | ... P82: =P81/P28 -> 0.18
B83: % of ocf
B85: Change in NWC | E85: 1192 | F85: -1498 | G85: -4351 | H85: -569 | I85: 1103 | J85: -1747 | K85: =K28*0.01 -> 493.45106 | L85: =L28*0.01 -> 510.57966 | M85: =M28*0.01 -> 529.91003 | N85: =N28*0.01 -> 550.84738 | O85: =O28*0.01 -> 572.85187 | P85: =P28*0.01 -> 595.84485
B86: % of sales | E86: =E85/E28 -> 0.015308154 | F86: =F85/F28 -> -0.018956266 | G86: =G85/G28 -> -0.069004345 | H86: =H85/H28 -> -0.010492734 | I86: =I85/I28 -> 0.020771737 | J86: =J85/J28 -> -0.033053942 | K86: =K85/K28 -> 0.01 | L86: =L85/L28 -> 0.01 | ... P86: =P85/P28 -> 0.01
B87: % of changes in sales
B89: Stock Based Compensation | E89: 1911 | F89: 2143 | G89: 3071 | H89: 3229 | I89: 3410 | J89: 2434 | K89: =J89*0.98 -> 2385.32 | L89: =K89*1.02 -> 2433.0264 | M89: =L89*1.02 -> 2481.6869 | N89: =M89*1.02 -> 2531.3207 | O89: =N89*1.02 -> 2581.9471 | P89: =O89*1.02 -> 2633.586
B90: % of sales | E90: =E89/E28 -> 0.024541847 | F90: =F89/F28 -> 0.027118344 | G90: =G89/G28 -> 0.048704285 | H90: =H89/H28 -> 0.059544885 | I90: =I89/I28 -> 0.064217246 | J90: =J89/J28 -> 0.046052258 | K90: =K89/K28 -> 0.048339545 | L90: =L89/L28 -> 0.047652239 | ... P90: =P89/P28 -> 0.044199191
B92: Cash Flow from Operations | E92: =E67+E78+E85+E89 -> 36241 | F92: =F67+F78+F85+F89 -> 32305 | G92: =G67+G78+G85+G89 -> 19769 | H92: =H67+H78+H85+H89 -> 13951 | I92: =I67+I78+I85+I89 -> -2864 | J92: =J67+J78+J85+J89 -> 12126 | K92: =K67+K78+K85+K89 -> 26009.097 | L92: =L67+L78+L85+L89 -> 26412.304 | ... P92: =P67+P78+P85+P89 -> 26299.959
A94: x | B94: DCF | E94: 2020 | F94: 2021 | G94: 2022 | H94: 2023 | I94: 2024 | J94: 2025 | K94: 2026E | L94: 2027E | M94: 2028E | N94: 2029E | O94: 2030E | P94: 2031E
B95: % growth
B96: Revenue | E96: =E28 -> 77867 | F96: =F28 -> 79024 | G96: =G28 -> 63054 | H96: =H28 -> 54228 | I96: =I28 -> 53101 | J96: =J28 -> 52853 | K96: =K28 -> 49345.106 | L96: =L28 -> 51057.966 | ... P96: =P28 -> 59584.485
B97: % growth | F97: =(F96-E96)/E96 -> 0.014858669 | G97: =(G96-F96)/F96 -> -0.2020905 | H97: =(H96-G96)/G96 -> -0.13997526 | I97: =(I96-H96)/H96 -> -0.020782622 | J97: =(J96-I96)/I96 -> -0.0046703452 | K97: =(K96-J96)/J96 -> -0.06637076 | L97: =(L96-K96)/K96 -> 0.034711853 | M97: =(M96-L96)/L96 -> 0.037859646 | ... P97: =(P96-O96)/O96 -> 0.040137745
B99: Operating Cash Flow | E99: =E92 -> 36241 | F99: =F92 -> 32305 | G99: =G92 -> 19769 | H99: =H92 -> 13951 | I99: =I92 -> -2864 | J99: =J92 -> 12126 | K99: =K92 -> 26009.097 | L99: =L92 -> 26412.304 | ... P99: =P92 -> 26299.959
B100: % of sales | E100: =E99/E96 -> 0.46542181 | F100: =F99/F96 -> 0.40879986 | G100: =G99/G96 -> 0.31352492 | H100: =H99/H96 -> 0.25726562 | I100: =I99/I96 -> -0.053934954 | J100: =J99/J96 -> 0.22942879 | K100: =K99/K96 -> 0.52708565 | L100: =L99/L96 -> 0.51730035 | ... P100: =P99/P96 -> 0.44138939
B102: CapEx | E102: =E81 -> 14258 | F102: =F81 -> 18733 | G102: =G81 -> 24831 | H102: =H81 -> 25750 | I102: =I81 -> 23944 | J102: =J81 -> 14464 | K102: =K81 -> 13816.63 | L102: =L81 -> 13275.071 | ... P102: =P81 -> 10725.207
B103: % of sales | E103: =E102/E96 -> 0.18310709 | F103: =F102/F96 -> 0.23705457 | G103: =G102/G96 -> 0.39380531 | H103: =H102/H96 -> 0.47484694 | I103: =I102/I96 -> 0.4509143 | J103: =J102/J96 -> 0.27366469 | K103: =K102/K96 -> 0.28 | L103: =L102/L96 -> 0.26 | ... P103: =P102/P96 -> 0.18
B105: Free Cash Flow | E105: =E99-E102 -> 21983 | F105: =F99-F102 -> 13572 | G105: =G99-G102 -> -5062 | H105: =H99-H102 -> -11799 | I105: =I99-I102 -> -26808 | J105: =J99-J102 -> -2338 | K105: =K99-K102 -> 12192.467 | L105: =L99-L102 -> 13137.233 | ... P105: =P99-P102 -> 15574.752
B106: % of sales | E106: =E105/E96 -> 0.28231472 | F106: =F105/F96 -> 0.17174529 | G106: =G105/G96 -> -0.080280395 | H106: =H105/H96 -> -0.21758132 | I106: =I105/I96 -> -0.50484925 | J106: =J105/J96 -> -0.0442359 | K106: =K105/K96 -> 0.24708565 | L106: =L105/L96 -> 0.25730035 | ... P106: =P105/P96 -> 0.26138939
B108: Present Value of FCF | K108: =K105/(1+$U$7)^((DATE(2026,7,1)-$E$12)/365) -> 12222.522 | L108: =L105/(1+$U$7)^((DATE(2027,7,1)-$E$12)/365) -> 11918.204 | M108: =M105/(1+$U$7)^((DATE(2028,7,1)-$E$12)/365) -> 10693.435 | N108: =N105/(1+$U$7)^((DATE(2029,7,1)-$E$12)/365) -> 10133.3 | O108: =O105/(1+$U$7)^((DATE(2030,7,1)-$E$12)/365) -> 9853.239 | P108: =P105/(1+$U$7)^((DATE(2031,7,1)-$E$12)/365) -> 9474.5841
A110: x | B110: Per Share | E110: 2020 | F110: 2021 | G110: =F110+1 -> 2022 | H110: =G110+1 -> 2023 | I110: =H110+1 -> 2024 | J110: =I110+1 -> 2025 | K110: 2026E | L110: 2027E | M110: 2028E | N110: 2029E | O110: 2030E | P110: 2031E
B112: EPS | E112: =E73 -> 4.9771374 | F112: =F73 -> 4.8948017 | G112: =G73 -> 1.9508277 | H112: =H73 -> 0.40310263 | I112: =I73 -> -4.382243 | J112: =J73 -> -0.058940397 | K112: =K73 -> 2.5171573 | L112: =L73 -> 2.5540618 | ... P112: =P73 -> 2.8217384
B113: % change | F113: =(F112-E112)/E112 -> -0.01654279 | G113: =(G112-F112)/F112 -> -0.60144909 | H113: =(H112-G112)/G112 -> -0.79336841 | I113: =(I112-H112)/H112 -> -11.871284 | J113: =(J112-I112)/I112 -> -0.98655018 | K113: =(K112-J112)/J112 -> -43.706826 | L113: =(L112-K112)/K112 -> 0.014661178 | M113: =(M112-L112)/L112 -> 0.032748619 | ... P113: =(P112-O112)/O112 -> 0.013869236
B115: Shares Outstanding | E115: 4199 | F115: =E18 -> 4340 | G115: =F18 -> 4350 | H115: =G18 -> 4339 | I115: =H18 -> 4320 | J115: =I18 -> 4313 | K115: =K70 -> 5237 | L115: =L70 -> 5446.48 | M115: =M70 -> 5555.4096 | N115: =N70 -> 5666.5178 | O115: =O70 -> 5779.8481 | P115: =P70 -> 5895.4451
B116: % change | F116: =(F115-E115)/E115 -> 0.033579424 | G116: =(G115-F115)/F115 -> 0.0023041475 | H116: =(H115-G115)/G115 -> -0.0025287356 | I116: =(I115-H115)/H115 -> -0.0043788891 | J116: =(J115-I115)/I115 -> -0.0016203704 | K116: =(K115-J115)/J115 -> 0.21423603 | L116: =(L115-K115)/K115 -> 0.04 | M116: =(M115-L115)/L115 -> 0.02 | ... P116: =(P115-O115)/O115 -> 0.02
B118: P/E | F118: =E17/F112 -> 12.096506 | G118: =F17/G112 -> 32.606673 | H118: =G17/H112 -> 146.19106 | I118: =H17/I112 -> -14.207336 | J118: =I17/J112 -> -1401.9247 | K118: =$E$9/K112 -> 32.826713 | L118: =$E$9/L112 -> 32.352389 | M118: =$E$9/M112 -> 31.32649 | N118: =$E$9/N112 -> 30.38922 | O118: =$E$9/O112 -> 29.689504 | P118: =$E$9/P112 -> 29.283366
B119: P/EBIT | F119: =E17*F115/F46 -> 13.207823 | G119: =F17*G115/G46 -> 118.55334 | H119: =G17*H115/H46 -> 2749.433 | I119: =H17*I115/I46 -> -23.031615 | J119: =I17*J115/J46 -> -160.96802 | K119: =$E$9*K115/K46 -> 29.371264 | L119: =$E$9*L115/L46 -> 28.676736 | M119: =$E$9*M115/M46 -> 27.513733 | N119: =$E$9*N115/N46 -> 26.450271 | O119: =$E$9*O115/O46 -> 25.611411 | P119: =$E$9*P115/P46 -> 24.890861
B120: P/EBITDA | F120: =E17*F115/(F46+F78) -> 8.2236111 | G120: =F17*G115/(G46+G78) -> 18.004002 | H120: =G17*H115/(H46+H78) -> 26.374138 | I120: =H17*I115/(I46+I78) -> -899.54247 | J120: =I17*J115/(J46+J78) -> 37.545637 | K120: =$E$9*K115/(K46+K78) -> 17.532916 | L120: =$E$9*L115/(L46+L78) -> 17.82227 | M120: =$E$9*M115/(M46+M78) -> 18.147457 | N120: =$E$9*N115/(N46+N78) -> 18.749037 | O120: =$E$9*O115/(O46+O78) -> 18.713032 | P120: =$E$9*P115/(P46+P78) -> 18.73172
B121: P/S | F121: =E17*F115/F28 -> 3.2518146 | G121: =F17*G115/G28 -> 4.3883576 | H121: =G17*H115/H28 -> 4.7152259 | I121: =H17*I115/I28 -> 5.065125 | J121: =I17*J115/J28 -> 6.7429132 | K121: =$E$9*K115/K28 -> 8.7695284 | L121: =$E$9*L115/L28 -> 8.8143472 | M121: =$E$9*M115/M28 -> 8.6626686 | N121: =$E$9*N115/N28 -> 8.5000743 | O121: =$E$9*O115/O28 -> 8.3370393 | P121: =$E$9*P115/P28 -> 8.1756288
B122: P/FCF | F122: =E17*F115/F105 -> 18.933938 | G122: =F17*G115/G105 -> -54.66288 | H122: =G17*H115/H105 -> -21.671097 | I122: =H17*I115/I105 -> -10.032945 | J122: =I17*J115/J105 -> -152.43079 | K122: =$E$9*K115/K105 -> 35.491857 | L122: =$E$9*L115/L105 -> 34.257036 | M122: =$E$9*M115/M105 -> 35.234041 | N122: =$E$9*N115/N105 -> 34.321532 | O122: =$E$9*O115/O105 -> 32.581904 | P122: =$E$9*P115/P105 -> 31.277585
B123: P/OCF | F123: =E17*F115/F99 -> 7.9545395 | G123: =F17*G115/G99 -> 13.996838 | H123: =G17*H115/H99 -> 18.32824 | I123: =H17*I115/I99 -> -93.911732 | J123: =I17*J115/J99 -> 29.390004 | K123: =$E$9*K115/K99 -> 16.637767 | L123: =$E$9*L115/L99 -> 17.039129 | M123: =$E$9*M115/M99 -> 17.469961 | N123: =$E$9*N115/N99 -> 18.175752 | O123: =$E$9*O115/O99 -> 18.287816 | P123: =$E$9*P115/P99 -> 18.522486

Sheet Segments
K2: all values in millions except per share numbers
A4: x | B4: Levers | D4: 2026 | E4: 2031 | I4: 2026 | J4: 2031
B6: North America Rev Growth | D6: 0.055 | E6: 0.04 | G6: North America OI Margin | I6: 0.265 | J6: 0.28
B7: EMEA Rev Growth | D7: 0.05 | E7: 0.04 | G7: EMEA OI Margin | I7: 0.375 | J7: 0.385
B8: Latin America Rev Growth | D8: 0.06 | E8: 0.05 | G8: Latin America OI Margin | I8: 0.595 | J8: 0.605
B9: Asia Pacific Rev Growth | D9: 0.04 | E9: 0.05 | G9: Asia Pacific OI Margin | I9: 0.365 | J9: 0.38
B10: Bottling Investments Rev Growth | D10: -0.15 | E10: 0 | G10: Bottling Investments OI Margin | I10: 0.075 | J10: 0.09
B12: Corporate Revenue ($M) | D12: 145 | E12: 150 | G12: Corporate Expense % of Rev | I12: -0.036 | J12: -0.03
B13: Eliminations % of Gross Rev | D13: 0.02 | E13: 0.018
B14: Concentrate % of Revenue | D14: 0.595 | E14: 0.605
A18: x | B18: Operating Segments ($M) | F18: 2023 | G18: 2024 | H18: 2025 | I18: 2026E | J18: 2027E | K18: 2028E | L18: 2029E | M18: 2030E | N18: 2031E
B20: Revenue | F20: =F23+F38+F41+F44 -> 45754 | G20: =G23+G38+G41+G44 -> 47061 | H20: =H23+H38+H41+H44 -> 47941 | I20: =I23+I38+I41+I44 -> 49345.106 | J20: =J23+J38+J41+J44 -> 51057.966 | K20: =K23+K38+K41+K44 -> 52991.003 | L20: =L23+L38+L41+L44 -> 55084.738 | M20: =M23+M38+M41+M44 -> 57285.187 | N20: =N23+N38+N41+N44 -> 59584.485
B21: % growth | F21: =(F20-43004)/43004 -> 0.06394754 | G21: =(G20-F20)/F20 -> 0.028565808 | H21: =(H20-G20)/G20 -> 0.018699135 | I21: =(I20-H20)/H20 -> 0.029288213 | J21: =(J20-I20)/I20 -> 0.034711853 | K21: =(K20-J20)/J20 -> 0.037859646 | L21: =(L20-K20)/K20 -> 0.039511147 | M21: =(M20-L20)/L20 -> 0.039946608 | N21: =(N20-M20)/M20 -> 0.040137745
B23: Geographic Segments | F23: =F26+F29+F32+F35 -> 39187 | G23: =G26+G29+G32+G35 -> 41892 | H23: =H26+H29+H32+H35 -> 43071 | I23: =I26+I29+I32+I35 -> 45329.44 | J23: =J26+J29+J32+J35 -> 47597.898 | K23: =K26+K29+K32+K35 -> 49865.11 | L23: =L26+L29+L32+L35 -> 52119.665 | M23: =M26+M29+M32+M35 -> 54400.814 | N23: =N26+N29+N32+N35 -> 56729.897
B24: % growth | G24: =(G23-F23)/F23 -> 0.069027994 | H24: =(H23-G23)/G23 -> 0.028143798 | I24: =(I23-H23)/H23 -> 0.052435281 | J24: =(J23-I23)/I23 -> 0.050043819 | K24: =(K23-J23)/J23 -> 0.047632606 | L24: =(L23-K23)/K23 -> 0.04521307 | M24: =(M23-L23)/L23 -> 0.043767536 | N24: =(N23-M23)/M23 -> 0.04281338
B26: North America | F26: 16973 | G26: 18869 | H26: 19586 | I26: =H26*(1+I102) -> 20663.23 | J26: =I26*(1+J102) -> 21722.221 | K26: =J26*(1+K102) -> 22754.026 | L26: =K26*(1+L102) -> 23749.515 | M26: =L26*(1+M102) -> 24735.12 | N26: =M26*(1+N102) -> 25724.524
B27: % growth | G27: =(G26-F26)/F26 -> 0.11170683 | H27: =(H26-G26)/G26 -> 0.037998834 | I27: =(I26-H26)/H26 -> 0.055 | J27: =(J26-I26)/I26 -> 0.05125 | K27: =(K26-J26)/J26 -> 0.0475 | L27: =(L26-K26)/K26 -> 0.04375 | M27: =(M26-L26)/L26 -> 0.0415 | N27: =(N26-M26)/M26 -> 0.04
B29: EMEA | F29: 10838 | G29: 10958 | H29: 11513 | I29: =H29*(1+I103) -> 12088.65 | J29: =I29*(1+J103) -> 12662.861 | K29: =J29*(1+K103) -> 13232.69 | L29: =K29*(1+L103) -> 13795.079 | M29: =L29*(1+M103) -> 14360.677 | N29: =M29*(1+N103) -> 14935.104
B30: % growth | G30: =(G29-F29)/F29 -> 0.011072154 | H30: =(H29-G29)/G29 -> 0.050647928 | I30: =(I29-H29)/H29 -> 0.05 | J30: =(J29-I29)/I29 -> 0.0475 | K30: =(K29-J29)/J29 -> 0.045 | L30: =(L29-K29)/K29 -> 0.0425 | M30: =(M29-L29)/L29 -> 0.041 | N30: =(N29-M29)/M29 -> 0.04
B32: Latin America | F32: 5834 | G32: 6471 | H32: 6334 | I32: =H32*(1+I104) -> 6714.04 | J32: =I32*(1+J104) -> 7100.0973 | K32: =J32*(1+K104) -> 7490.6027 | L32: =K32*(1+L104) -> 7883.8593 | M32: =L32*(1+M104) -> 8285.9361 | N32: =M32*(1+N104) -> 8700.2329
B33: % growth | G33: =(G32-F32)/F32 -> 0.10918752 | H33: =(H32-G32)/G32 -> -0.02117138 | I33: =(I32-H32)/H32 -> 0.06 | J33: =(J32-I32)/I32 -> 0.0575 | K33: =(K32-J32)/J32 -> 0.055 | L33: =(L32-K32)/K32 -> 0.0525 | M33: =(M32-L32)/L32 -> 0.051 | N33: =(N32-M32)/M32 -> 0.05
B35: Asia Pacific | F35: 5542 | G35: 5594 | H35: 5638 | I35: =H35*(1+I105) -> 5863.52 | J35: =I35*(1+J105) -> 6112.7196 | K35: =J35*(1+K105) -> 6387.792 | L35: =K35*(1+L105) -> 6691.2121 | M35: =L35*(1+M105) -> 7019.0815 | N35: =M35*(1+N105) -> 7370.0356
B36: % growth | G36: =(G35-F35)/F35 -> 0.0093828943 | H36: =(H35-G35)/G35 -> 0.0078655703 | I36: =(I35-H35)/H35 -> 0.04 | J36: =(J35-I35)/I35 -> 0.0425 | K36: =(K35-J35)/J35 -> 0.045 | L36: =(L35-K35)/K35 -> 0.0475 | M36: =(M35-L35)/L35 -> 0.049 | N36: =(N35-M35)/M35 -> 0.05
B38: Bottling Investments | F38: 7860 | G38: 6223 | H38: 5735 | I38: =H38*(1+I108) -> 4874.75 | J38: =I38*(1+J108) -> 4326.3406 | K38: =J38*(1+K108) -> 4001.8651 | L38: =K38*(1+L108) -> 3851.7951 | M38: =L38*(1+M108) -> 3794.0182 | N38: =M38*(1+N108) -> 3794.0182
B39: % growth | G39: =(G38-F38)/F38 -> -0.20826972 | H39: =(H38-G38)/G38 -> -0.078418769 | I39: =(I38-H38)/H38 -> -0.15 | J39: =(J38-I38)/I38 -> -0.1125 | K39: =(K38-J38)/J38 -> -0.075 | L39: =(L38-K38)/K38 -> -0.0375 | M39: =(M38-L38)/L38 -> -0.015 | N39: =(N38-M38)/M38 -> 0
B41: Corporate | F41: 140 | G41: 110 | H41: 144 | I41: =I112 -> 145 | J41: =J112 -> 146.25 | K41: =K112 -> 147.5 | L41: =L112 -> 148.75 | M41: =M112 -> 149.5 | N41: =N112 -> 150
B44: Eliminations | F44: -1433 | G44: -1164 | H44: -1009 | I44: =-(I23+I38)*I113 -> -1004.0838 | J44: =-(J23+J38)*J113 -> -1012.5227 | K44: =-(K23+K38)*K113 -> -1023.4725 | L44: =-(L23+L38)*L113 -> -1035.472 | M44: =-(M23+M38)*M113 -> -1059.146 | N44: =-(N23+N38)*N113 -> -1089.4305
A55: x | B55: Operating Income by Segment | F55: 2023 | G55: 2024 | H55: 2025 | I55: 2026E | J55: 2027E | K55: 2028E | L55: 2029E | M55: 2030E | N55: 2031E
B57: Operating Income | F57: =F60+F75+F78 -> 11311 | G57: =G60+G75+G78 -> 9992 | H57: =H60+H75+H78 -> 13762 | I57: =I60+I75+I78 -> 14733.221 | J57: =J60+J75+J78 -> 15693.65 | K57: =K60+K75+K78 -> 16684.159 | L57: =L60+L75+L78 -> 17702.063 | M57: =M60+M75+M78 -> 18647.502 | N57: =N60+N75+N78 -> 19571.063
B58: % of sales | F58: =F57/F20 -> 0.24721336 | G58: =G57/G20 -> 0.21232018 | H58: =H57/H20 -> 0.28706118 | I58: =I57/I20 -> 0.29857511 | J58: =J57/J20 -> 0.30736927 | K58: =K57/K20 -> 0.3148489 | L58: =L57/L20 -> 0.32136057 | M58: =M57/M20 -> 0.3255205 | N58: =N57/N20 -> 0.32845905
B60: Geographic Segments | F60: =F63+F66+F69+F72 -> 14450 | G60: =G63+G66+G69+G72 -> 14759 | H60: =H63+H66+H69+H72 -> 15152 | I60: =I63+I66+I69+I72 -> 16144.038 | J60: =J63+J66+J69+J72 -> 17114.45 | K60: =K63+K66+K69+K72 -> 18102.708 | L60: =L63+L66+L69+L72 -> 19105.015 | M60: =M63+M66+M69+M72 -> 20064.659 | N60: =N63+N66+N69+N72 -> 21017.136
B61: % margin | F61: =F60/F23 -> 0.36874474 | G61: =G60/G23 -> 0.3523107 | H61: =H60/H23 -> 0.35179123 | I61: =I60/I23 -> 0.35614908 | J61: =J60/J23 -> 0.35956315 | K61: =K60/K23 -> 0.36303355 | L61: =L60/L23 -> 0.36656059 | M61: =M60/M23 -> 0.36883011 | N61: =N60/N23 -> 0.37047725
B63: North America | F63: 4634 | G63: 4556 | H63: 5070 | I63: =I26*I121 -> 5475.7559 | J63: =J26*J121 -> 5837.8468 | K63: =K26*K121 -> 6200.4721 | L63: =L26*L121 -> 6560.8034 | M63: =M26*M121 -> 6888.7308 | N63: =N26*N121 -> 7202.8668
B64: % margin | F64: =F63/F26 -> 0.27302186 | G64: =G63/G26 -> 0.24145424 | H64: =H63/H26 -> 0.25885837 | I64: =I63/I26 -> 0.265 | J64: =J63/J26 -> 0.26875 | K64: =K63/K26 -> 0.2725 | L64: =L63/L26 -> 0.27625 | M64: =M63/M26 -> 0.2785 | N64: =N63/N26 -> 0.28
B66: EMEA | F66: 4323 | G66: 4255 | H66: 4298 | I66: =I29*I122 -> 4533.2437 | J66: =J29*J122 -> 4780.23 | K66: =K29*K122 -> 5028.4221 | L66: =L29*L122 -> 5276.6177 | M66: =M29*M122 -> 5514.5 | N66: =N29*N122 -> 5750.0151
B67: % margin | F67: =F66/F29 -> 0.39887433 | G67: =G66/G29 -> 0.38830078 | H67: =H66/H29 -> 0.37331712 | I67: =I66/I29 -> 0.375 | J67: =J66/J29 -> 0.3775 | K67: =K66/K29 -> 0.38 | L67: =L66/L29 -> 0.3825 | M67: =M66/M29 -> 0.384 | N67: =N66/N29 -> 0.385
B69: Latin America | F69: 3436 | G69: 3792 | H69: 3742 | I69: =I32*I123 -> 3994.8538 | J69: =J32*J123 -> 4242.3081 | K69: =K32*K123 -> 4494.3616 | L69: =L32*L123 -> 4750.0252 | M69: =M32*M123 -> 5004.7054 | N69: =N32*N123 -> 5263.6409
B70: % margin | F70: =F69/F32 -> 0.58896126 | G70: =G69/G32 -> 0.58599907 | H70: =H69/H32 -> 0.59077992 | I70: =I69/I32 -> 0.595 | J70: =J69/J32 -> 0.5975 | K70: =K69/K32 -> 0.6 | L70: =L69/L32 -> 0.6025 | M70: =M69/M32 -> 0.604 | N70: =N69/N32 -> 0.605
B72: Asia Pacific | F72: 2057 | G72: 2156 | H72: 2042 | I72: =I35*I124 -> 2140.1848 | J72: =J35*J124 -> 2254.0654 | K72: =K35*K124 -> 2379.4525 | L72: =L35*L124 -> 2517.5686 | M72: =M35*M124 -> 2656.7223 | N72: =N35*N124 -> 2800.6135
B73: % margin | F73: =F72/F35 -> 0.37116564 | G73: =G72/G35 -> 0.38541294 | H73: =H72/H35 -> 0.36218517 | I73: =I72/I35 -> 0.365 | J73: =J72/J35 -> 0.36875 | K73: =K72/K35 -> 0.3725 | L73: =L72/L35 -> 0.37625 | M73: =M72/M35 -> 0.3785 | N73: =N72/N35 -> 0.38
B75: Bottling Investments | F75: 578 | G75: 496 | H75: 426 | I75: =I38*I125 -> 365.60625 | J75: =J38*J125 -> 340.69932 | K75: =K38*K125 -> 330.15387 | L75: =L38*L125 -> 332.21733 | M75: =M38*M125 -> 335.77061 | N75: =N38*N125 -> 341.46164
B76: % margin | F76: =F75/F38 -> 0.073536896 | G76: =G75/G38 -> 0.079704323 | H76: =H75/H38 -> 0.074280732 | I76: =I75/I38 -> 0.075 | J76: =J75/J38 -> 0.07875 | K76: =K75/K38 -> 0.0825 | L76: =L75/L38 -> 0.08625 | M76: =M75/M38 -> 0.0885 | N76: =N75/N38 -> 0.09
B78: Corporate & Unallocated | F78: -3717 | G78: -5263 | H78: -1816 | I78: =I20*I126 -> -1776.4238 | J78: =J20*J126 -> -1761.4998 | K78: =K20*K126 -> -1748.7031 | L78: =L20*L126 -> -1735.1692 | M78: =M20*M126 -> -1752.9267 | N78: =N20*N126 -> -1787.5345
B79: % of total revenue | F79: =F78/F20 -> -0.081238799 | G79: =G78/G20 -> -0.11183358 | H79: =H78/H20 -> -0.037879894 | I79: =I78/I20 -> -0.036 | J79: =J78/J20 -> -0.0345 | K79: =K78/K20 -> -0.033 | L79: =L78/L20 -> -0.0315 | M79: =M78/M20 -> -0.0306 | N79: =N78/N20 -> -0.03
A97: x | B97: Core Levers | I97: 2026E | J97: 2027E | K97: 2028E | L97: 2029E | M97: 2030E | N97: 2031E
B99: Ramp Weight | I99: 0 | J99: 0.25 | K99: 0.5 | L99: 0.75 | M99: 0.9 | N99: 1
B101: Revenue Growth by Segment
B102: North America | I102: =D6 -> 0.055 | J102: =$I102+($N102-$I102)*J$99 -> 0.05125 | K102: =$I102+($N102-$I102)*K$99 -> 0.0475 | L102: =$I102+($N102-$I102)*L$99 -> 0.04375 | M102: =$I102+($N102-$I102)*M$99 -> 0.0415 | N102: =E6 -> 0.04
B103: EMEA | I103: =D7 -> 0.05 | J103: =$I103+($N103-$I103)*J$99 -> 0.0475 | K103: =$I103+($N103-$I103)*K$99 -> 0.045 | L103: =$I103+($N103-$I103)*L$99 -> 0.0425 | M103: =$I103+($N103-$I103)*M$99 -> 0.041 | N103: =E7 -> 0.04
B104: Latin America | I104: =D8 -> 0.06 | J104: =$I104+($N104-$I104)*J$99 -> 0.0575 | K104: =$I104+($N104-$I104)*K$99 -> 0.055 | L104: =$I104+($N104-$I104)*L$99 -> 0.0525 | M104: =$I104+($N104-$I104)*M$99 -> 0.051 | N104: =E8 -> 0.05
B105: Asia Pacific | I105: =D9 -> 0.04 | J105: =$I105+($N105-$I105)*J$99 -> 0.0425 | K105: =$I105+($N105-$I105)*K$99 -> 0.045 | L105: =$I105+($N105-$I105)*L$99 -> 0.0475 | M105: =$I105+($N105-$I105)*M$99 -> 0.049 | N105: =E9 -> 0.05
B107: Other Segments
B108: Bottling Investments Growth | I108: =D10 -> -0.15 | J108: =$I108+($N108-$I108)*J$99 -> -0.1125 | K108: =$I108+($N108-$I108)*K$99 -> -0.075 | L108: =$I108+($N108-$I108)*L$99 -> -0.0375 | M108: =$I108+($N108-$I108)*M$99 -> -0.015 | N108: =E10 -> 0
B111: Corporate & Eliminations
B112: Corporate Revenue ($M) | I112: =D12 -> 145 | J112: =$I112+($N112-$I112)*J$99 -> 146.25 | K112: =$I112+($N112-$I112)*K$99 -> 147.5 | L112: =$I112+($N112-$I112)*L$99 -> 148.75 | M112: =$I112+($N112-$I112)*M$99 -> 149.5 | N112: =E12 -> 150
B113: Eliminations % of Gross Rev | I113: =D13 -> 0.02 | J113: =$I113+($N113-$I113)*J$99 -> 0.0195 | K113: =$I113+($N113-$I113)*K$99 -> 0.019 | L113: =$I113+($N113-$I113)*L$99 -> 0.0185 | M113: =$I113+($N113-$I113)*M$99 -> 0.0182 | N113: =E13 -> 0.018
B115: Revenue Mix
B116: Concentrate % of Revenue | I116: =D14 -> 0.595 | J116: =$I116+($N116-$I116)*J$99 -> 0.5975 | K116: =$I116+($N116-$I116)*K$99 -> 0.6 | L116: =$I116+($N116-$I116)*L$99 -> 0.6025 | M116: =$I116+($N116-$I116)*M$99 -> 0.604 | N116: =E14 -> 0.605
B120: Operating Margins by Segment
B121: North America | I121: =I6 -> 0.265 | J121: =$I121+($N121-$I121)*J$99 -> 0.26875 | K121: =$I121+($N121-$I121)*K$99 -> 0.2725 | L121: =$I121+($N121-$I121)*L$99 -> 0.27625 | M121: =$I121+($N121-$I121)*M$99 -> 0.2785 | N121: =J6 -> 0.28
B122: EMEA | I122: =I7 -> 0.375 | J122: =$I122+($N122-$I122)*J$99 -> 0.3775 | K122: =$I122+($N122-$I122)*K$99 -> 0.38 | L122: =$I122+($N122-$I122)*L$99 -> 0.3825 | M122: =$I122+($N122-$I122)*M$99 -> 0.384 | N122: =J7 -> 0.385
B123: Latin America | I123: =I8 -> 0.595 | J123: =$I123+($N123-$I123)*J$99 -> 0.5975 | K123: =$I123+($N123-$I123)*K$99 -> 0.6 | L123: =$I123+($N123-$I123)*L$99 -> 0.6025 | M123: =$I123+($N123-$I123)*M$99 -> 0.604 | N123: =J8 -> 0.605
B124: Asia Pacific | I124: =I9 -> 0.365 | J124: =$I124+($N124-$I124)*J$99 -> 0.36875 | K124: =$I124+($N124-$I124)*K$99 -> 0.3725 | L124: =$I124+($N124-$I124)*L$99 -> 0.37625 | M124: =$I124+($N124-$I124)*M$99 -> 0.3785 | N124: =J9 -> 0.38
B125: Bottling Investments | I125: =I10 -> 0.075 | J125: =$I125+($N125-$I125)*J$99 -> 0.07875 | K125: =$I125+($N125-$I125)*K$99 -> 0.0825 | L125: =$I125+($N125-$I125)*L$99 -> 0.08625 | M125: =$I125+($N125-$I125)*M$99 -> 0.0885 | N125: =J10 -> 0.09
B126: Corporate Expense % of Rev | I126: =I12 -> -0.036 | J126: =$I126+($N126-$I126)*J$99 -> -0.0345 | K126: =$I126+($N126-$I126)*K$99 -> -0.033 | L126: =$I126+($N126-$I126)*L$99 -> -0.0315 | M126: =$I126+($N126-$I126)*M$99 -> -0.0306 | N126: =J12 -> -0.03
A135: x | B135: Brand & Category Build — Estimated Revenue Share
B137: Trademark Coca-Cola (incl. Coke Zero Sugar) | H137: 0.45 | I137: 0.45 | J137: =$I137+($N137-$I137)*J$99 -> 0.4475 | K137: =$I137+($N137-$I137)*K$99 -> 0.445 | L137: =$I137+($N137-$I137)*L$99 -> 0.4425 | M137: =$I137+($N137-$I137)*M$99 -> 0.441 | N137: 0.44
B138: Sparkling Flavors (Sprite, Fanta, etc.) | H138: 0.21 | I138: 0.21 | J138: =$I138+($N138-$I138)*J$99 -> 0.2075 | K138: =$I138+($N138-$I138)*K$99 -> 0.205 | L138: =$I138+($N138-$I138)*L$99 -> 0.2025 | M138: =$I138+($N138-$I138)*M$99 -> 0.201 | N138: 0.2
B139: Water, Sports, Coffee & Tea (smartwater, BODYARMOR, Costa) | H139: 0.24 | I139: 0.24 | J139: =$I139+($N139-$I139)*J$99 -> 0.2425 | K139: =$I139+($N139-$I139)*K$99 -> 0.245 | L139: =$I139+($N139-$I139)*L$99 -> 0.2475 | M139: =$I139+($N139-$I139)*M$99 -> 0.249 | N139: 0.25
B140: Juice, Value-Added Dairy & Plant (Minute Maid, fairlife) | H140: 0.1 | I140: 0.1 | J140: =$I140+($N140-$I140)*J$99 -> 0.1025 | K140: =$I140+($N140-$I140)*K$99 -> 0.105 | L140: =$I140+($N140-$I140)*L$99 -> 0.1075 | M140: =$I140+($N140-$I140)*M$99 -> 0.109 | N140: 0.11
B141: Total (must equal 100%) | H141: =SUM(H137:H140) -> 1 | I141: =SUM(I137:I140) -> 1 | J141: =SUM(J137:J140) -> 1 | K141: =SUM(K137:K140) -> 1 | L141: =SUM(L137:L140) -> 1 | M141: =SUM(M137:M140) -> 1 | N141: =SUM(N137:N140) -> 1
B143: Estimated Revenue by Category ($M)
B144: Trademark Coca-Cola | H144: =H137*H$20 -> 21573.45 | I144: =I137*I$20 -> 22205.298 | J144: =J137*J$20 -> 22848.44 | K144: =K137*K$20 -> 23580.996 | L144: =L137*L$20 -> 24374.997 | M144: =M137*M$20 -> 25262.767 | N144: =N137*N$20 -> 26217.173
B145: Sparkling Flavors (Sprite, Fanta, etc.) | H145: =H138*H$20 -> 10067.61 | I145: =I138*I$20 -> 10362.472 | J145: =J138*J$20 -> 10594.528 | K145: =K138*K$20 -> 10863.156 | L145: =L138*L$20 -> 11154.659 | M145: =M138*M$20 -> 11514.322 | N145: =N138*N$20 -> 11916.897
B146: Water, Sports, Coffee & Tea | H146: =H139*H$20 -> 11505.84 | I146: =I139*I$20 -> 11842.825 | J146: =J139*J$20 -> 12381.557 | K146: =K139*K$20 -> 12982.796 | L146: =L139*L$20 -> 13633.473 | M146: =M139*M$20 -> 14264.011 | N146: =N139*N$20 -> 14896.121
B147: Juice, Value-Added Dairy & Plant-Based | H147: =H140*H$20 -> 4794.1 | I147: =I140*I$20 -> 4934.5106 | J147: =J140*J$20 -> 5233.4415 | K147: =K140*K$20 -> 5564.0553 | L147: =L140*L$20 -> 5921.6093 | M147: =M140*M$20 -> 6244.0853 | N147: =N140*N$20 -> 6554.2933
B148: Total | H148: =SUM(H144:H147) -> 47941 | I148: =SUM(I144:I147) -> 49345.106 | J148: =SUM(J144:J147) -> 51057.966 | K148: =SUM(K144:K147) -> 52991.003 | L148: =SUM(L144:L147) -> 55084.738 | M148: =SUM(M144:M147) -> 57285.187 | N148: =SUM(N144:N147) -> 59584.485
B150: memo: 33.8B unit cases sold in 2025; sparkling 69% / Trademark Coca-Cola 47% of volume
A153: x | B153: Concentrate vs. Finished Products ($M) | F153: 2023 | G153: 2024 | H153: 2025 | I153: 2026E | J153: 2027E | K153: 2028E | L153: 2029E | M153: 2030E | N153: 2031E | Q153: Foundry Capacity / Supply Build | U153: 2031E | W153: External Foundry Revenue Build | AA153: 2031E
B155: Concentrate Operations | F155: 26539 | G155: 27725 | H155: 28462 | I155: =I20*I116 -> 29360.338 | J155: =J20*J116 -> 30507.135 | K155: =K20*K116 -> 31794.602 | L155: =L20*L116 -> 33188.555 | M155: =M20*M116 -> 34600.253 | N155: =N20*N116 -> 36048.613 | Q155: =B171 -> 0 | U155: =N171 -> 0 | W155: =Q159 -> External Foundry Sold WSPM | AA155: =U159 -> 0
B156: % of revenue | F156: =F155/F20 -> 0.58003672 | G156: =G155/G20 -> 0.589129 | H156: =H155/H20 -> 0.59368807 | I156: =I155/I20 -> 0.595 | J156: =J155/J20 -> 0.5975 | K156: =K155/K20 -> 0.6 | L156: =L155/L20 -> 0.6025 | M156: =M155/M20 -> 0.604 | N156: =N155/N20 -> 0.605 | Q156: Usable Capacity | U156: =N157 -> 0 | W156: Revenue / Wafer | AA156: =J7 -> 0.385
Q157: Usable WSPM | U157: =N172 -> 0 | W157: Core External Wafer Revenue | AA157: =AA160-AA158-AA159 -> -1103.3105
B158: Finished Products Operations | F158: 19215 | G158: 19336 | H158: 19479 | I158: =I20-I155 -> 19984.768 | J158: =J20-J155 -> 20550.831 | K158: =K20-K155 -> 21196.401 | L158: =L20-L155 -> 21896.183 | M158: =M20-M155 -> 22684.934 | N158: =N20-N155 -> 23535.871 | Q158: Internal Product WSPM Need | U158: =N173 -> 0 | W158: EMIB / Packaging Revenue | AA158: =J9 -> 0.38
B159: % of revenue | F159: =F158/F20 -> 0.41996328 | G159: =G158/G20 -> 0.410871 | H159: =H158/H20 -> 0.40631193 | I159: =I158/I20 -> 0.405 | J159: =J158/J20 -> 0.4025 | K159: =K158/K20 -> 0.4 | L159: =L158/L20 -> 0.3975 | M159: =M158/M20 -> 0.396 | N159: =N158/N20 -> 0.395 | Q159: External Foundry Sold WSPM | U159: =N174 -> 0 | W159: TeraFab Contribution | AA159: =J10*E12 -> 13.5
Q160: Excess / Shortfall WSPM | U160: =N175 -> 0 | W160: External Foundry Revenue | AA160: =N44 -> -1089.4305
B161: Total | F161: =F155+F158 -> 45754 | G161: =G155+G158 -> 47061 | H161: =H155+H158 -> 47941 | I161: =I155+I158 -> 49345.106 | J161: =J155+J158 -> 51057.966 | K161: =K155+K158 -> 52991.003 | L161: =L155+L158 -> 55084.738 | M161: =M155+M158 -> 57285.187 | N161: =N155+N158 -> 59584.485
A174: x
B176: Revenue Check (vs Main) | I176: =I20-Main!K28 -> 0 | J176: =J20-Main!L28 -> 0 | K176: =K20-Main!M28 -> 0 | L176: =L20-Main!N28 -> 0 | M176: =M20-Main!O28 -> 0 | N176: =N20-Main!P28 -> 0
B177: Op Income Check (vs Main) | I177: =I57-Main!K46 -> 0 | J177: =J57-Main!L46 -> 0 | K177: =K57-Main!M46 -> 0 | L177: =L57-Main!N46 -> 0 | M177: =M57-Main!O46 -> 0 | N177: =N57-Main!P46 -> 0
B178: Category Build Check (vs Revenue) | I178: =I148-I20 -> 0 | J178: =J148-J20 -> 0 | K178: =K148-K20 -> 0 | L178: =L148-L20 -> 0 | M178: =M148-M20 -> 0 | N178: =N148-N20 -> 0
B179: Category Share Check (=100%) | I179: =I141-1 -> 0 | J179: =J141-1 -> 0 | K179: =K141-1 -> 0 | L179: =L141-1 -> 0 | M179: =M141-1 -> 0 | N179: =N141-1 -> 0
AB184: =D182 -> 0 | AC184: =E182 -> 0 | AD184: =F182 -> 0 | AE184: =G182 -> 0 | AF184: =H182 -> 0 | AG184: =I182 -> 0
AA185: Non-AI CPU TAM | AB185: =(D190-D189)/1000 -> 0 | AC185: =(E190-E189)/1000 -> 0 | AD185: =(F190-F189)/1000 -> 0 | AE185: =(G190-G189)/1000 -> 0 | AF185: =(H190-H189)/1000 -> 0 | AG185: =(I190-I189)/1000 -> 0
AA186: AI CPU TAM | AB186: =D189/1000 -> 0 | AC186: =E189/1000 -> 0 | AD186: =F189/1000 -> 0 | AE186: =G189/1000 -> 0 | AF186: =H189/1000 -> 0 | AG186: =I189/1000 -> 0 | AH186: 0.01
AA187: Total | AB187: =D190/1000 -> 0 | AC187: =E190/1000 -> 0 | AD187: =F190/1000 -> 0 | AE187: =G190/1000 -> 0 | AF187: =H190/1000 -> 0 | AG187: =I190/1000 -> 0

Sheet Extras
M3: Current Share Price | N3: 82.63

Sheet Quarterly Segments
H2: Sep '24 | I2: Dec '24 | J2: Mar '25 | K2: Jun '25 | L2: Sep '25 | M2: Dec '25 | N2: Mar '26E | O2: Jun '26E | P2: Sep '26E | Q2: Dec '26E | R2: Mar '27E
H3: FY 25 | L3: FY 26 | P3: FY 27
B4: Quarterly Product Segments | H4: Q1 | I4: Q2 | J4: Q3 | K4: Q4 | L4: Q1 | M4: Q2 | N4: Q3 | O4: Q4 | P4: Q1 | Q4: Q2 | R4: Q3
