Workbook

Sheet Main
Q2: all values in millions except per share numbers
A4: x | B4: Company Overview | W4: 10 Year DCF | Y4: 2032 | Z4: =Y4+1 -> 2033 | AA4: =Z4+1 -> 2034 | AB4: =AA4+1 -> 2035 | AC4: =AB4+1 -> 2036
B6: Price | G6: Key Stats | M6: Valuation | R6: Notes | W6: Revenue | Y6: =N101*1.24 -> 258361.47 | Z6: =Y6*1.22 -> 315200.99 | AA6: =Z6*1.18 -> 371937.17 | AB6: =AA6*1.15 -> 427727.74 | AC6: =AB6*1.1 -> 470500.52
B7: Ticker | E7: SPCE | G7: Employees | I7: 13000 | M7: PV of FCF | P7: =SUM(I113:N113) -> -60139.328 | R7: WACC | U7: 0.1 | W7: % growth | Y7: =(Y6-N101)/N101 -> 0.24 | Z7: =(Z6-Y6)/Y6 -> 0.22 | AA7: =(AA6-Z6)/Z6 -> 0.18 | AB7: =(AB6-AA6)/AA6 -> 0.15 | AC7: =(AC6-AB6)/AB6 -> 0.1
B8: Implied Share Price | E8: =AVERAGE((P13/P12),(T23)) -> 184.35501 | G8: Founded | I8: 37329 | M8: Terminal Value | P8: =(N52*U8) -> 1709898.1 | R8: EV/EBITDA Multiple | U8: 25
B9: Price | E9: =1750000/H18 -> 301.82822 | G9: CEO | I9: Elon Musk | M9: PV of Terminal Value | P9: =-(PV(U7,(DATE(2031,12,31)-$D$12)/365,0,P8)) -> 1000869.3
B10: Implied Upside / (Downside) | E10: =E8/E9-1 -> -0.38920553 | G10: Headquarters | I10: Starbase, Texas | M10: Net Debt | P10: =H22-H21 -> 14413 | W10: Free Cash Flow | Y10: =Y6*0.22 -> 56839.523 | Z10: =Z6*0.23 -> 72496.228 | AA10: =AA6*0.24 -> 89264.92 | AB10: =AB6*0.25 -> 106931.94 | AC10: =AC6*0.25 -> 117625.13
B11: IRR | E11: =(I17/E9)^(1/2)-1 -> -0.11622038 | G11: Primary Industry | I11: Aerospace / Satcom / AI | M11: Bitcoin | P11: 1293 | W11: % of sales | Y11: 0.19 | Z11: 0.22 | AA11: 0.25 | AB11: 0.27 | AC11: 0.28
B12: Last Updated | D12: 46162 | G12: Fiscal Year End | I12: 46387 | M12: Shares Outstanding | P12: 5026
M13: Implied Market Cap | P13: =P9+P7-P10+P11 -> 927609.96 | R13: Share Price | U13: =P13/P12 -> 184.56227 | W13: Present Value of FCF | Y13: =Y10/(1+$U$7)^((DATE(2032,7,1)-$D$12)/365) -> 31717.906 | Z13: =Z10/(1+$U$7)^((DATE(2033,7,1)-$D$12)/365) -> 36777.043 | AA13: =AA10/(1+$U$7)^((DATE(2034,7,1)-$D$12)/365) -> 41167.03 | AB13: =AB10/(1+$U$7)^((DATE(2035,7,1)-$D$12)/365) -> 44831.52 | AC13: =AC10/(1+$U$7)^((DATE(2036,7,1)-$D$12)/365) -> 44819.814
A15: x | B15: Key Statistics | E15: 2023 | F15: 2024 | G15: 2025 | H15: 2026E | I15: 2027E | J15: 2028E | M15: Financial Ratios | R15: Gordon Growth Method
B17: Stock Price | E17: =180000/E18 -> 65.241029 | F17: =350000/F18 -> 122.89326 | G17: =800000/G18 -> 273.4108 | H17: =AVERAGE($U$13*(1+$U$7)-I110/H18,$T$23*(1+$U$7)-I110/H18) -> 209.75669 | I17: =AVERAGE($U$13*(1+$U$7)^2-(I110/H18)*(1+$U$7)-J110/I18,$T$23*(1+$U$7)^2-(I110/H18)*(1+$U$7)-J110/I18) -> 235.74788 | M17: PV of FCF | P17: =SUM(H116:L116) -> 0 | R17: FCF Value | T17: =SUM(I112:N112)+SUM((Y13:AC13)) -> 199313.31
B18: shares outstanding | E18: =F70 -> 2759 | F18: =G70 -> 2848 | G18: =H70 -> 2926 | H18: =I120 -> 5798 | I18: =J120 -> 6029.92 | M18: Market Cap | P18: =E9*P12 -> 1516988.6 | R18: Terminal Value | T18: =(AC10*(1+0.04)/($U$7-0.04))/(1+$U$7)^((DATE(2036,12,31)-$D$12)/365) -> 740626.25
M19: Enterprise Value | P19: =P18+P10 -> 1531401.6 | R19: Net Debt | T19: =P10 -> 14413
B20: Market Cap | E20: =E17*E18 -> 180000 | F20: =F17*F18 -> 350000 | G20: =G17*G18 -> 800000 | H20: =H17*H18 -> 1216169.3 | I20: =I17*I18 -> 1421540.9 | M20: P/E (LTM) | P20: =$P$18/H67 -> -307.26932 | R20: Strategic Investments
B21: Cash | E21: 4620 | F21: 11385 | G21: 24744 | H21: 15852 | M21: P/E (NTM) | P21: =$P$18/I67 -> -216.61535 | R21: Total | T21: =T17+T18-T19+T20 -> 925526.56
B22: Debt | F22: =13421+372 -> 13793 | G22: =21968+928 -> 22896 | H22: =28727+1538 -> 30265 | M22: EV/EBITDA (LTM) | P22: =P19/(H49+H78) -> 372.42257
B23: Enterprise Value | E23: =E20-E21+E22 -> 175380 | F23: =F20-F21+F22 -> 352408 | G23: =G20-G21+G22 -> 798152 | H23: =H20-H21+H22 -> 1230582.3 | I23: =I20-I21+I22 -> 1421540.9 | M23: EV/EBITDA (NTM) | P23: =P19/(I49+I78) -> 798.49687 | R23: Share Price | T23: =T21/P12 -> 184.14774
M24: EV/EBIT (LTM) | P24: =P19/H49 -> -591.50314
A26: x | B26: Income Statement ($M) | F26: 2023 | G26: 2024 | H26: 2025 | I26: 2026E | J26: 2027E | K26: 2028E | L26: 2029E | M26: 2030E | N26: 2031E
B28: Revenue | F28: 10387 | G28: 14015 | H28: 18674 | I28: =Segments!I14 -> 31125.087 | J28: =Segments!J14 -> 50787.839 | K28: =Segments!K14 -> 78808.082 | L28: =Segments!L14 -> 117434.13 | M28: =Segments!M14 -> 161900.47 | N28: =Segments!N14 -> 208356.02
B29: % growth | G29: =(G28-F28)/F28 -> 0.34928276 | H29: =(H28-G28)/G28 -> 0.33242954 | I29: =(I28-H28)/H28 -> 0.66676056 | J29: =(J28-I28)/I28 -> 0.63173327 | K29: =(K28-J28)/J28 -> 0.55171166 | L29: =(L28-K28)/K28 -> 0.49012803 | M29: =(M28-L28)/L28 -> 0.37864921 | N29: =(N28-M28)/M28 -> 0.28693893
B31: COGS | F31: 6110 | G31: 7996 | H31: 9451 | I31: =I28*0.5 -> 15562.543 | J31: =J28*0.49 -> 24886.041 | K31: =K28*0.48 -> 37827.88 | L31: =L28*0.47 -> 55194.042 | M31: =M28*0.46 -> 74474.218 | N31: =N28*0.45 -> 93760.21
B32: % of sales | F32: =F31/F28 -> 0.58823529 | G32: =G31/G28 -> 0.57053157 | H32: =H31/H28 -> 0.50610474 | I32: =I31/I28 -> 0.5 | J32: =J31/J28 -> 0.49 | K32: =K31/K28 -> 0.48 | L32: =L31/L28 -> 0.47 | M32: =M31/M28 -> 0.46 | N32: =N31/N28 -> 0.45
B34: Gross Profit | F34: =F28-F31 -> 4277 | G34: =G28-G31 -> 6019 | H34: =H28-H31 -> 9223 | I34: =I28-I31 -> 15562.543 | J34: =J28-J31 -> 25901.798 | K34: =K28-K31 -> 40980.203 | L34: =L28-L31 -> 62240.09 | M34: =M28-M31 -> 87426.256 | N34: =N28-N31 -> 114595.81
B35: % of sales | F35: =F34/F28 -> 0.41176471 | G35: =G34/G28 -> 0.42946843 | H35: =H34/H28 -> 0.49389526 | I35: =I34/I28 -> 0.5 | J35: =J34/J28 -> 0.51 | K35: =K34/K28 -> 0.52 | L35: =L34/L28 -> 0.53 | M35: =M34/M28 -> 0.54 | N35: =N34/N28 -> 0.55
B37: Research & Development | F37: 2105 | G37: 3464 | H37: 8643 | I37: =I28*0.6 -> 18675.052 | J37: =J28*0.3 -> 15236.352 | K37: =K28*0.2 -> 15761.616 | L37: =L28*0.2 -> 23486.827 | M37: =M28*0.2 -> 32380.095 | N37: =N28*0.2 -> 41671.204
B38: % of sales | F38: =F37/F$28 -> 0.20265717 | G38: =G37/G$28 -> 0.24716375 | H38: =H37/H$28 -> 0.46283603 | I38: =I37/I$28 -> 0.6 | J38: =J37/J$28 -> 0.3 | K38: =K37/K$28 -> 0.2 | L38: =L37/L$28 -> 0.2 | M38: =M37/M$28 -> 0.2 | N38: =N37/N$28 -> 0.2
B40: SG&A | F40: 1665 | G40: 1813 | H40: 2644 | I40: =I28*0.125 -> 3890.6358 | J40: =J28*0.12 -> 6094.5407 | K40: =K28*0.115 -> 9062.9295 | L40: =L28*0.11 -> 12917.755 | M40: =M28*0.105 -> 16999.55 | N40: =N28*0.1 -> 20835.602
B41: % of sales | F41: =F40/F$28 -> 0.16029652 | G41: =G40/G$28 -> 0.1293614 | H41: =H40/H$28 -> 0.14158723 | I41: =I40/I$28 -> 0.125 | J41: =J40/J$28 -> 0.12 | K41: =K40/K$28 -> 0.115 | L41: =L40/L$28 -> 0.11 | M41: =M40/M$28 -> 0.105 | N41: =N40/N$28 -> 0.1
B43: Restructuring | F43: 237 | G43: 213 | H43: 487
B44: % of sales | F44: =F43/F$28 -> 0.022816983 | G44: =G43/G$28 -> 0.015198002 | H44: =H43/H$28 -> 0.02607904 | I44: =I43/I$28 -> 0 | J44: =J43/J$28 -> 0 | K44: =K43/K$28 -> 0 | L44: =L43/L$28 -> 0 | M44: =M43/M$28 -> 0 | N44: =N43/N$28 -> 0
B46: Impairment | F46: 3775 | G46: 63 | H46: 38 | J46: 0 | K46: 0 | L46: 0 | M46: 0 | N46: 0
B47: % of sales | F47: =F46/F$28 -> 0.36343506 | G47: =G46/G$28 -> 0.0044951837 | H47: =H46/H$28 -> 0.0020349149 | I47: =I46/I$28 -> 0 | J47: =J46/J$28 -> 0 | K47: =K46/K$28 -> 0 | L47: =L46/L$28 -> 0 | M47: =M46/M$28 -> 0 | N47: =N46/N$28 -> 0
B49: Operating Income (EBIT) | F49: =F34-F37-F40-F43-F46 -> -3505 | G49: =G34-G37-G40-G43-G46 -> 466 | H49: =H34-H37-H40-H43-H46 -> -2589 | I49: =I34-I37-I40-I43-I46 -> -7003.1445 | J49: =J34-J37-J40-J43-J46 -> 4570.9055 | K49: =K34-K37-K40-K43-K46 -> 16155.657 | L49: =L34-L37-L40-L43-L46 -> 25835.509 | M49: =M34-M37-M40-M43-M46 -> 38046.611 | N49: =N34-N37-N40-N43-N46 -> 52089.005
B50: % of sales | F50: =F49/F$28 -> -0.33744103 | G50: =G49/G$28 -> 0.033250089 | H50: =H49/H$28 -> -0.13864196 | I50: =I49/I$28 -> -0.225 | J50: =J49/J$28 -> 0.09 | K50: =K49/K$28 -> 0.205 | L50: =L49/L$28 -> 0.22 | M50: =M49/M$28 -> 0.235 | N50: =N49/N$28 -> 0.25
B52: EBITDA | F52: =F49+F78 -> -870 | G52: =G49+G78 -> 4290 | H52: =H49+H78 -> 4112 | I52: =I49+I78 -> 1917.8555 | J52: =J49+J78 -> 16837.281 | K52: =K49+K78 -> 33083.254 | L52: =L49+L78 -> 41634.6 | M52: =M49+M78 -> 53394.3 | N52: =N49+N78 -> 68395.924
B53: % of sales | F53: =F52/F$28 -> -0.083758544 | G53: =G52/G$28 -> 0.30610061 | H53: =H52/H$28 -> 0.22019921 | I53: =I52/I$28 -> 0.061617676 | J53: =J52/J$28 -> 0.33152189 | K53: =K52/K$28 -> 0.4197952 | L53: =L52/L$28 -> 0.35453577 | M53: =M52/M$28 -> 0.32979706 | N53: =N52/N$28 -> 0.32826469
B55: Interest Income (Expense) | F55: =249-1693 -> -1444 | G55: =371-1580 -> -1209 | H55: =492-1945 -> -1453
B56: % of sales | F56: =F55/F$28 -> -0.13901993 | G56: =G55/G$28 -> -0.086264716 | H56: =H55/H$28 -> -0.077808718 | I56: =I55/I$28 -> 0 | J56: =J55/J$28 -> 0 | K56: =K55/K$28 -> 0 | L56: =L55/L$28 -> 0 | M56: =M55/M$28 -> 0 | N56: =N55/N$28 -> 0
N57: 0
B58: Other Income | F58: -42 | G58: 985 | H58: -177 | I58: 0 | J58: 0 | K58: 0 | L58: 0 | M58: 0 | N58: =N57/N$28 -> 0
B59: % of sales | F59: =F58/F$28 -> -0.0040435159 | G59: =G58/G$28 -> 0.070281841 | H59: =H58/H$28 -> -0.0094784192 | I59: =I58/I$28 -> 0 | J59: =J58/J$28 -> 0 | K59: =K58/K$28 -> 0 | L59: =L58/L$28 -> 0 | M59: =M58/M$28 -> 0
B61: Income Before Taxes | F61: =F49+F55+F58 -> -4991 | G61: =G49+G55+G58 -> 242 | H61: =H49+H55+H58 -> -4219 | I61: =I49+I58 -> -7003.1445 | J61: =J49+J58 -> 4570.9055 | K61: =K49+K58 -> 16155.657 | L61: =L49+L58 -> 25835.509 | M61: =M49+M58 -> 38046.611 | N61: =N49+N58 -> 52089.005
B62: % of sales | F62: =F61/F$28 -> -0.48050448 | G62: =G61/G$28 -> 0.017267214 | H62: =H61/H$28 -> -0.2259291 | I62: =I61/I$28 -> -0.225 | J62: =J61/J$28 -> 0.09 | K62: =K61/K$28 -> 0.205 | L62: =L61/L$28 -> 0.22 | M62: =M61/M$28 -> 0.235 | N62: =N61/N$28 -> 0.25
B64: Provision for Income Taxes | F64: -363 | G64: -549 | H64: 718 | I64: =IF(I61>0,I61*0.12,0) -> 0 | J64: =IF(J61>0,J61*0.12,0) -> 548.50866 | K64: =IF(K61>0,K61*0.13,0) -> 2100.2354 | L64: =IF(L61>0,L61*0.14,0) -> 3616.9713 | M64: =IF(M61>0,M61*0.15,0) -> 5706.9917 | N64: =IF(N61>0,N61*0.16,0) -> 8334.2409
B65: Tax Rate % | F65: =F64/F61 -> 0.072730916 | G65: =G64/G61 -> -2.268595 | H65: =H64/H61 -> -0.17018251 | I65: =I64/I61 -> 0 | J65: =J64/J61 -> 0.12 | K65: =K64/K61 -> 0.13 | L65: =L64/L61 -> 0.14 | M65: =M64/M61 -> 0.15 | N65: =N64/N61 -> 0.16
B67: Net Income | F67: =F61-F64 -> -4628 | G67: =G61-G64-773 -> 18 | H67: =H61-H64 -> -4937 | I67: =I61-I64 -> -7003.1445 | J67: =J61-J64 -> 4022.3969 | K67: =K61-K64 -> 14055.422 | L67: =L61-L64 -> 22218.538 | M67: =M61-M64 -> 32339.62 | N67: =N61-N64 -> 43754.765
B68: % of sales | F68: =F67/F$28 -> -0.44555695 | G68: =G67/G$28 -> 0.0012843382 | H68: =H67/H$28 -> -0.26437828 | I68: =I67/I$28 -> -0.225 | J68: =J67/J$28 -> 0.0792 | K68: =K67/K$28 -> 0.17835 | L68: =L67/L$28 -> 0.1892 | M68: =M67/M$28 -> 0.19975 | N68: =N67/N$28 -> 0.21
B70: Shares Outsanding | F70: 2759 | G70: 2848 | H70: 2926 | I70: 5798 | J70: =I70*1.04 -> 6029.92 | K70: =J70*1.02 -> 6150.5184 | L70: =K70*1.02 -> 6273.5288 | M70: =L70*1.02 -> 6398.9993 | N70: =M70*1.02 -> 6526.9793
B71: % growth | G71: =(G70-F70)/F70 -> 0.032258065 | H71: =(H70-G70)/G70 -> 0.02738764 | I71: =(I70-H70)/H70 -> 0.98154477 | J71: =(J70-I70)/I70 -> 0.04 | K71: =(K70-J70)/J70 -> 0.02 | L71: =(L70-K70)/K70 -> 0.02 | M71: =(M70-L70)/L70 -> 0.02 | N71: =(N70-M70)/M70 -> 0.02
B73: EPS | F73: =F67/F70 -> -1.6774194 | G73: =G67/G70 -> 0.0063202247 | H73: =H67/H70 -> -1.6872864 | I73: =I67/I70 -> -1.2078552 | J73: =J67/J70 -> 0.66707301 | K73: =K67/K70 -> 2.2852418 | L73: =L67/L70 -> 3.5416332 | M73: =M67/M70 -> 5.0538558 | N73: =N67/N70 -> 6.7036775
B74: % growth | G74: =(G73-F73)/F73 -> -1.0037678 | H74: =(H73-G73)/G73 -> -267.9662 | I74: =(I73-H73)/H73 -> -0.28414334 | J74: =(J73-I73)/I73 -> -1.552279 | K74: =(K73-J73)/J73 -> 2.4257746 | L74: =(L73-K73)/K73 -> 0.54978492 | M74: =(M73-L73)/L73 -> 0.42698451 | N74: =(N73-M73)/M73 -> 0.32644813
A76: x | B76: Cash Flow Items | F76: 2023 | G76: 2024 | H76: 2025 | I76: 2026E | J76: 2027E | K76: 2028E | L76: 2029E | M76: 2030E | N76: 2031E
B78: D&A | F78: 2635 | G78: 3824 | H78: 6701 | I78: =I82*0.2 -> 8921 | J78: =J82*0.25 -> 12266.375 | K78: =K82*0.3 -> 16927.597 | L78: =L82*0.35 -> 15799.091 | M78: =M82*0.4 -> 15347.688 | N78: =N82*0.5 -> 16306.919
B79: % of capex | F79: =F78/F82 -> 0.59682899 | G79: =G78/G82 -> 0.34256024 | H79: =H78/H82 -> 0.32314221 | I79: =I78/I82 -> 0.2 | J79: =J78/J82 -> 0.25 | K79: =K78/K82 -> 0.3 | L79: =L78/L82 -> 0.35 | M79: =M78/M82 -> 0.4 | N79: =N78/N82 -> 0.5
B80: % of sales | F80: =F78/F$28 -> 0.25368249 | G80: =G78/G$28 -> 0.27285052 | H80: =H78/H$28 -> 0.35884117 | I80: =I78/I$28 -> 0.28661768 | J80: =J78/J$28 -> 0.24152189 | K80: =K78/K$28 -> 0.2147952 | L80: =L78/L$28 -> 0.13453577 | M80: =M78/M$28 -> 0.094797057 | N80: =N78/N$28 -> 0.078264688
B82: CapEx | F82: 4415 | G82: 11163 | H82: 20737 | I82: =Segments!I72 -> 44605 | J82: =I82*1.1 -> 49065.5 | K82: =J82*1.15 -> 56425.325 | L82: =K82*0.8 -> 45140.26 | M82: =L82*0.85 -> 38369.221 | N82: =M82*0.85 -> 32613.838
B83: % of sales | F83: =F82/F28 -> 0.42505054 | G83: =G82/G28 -> 0.79650375 | H83: =H82/H28 -> 1.1104745 | I83: =I82/I28 -> 1.4330884 | J83: =J82/J28 -> 0.96608757 | K83: =K82/K28 -> 0.71598399 | L83: =L82/L28 -> 0.3843879 | M83: =M82/M28 -> 0.23699264 | N83: =N82/N28 -> 0.15652938
B84: % of ocf | F84: =F82/F96 -> 0.97676991 | G84: =G82/G96 -> 1.9326524 | H84: =H82/H96 -> 3.0563007 | I84: =I82/I96 -> 10.582327 | J84: =J82/J96 -> 2.6067737 | K84: =K82/K96 -> 1.6675495 | L84: =L82/L96 -> 1.0929986 | M84: =M82/M96 -> 0.7456711 | N84: =N82/N96 -> 0.50691501
B86: Change in NWC | F86: 2006 | G86: 1673 | H86: 2089 | I86: =I28*0.01 -> 311.25087 | J86: =J28*0.01 -> 507.87839 | K86: =K28*0.01 -> 788.08082 | L86: =L28*0.01 -> 1174.3413 | M86: =M28*0.01 -> 1619.0047 | N86: =N28*0.01 -> 2083.5602
B87: % of sales | F87: =F86/F28 -> 0.19312602 | G87: =G86/G28 -> 0.1193721 | H87: =H86/H28 -> 0.11186677 | I87: =I86/I28 -> 0.01 | J87: =J86/J28 -> 0.01 | K87: =K86/K28 -> 0.01 | L87: =L86/L28 -> 0.01 | M87: =M86/M28 -> 0.01 | N87: =N86/N28 -> 0.01
B88: % of changes in sales
B90: Stock Based Compensation | F90: 679 | G90: 784 | H90: 1947 | I90: =H90*1.02 -> 1985.94 | J90: =I90*1.02 -> 2025.6588 | K90: =J90*1.02 -> 2066.172 | L90: =K90*1.02 -> 2107.4954 | M90: =L90*1.02 -> 2149.6453 | N90: =M90*1.02 -> 2192.6382
B91: % of sales | F91: =F90/F28 -> 0.065370174 | G91: =G90/G28 -> 0.055940064 | H91: =H90/H28 -> 0.10426261 | I91: =I90/I28 -> 0.063805124 | J91: =J90/J28 -> 0.039884721 | K91: =K90/K28 -> 0.026217767 | L91: =L90/L28 -> 0.017946191 | M91: =M90/M28 -> 0.013277573 | N91: =N90/N28 -> 0.010523517
B93: Adjustments | F93: 3828 | G93: =-1296+773 -> -523 | H93: 985
B94: % of sales | F94: =F93/F31 -> 0.62651391 | G94: =G93/G31 -> -0.065407704 | H94: =H93/H31 -> 0.10422178 | I94: =I93/I31 -> 0 | J94: =J93/J31 -> 0 | K94: =K93/K31 -> 0 | L94: =L93/L31 -> 0 | M94: =M93/M31 -> 0 | N94: =N93/N31 -> 0
B96: Cash Flow from Operations | F96: =F67+F78+F86+F90+F93 -> 4520 | G96: =G67+G78+G86+G90+G93 -> 5776 | H96: =H67+H78+H86+H90+H93 -> 6785 | I96: =I67+I78+I86+I90 -> 4215.0464 | J96: =J67+J78+J86+J90 -> 18822.309 | K96: =K67+K78+K86+K90 -> 33837.272 | L96: =L67+L78+L86+L90 -> 41299.466 | M96: =M67+M78+M86+M90 -> 51455.958 | N96: =N67+N78+N86+N90 -> 64337.882
B97: % growth | G97: =(G96-F96)/F96 -> 0.27787611 | H97: =(H96-G96)/G96 -> 0.17468837 | I97: =(I96-H96)/H96 -> -0.37876988 | J97: =(J96-I96)/I96 -> 3.4655046 | K97: =(K96-J96)/J96 -> 0.79772161 | L97: =(L96-K96)/K96 -> 0.22053178 | M97: =(M96-L96)/L96 -> 0.2459231 | N97: =(N96-M96)/M96 -> 0.25034854
A99: x | B99: DCF | F99: 2023 | G99: 2024 | H99: 2025 | I99: 2026E | J99: 2027E | K99: 2028E | L99: 2029E | M99: 2030E | N99: 2031E
B101: Revenue | F101: =F28 -> 10387 | G101: =G28 -> 14015 | H101: =H28 -> 18674 | I101: =I28 -> 31125.087 | J101: =J28 -> 50787.839 | K101: =K28 -> 78808.082 | L101: =L28 -> 117434.13 | M101: =M28 -> 161900.47 | N101: =N28 -> 208356.02
B102: % growth | G102: =(G101-F101)/F101 -> 0.34928276 | H102: =(H101-G101)/G101 -> 0.33242954 | I102: =(I101-H101)/H101 -> 0.66676056 | J102: =(J101-I101)/I101 -> 0.63173327 | K102: =(K101-J101)/J101 -> 0.55171166 | L102: =(L101-K101)/K101 -> 0.49012803 | M102: =(M101-L101)/L101 -> 0.37864921 | N102: =(N101-M101)/M101 -> 0.28693893
B104: Operating Cash Flow | F104: =F96 -> 4520 | G104: =G96 -> 5776 | H104: =H96 -> 6785 | I104: =I96 -> 4215.0464 | J104: =J96 -> 18822.309 | K104: =K96 -> 33837.272 | L104: =L96 -> 41299.466 | M104: =M96 -> 51455.958 | N104: =N96 -> 64337.882
B105: % of sales | F105: =F104/F101 -> 0.43515933 | G105: =G104/G101 -> 0.41212986 | H105: =H104/H101 -> 0.3633394 | I105: =I104/I101 -> 0.1354228 | J105: =J104/J101 -> 0.37060661 | K105: =K104/K101 -> 0.42936296 | L105: =L104/L101 -> 0.35168196 | M105: =M104/M101 -> 0.31782463 | N105: =N104/N101 -> 0.3087882
B107: CapEx | F107: =F82 -> 4415 | G107: =G82 -> 11163 | H107: =H82 -> 20737 | I107: =I82 -> 44605 | J107: =J82 -> 49065.5 | K107: =K82 -> 56425.325 | L107: =L82 -> 45140.26 | M107: =M82 -> 38369.221 | N107: =N82 -> 32613.838
B108: % of sales | F108: =F107/F101 -> 0.42505054 | G108: =G107/G101 -> 0.79650375 | H108: =H107/H101 -> 1.1104745 | I108: =I107/I101 -> 1.4330884 | J108: =J107/J101 -> 0.96608757 | K108: =K107/K101 -> 0.71598399 | L108: =L107/L101 -> 0.3843879 | M108: =M107/M101 -> 0.23699264 | N108: =N107/N101 -> 0.15652938
B110: Free Cash Flow | F110: =F104-F107 -> 105 | G110: =G104-G107 -> -5387 | H110: =H104-H107 -> -13952 | I110: =I104-I107 -> -40389.954 | J110: =J104-J107 -> -30243.191 | K110: =K104-K107 -> -22588.053 | L110: =L104-L107 -> -3840.7944 | M110: =M104-M107 -> 13086.737 | N110: =N104-N107 -> 31724.044
B111: % of sales | F111: =F110/F101 -> 0.01010879 | G111: =G110/G101 -> -0.38437389 | H111: =H110/H101 -> -0.74713505 | I111: =I110/I101 -> -1.2976656 | J111: =J110/J101 -> -0.59548095 | K111: =K110/K101 -> -0.28662102 | L111: =L110/L101 -> -0.032705946 | M111: =M110/M101 -> 0.080831988 | N111: =N110/N101 -> 0.15225883
B113: Present Value of FCF | I113: =I110/(1+$U$7)^((DATE(2026,7,1)-$D$12)/365) -> -39949.409 | J113: =J110/(1+$U$7)^((DATE(2027,7,1)-$D$12)/365) -> -27193.927 | K113: =K110/(1+$U$7)^((DATE(2028,7,1)-$D$12)/365) -> -18459.377 | L113: =L110/(1+$U$7)^((DATE(2029,7,1)-$D$12)/365) -> -2853.4259 | M113: =M110/(1+$U$7)^((DATE(2030,7,1)-$D$12)/365) -> 8838.6154 | N113: =N110/(1+$U$7)^((DATE(2031,7,1)-$D$12)/365) -> 19478.195
A115: x | B115: Per Share | F115: 2023 | G115: 2024 | H115: 2025 | I115: 2026E | J115: 2027E | K115: 2028E | L115: 2029E | M115: 2030E | N115: 2031E
B117: EPS | F117: =F73 -> -1.6774194 | G117: =G73 -> 0.0063202247 | H117: =H73 -> -1.6872864 | I117: =I73 -> -1.2078552 | J117: =J73 -> 0.66707301 | K117: =K73 -> 2.2852418 | L117: =L73 -> 3.5416332 | M117: =M73 -> 5.0538558 | N117: =N73 -> 6.7036775
B118: % change | G118: =(G117-F117)/F117 -> -1.0037678 | H118: =(H117-G117)/G117 -> -267.9662 | I118: =(I117-H117)/H117 -> -0.28414334 | J118: =(J117-I117)/I117 -> -1.552279 | K118: =(K117-J117)/J117 -> 2.4257746 | L118: =(L117-K117)/K117 -> 0.54978492 | M118: =(M117-L117)/L117 -> 0.42698451 | N118: =(N117-M117)/M117 -> 0.32644813
B120: Shares Outstanding | F120: =F70 -> 2759 | G120: =G70 -> 2848 | H120: =H70 -> 2926 | I120: =I70 -> 5798 | J120: =J70 -> 6029.92 | K120: =K70 -> 6150.5184 | L120: =L70 -> 6273.5288 | M120: =M70 -> 6398.9993 | N120: =N70 -> 6526.9793
B121: % change | G121: =(G120-F120)/F120 -> 0.032258065 | H121: =(H120-G120)/G120 -> 0.02738764 | I121: =(I120-H120)/H120 -> 0.98154477 | J121: =(J120-I120)/I120 -> 0.04 | K121: =(K120-J120)/J120 -> 0.02 | L121: =(L120-K120)/K120 -> 0.02 | M121: =(M120-L120)/L120 -> 0.02 | N121: =(N120-M120)/M120 -> 0.02
B123: P/E | F123: =J17/F117 -> 0 | G123: =#REF!/G117 -> #REF! | H123: =K17/H117 -> 0 | I123: =$E$9/I117 -> -249.88775 | J123: =$E$9/J117 -> 452.46654 | K123: =$E$9/K117 -> 132.07715 | L123: =$E$9/L117 -> 85.222889 | M123: =$E$9/M117 -> 59.722365 | N123: =$E$9/N117 -> 45.024275
B124: P/EBIT | F124: =J17*F120/F49 -> 0 | G124: =#REF!*G120/G49 -> #REF! | H124: =K17*H120/H49 -> 0 | I124: =$E$9*I120/I49 -> -249.88775 | J124: =$E$9*J120/J49 -> 398.17056 | K124: =$E$9*K120/K49 -> 114.90712 | L124: =$E$9*L120/L49 -> 73.291685 | M124: =$E$9*M120/M49 -> 50.76401 | N124: =$E$9*N120/N49 -> 37.820391
B125: P/EBITDA | F125: =J17*F120/(F49+F78) -> 0 | G125: =#REF!*G120/(G49+G78) -> #REF! | H125: =K17*H120/(H49+H78) -> 0 | I125: =$E$9*I120/(I49+I78) -> 912.4775 | J125: =$E$9*J120/(J49+J78) -> 108.09347 | K125: =$E$9*K120/(K49+K78) -> 56.11298 | L125: =$E$9*L120/(L49+L78) -> 45.479673 | M125: =$E$9*M120/(M49+M78) -> 36.172374 | N125: =$E$9*N120/(N49+N78) -> 28.803274
B126: P/S | F126: =J17*F120/F28 -> 0 | G126: =#REF!*G120/G28 -> #REF! | H126: =K17*H120/H28 -> 0 | I126: =$E$9*I120/I28 -> 56.224743 | J126: =$E$9*J120/J28 -> 35.83535 | K126: =$E$9*K120/K28 -> 23.55596 | L126: =$E$9*L120/L28 -> 16.124171 | M126: =$E$9*M120/M28 -> 11.929542 | N126: =$E$9*N120/N28 -> 9.4550977
B127: P/FCF | F127: =J17*F120/F110 -> 0 | G127: =#REF!*G120/G110 -> #REF! | H127: =K17*H120/H110 -> 0 | I127: =$E$9*I120/I110 -> -43.327606 | J127: =$E$9*J120/J110 -> -60.178835 | K127: =$E$9*K120/K110 -> -82.185038 | L127: =$E$9*L120/L110 -> -493.00427 | M127: =$E$9*M120/M110 -> 147.58442 | N127: =$E$9*N120/N110 -> 62.098846
B128: P/OCF | F128: =J17*F120/F104 -> 0 | G128: =#REF!*G120/G104 -> #REF! | H128: =K17*H120/H104 -> 0 | I128: =$E$9*I120/I104 -> 415.1793 | J128: =$E$9*J120/J104 -> 96.693769 | K128: =$E$9*K120/K104 -> 54.862579 | L128: =$E$9*L120/L104 -> 45.848729 | M128: =$E$9*M120/M104 -> 37.534984 | N128: =$E$9*N120/N104 -> 30.620009

Sheet Segments
K2: all values in millions except per share numbers
A4: x | B4: Levers | D4: 2026 | E4: 2031 | I4: 2026 | J4: 2031
B6: Mass to Orbit | D6: 556
B7: Launches | D7: 40
B8: Starlink Subs (m) | D8: 10.3
B9: Starlink ARPU | D9: 66
B10: AI Compute GW | D10: 1
A12: x | B12: Product Segments ($M) | F12: 2023 | G12: 2024 | H12: 2025 | I12: 2026E | J12: 2027E | K12: 2028E | L12: 2029E | M12: 2030E | N12: 2031E
B14: Revenue | F14: =F17+F26+F35 -> 10387 | G14: =G17+G26+G35 -> 14015 | H14: =H17+H26+H35 -> 18674 | I14: =I17+I26+I35 -> 31125.087 | J14: =J17+J26+J35 -> 50787.839 | K14: =K17+K26+K35 -> 78808.082 | L14: =L17+L26+L35 -> 117434.13 | M14: =M17+M26+M35 -> 161900.47 | N14: =N17+N26+N35 -> 208356.02
B15: % growth | G15: =(G14-F14)/F14 -> 0.34928276 | H15: =(H14-G14)/G14 -> 0.33242954 | I15: =(I14-H14)/H14 -> 0.66676056 | J15: =(J14-I14)/I14 -> 0.63173327 | K15: =(K14-J14)/J14 -> 0.55171166 | L15: =(L14-K14)/K14 -> 0.49012803 | M15: =(M14-L14)/L14 -> 0.37864921 | N15: =(N14-M14)/M14 -> 0.28693893
B17: Space | F17: =F20+F23 -> 3557 | G17: =G20+G23 -> 3796 | H17: =H20+H23 -> 4086 | I17: =I20+I23 -> 4117.8081 | J17: =J20+J23 -> 5647.5576 | K17: =K20+K23 -> 8041.3544 | L17: =L20+L23 -> 12031.016 | M17: =M20+M23 -> 17018.093 | N17: =N20+N23 -> 24000
B18: % growth | G18: =(G17-F17)/F17 -> 0.067191453 | H18: =(H17-G17)/G17 -> 0.076396207 | I18: =(I17-H17)/H17 -> 0.0077846616 | J18: =(J17-I17)/I17 -> 0.37149605 | K18: =(K17-J17)/J17 -> 0.42386409 | L18: =(L17-K17)/K17 -> 0.49614296 | M18: =(M17-L17)/L17 -> 0.41451834 | N18: =(N17-M17)/M17 -> 0.41026381
B20: Launch Services | F20: 1964 | G20: 2584 | H20: 2576 | I20: =H20*(1+((330-566)/566)+0.4) -> 2532.3081 | J20: =$I$20+($N$20-$I$20)*0.08 -> 3529.7235 | K20: =$I$20+($N$20-$I$20)*0.2 -> 5025.8465 | L20: =$I$20+($N$20-$I$20)*0.4 -> 7519.3849 | M20: =$I$20+($N$20-$I$20)*0.65 -> 10636.308 | N20: 15000
B21: % growth | G21: =(G20-F20)/F20 -> 0.31568228 | H21: =(H20-G20)/G20 -> -0.0030959752 | I21: =(I20-H20)/H20 -> -0.016961131 | J21: =(J20-I20)/I20 -> 0.39387598 | K21: =(K20-J20)/J20 -> 0.42386409 | L21: =(L20-K20)/K20 -> 0.49614296 | M21: =(M20-L20)/L20 -> 0.41451834 | N21: =(N20-M20)/M20 -> 0.41026381
B23: Launch & Development | F23: 1593 | G23: 1212 | H23: 1510 | I23: =H23*1.05 -> 1585.5 | J23: =J20*0.6 -> 2117.8341 | K23: =K20*0.6 -> 3015.5079 | L23: =L20*0.6 -> 4511.6309 | M23: =M20*0.6 -> 6381.7847 | N23: =N20*0.6 -> 9000
B24: % growth | G24: =(G23-F23)/F23 -> -0.23917137 | H24: =(H23-G23)/G23 -> 0.24587459 | I24: =(I23-H23)/H23 -> 0.05 | J24: =(J23-I23)/I23 -> 0.33575155 | K24: =(K23-J23)/J23 -> 0.42386409 | L24: =(L23-K23)/K23 -> 0.49614296 | M24: =(M23-L23)/L23 -> 0.41451834 | N24: =(N23-M23)/M23 -> 0.41026381
B26: Connectivity | F26: =F29+F32 -> 3869 | G26: =G29+G32 -> 7599 | H26: =H29+H32 -> 11387 | I26: =I29+I32 -> 15809.901 | J26: =J29+J32 -> 21782.147 | K26: =K29+K32 -> 29801.463 | L26: =L29+L32 -> 40668.225 | M26: =M29+M32 -> 53541.144 | N26: =N29+N32 -> 69057.463
B27: % growth | G27: =(G26-F26)/F26 -> 0.9640734 | H27: =(H26-G26)/G26 -> 0.49848664 | I27: =(I26-H26)/H26 -> 0.38841671 | J27: =(J26-I26)/I26 -> 0.37775354 | K27: =(K26-J26)/J26 -> 0.36816001 | L27: =(L26-K26)/K26 -> 0.36463855 | M27: =(M26-L26)/L26 -> 0.31653506 | N27: =(N26-M26)/M26 -> 0.28980178
B29: Consumer | F29: 2817 | G29: 4830 | H29: 7208 | I29: =H29*(1+((2148-1492)/1492)) -> 10377.201 | J29: =I29*(1+J30) -> 14448.002 | K29: =J29*(1+K30) -> 19533.66 | L29: =K29*(1+L30) -> 25779.911 | M29: =L29*(1+M30) -> 33441.92 | N29: =M29*(1+N30) -> 42928.471
B30: % growth | G30: =(G29-F29)/F29 -> 0.71458999 | H30: =(H29-G29)/G29 -> 0.49233954 | I30: =(I29-H29)/H29 -> 0.43967828 | J30: =I30+(I30-H30)*0.9 -> 0.39228315 | K30: =J30+(J30-I30)*0.85 -> 0.35199729 | L30: =K30+(K30-J30)*0.8 -> 0.31976859 | M30: =L30+(L30-K30)*0.7 -> 0.29720851 | N30: =M30+(M30-L30)*0.6 -> 0.28367246
B32: Enterprise & Government | F32: 1052 | G32: 2769 | H32: 4179 | I32: =H32*(1.3) -> 5432.7 | J32: =I32*1.35 -> 7334.145 | K32: =J32*1.4 -> 10267.803 | L32: =K32*1.45 -> 14888.314 | M32: =L32*1.35 -> 20099.224 | N32: =M32*1.3 -> 26128.992
B33: % growth | G33: =(G32-F32)/F32 -> 1.6321293 | H33: =(H32-G32)/G32 -> 0.5092091 | I33: =(I32-H32)/H32 -> 0.3 | J33: =(J32-I32)/I32 -> 0.35 | K33: =(K32-J32)/J32 -> 0.4 | L33: =(L32-K32)/K32 -> 0.45 | M33: =(M32-L32)/L32 -> 0.35 | N33: =(N32-M32)/M32 -> 0.3
B35: AI | F35: =F38+F41 -> 2961 | G35: =G38+G41 -> 2620 | H35: =H38+H41 -> 3201 | I35: =I38+I41 -> 11197.377 | J35: =J38+J41 -> 23358.135 | K35: =K38+K41 -> 40965.265 | L35: =L38+L41 -> 64734.892 | M35: =M38+M41 -> 91341.237 | N35: =N38+N41 -> 115298.56
B36: % growth | G36: =(G35-F35)/F35 -> -0.1151638 | H36: =(H35-G35)/G35 -> 0.22175573 | I36: =(I35-H35)/H35 -> 2.4980873 | J36: =(J35-I35)/I35 -> 1.0860362 | K36: =(K35-J35)/J35 -> 0.75379011 | L36: =(L35-K35)/K35 -> 0.58023856 | M36: =(M35-L35)/L35 -> 0.41100471 | N36: =(N35-M35)/M35 -> 0.26228374
B38: Advertising | F38: 2323 | G38: 1728 | H38: 1844 | I38: =H38*((1+(343-443)/443)) -> 1427.7472 | J38: =I38*1.05 -> 1499.1345 | K38: =J38*1.08 -> 1619.0653 | L38: =K38*1.1 -> 1780.9718 | M38: =L38*1.8 -> 3205.7493 | N38: =M38*1.6 -> 5129.1989
B39: % growth | G39: =(G38-F38)/F38 -> -0.25613431 | H39: =(H38-G38)/G38 -> 0.06712963 | I39: =(I38-H38)/H38 -> -0.22573363 | J39: =(J38-I38)/I38 -> 0.05 | K39: =(K38-J38)/J38 -> 0.08 | L39: =(L38-K38)/K38 -> 0.1 | M39: =(M38-L38)/L38 -> 0.8 | N39: =(N38-M38)/M38 -> 0.6
B41: AI Solutions & Infrastructure | F41: 638 | G41: 892 | H41: 1357 | I41: =H41*(1+(475-284)/284)+(1250*6) -> 9769.6303 | J41: =(2270*1.7)+(1500*12) -> 21859 | K41: =J41*1.8 -> 39346.2 | L41: =K41*1.6 -> 62953.92 | M41: =L41*1.4 -> 88135.488 | N41: =M41*1.25 -> 110169.36
B42: % growth | G42: =(G41-F41)/F41 -> 0.39811912 | H42: =(H41-G41)/G41 -> 0.52130045 | I42: =(I41-H41)/H41 -> 6.1994328 | J42: =(J41-I41)/I41 -> 1.2374439 | K42: =(K41-J41)/J41 -> 0.8 | L42: =(L41-K41)/K41 -> 0.6 | M42: =(M41-L41)/L41 -> 0.4 | N42: =(N41-M41)/M41 -> 0.25
A44: x | B44: Operating Income by Segment | F44: 2023 | G44: 2024 | H44: 2025 | I44: 2026E | J44: 2027E | K44: 2028E | L44: 2029E | M44: 2030E | N44: 2031E
B46: Operating Income | F46: =SUM(F49,F52,F55) -> -3505 | G46: =SUM(G49,G52,G55) -> 466 | H46: =SUM(H49,H52,H55) -> -2589 | I46: =SUM(I49,I52,I55) -> -10469
B47: % of sales | F47: =F46/F$14 -> -0.33744103 | G47: =G46/G$14 -> 0.033250089 | H47: =H46/H$14 -> -0.13864196 | I47: =I46/I$14 -> -0.33635248
B49: Space | F49: -1 | G49: 21 | H49: -657 | I49: =H49+4*(-662-(-70)) -> -3025
B50: % of sales | F50: =F49/F$14 -> -9.6274189e-05 | G50: =G49/G$14 -> 0.0014983946 | H50: =H49/H$14 -> -0.035182607 | I50: =I49/I$14 -> -0.097188484
B52: Connectivity | F52: 469 | G52: 2006 | H52: 4423 | I52: =H52+4*(1188-1033) -> 5043
B53: % of sales | F53: =F52/F$14 -> 0.045152595 | G53: =G52/G$14 -> 0.14313236 | H53: =H52/H$14 -> 0.23685338 | I53: =I52/I$14 -> 0.16202365
B55: AI | F55: -3973 | G55: -1561 | H55: -6355 | I55: =H55+4*(-2469-(-936)) -> -12487
B56: % of sales | F56: =F55/F$14 -> -0.38249735 | G56: =G55/G$14 -> -0.11138066 | H56: =H55/H$14 -> -0.34031273 | I56: =I55/I$14 -> -0.40118764
B58: EBITDA | F58: =SUM(F61,F64,F67) -> 2599 | G58: =SUM(G61,G64,G67) -> 5350 | H58: =SUM(H61,H64,H67) -> 6584 | I58: =SUM(I61,I64,I67) -> 4172
B59: % of sales | F59: =F58/F$14 -> 0.25021662 | G59: =G58/G$14 -> 0.38173386 | H59: =H58/H$14 -> 0.35257577 | I59: =I58/I$14 -> 0.13403979
B61: Space | F61: 997 | G61: 1154 | H61: 653 | I61: =H61+4*(-351-224) -> -1647
B62: % of sales | F62: =F61/F$14 -> 0.095985366 | G62: =G61/G$14 -> 0.08234035 | H62: =H61/H$14 -> 0.034968405 | I62: =I61/I$14 -> -0.052915515
B64: Connectivity | F64: 1602 | G64: 3849 | H64: 7168 | I64: =H64+4*(2087-1618) -> 9044
B65: % of sales | F65: =F64/F$14 -> 0.15423125 | G65: =G64/G$14 -> 0.27463432 | H65: =H64/H$14 -> 0.3838492 | I65: =I64/I$14 -> 0.29056947
B67: AI | G67: 347 | H67: -1237 | I67: =H67+4*(-609-(-112)) -> -3225
B68: % of sales | G68: =G67/G$14 -> 0.024759187 | H68: =H67/H$14 -> -0.066241834 | I68: =I67/I$14 -> -0.10361417
A70: x | B70: Industry Metrics | F70: 2023 | G70: 2024 | H70: 2025 | I70: 2026E | J70: 2027E | K70: 2028E | L70: 2029E | M70: 2030E | N70: 2031E
B72: Capital Expenditures | F72: =SUM(F75,F78,F81) -> 4415 | G72: =SUM(G75,G78,G81) -> 11163 | H72: =SUM(H75,H78,H81) -> 20737 | I72: =SUM(I75,I78,I81) -> 44605
B73: % of sales | F73: =F72/F$14 -> 0.42505054 | G73: =G72/G$14 -> 0.79650375 | H73: =H72/H$14 -> 1.1104745 | I73: =I72/I$14 -> 1.4330884
B75: Space CapEx | F75: 1497 | G75: 2032 | H75: 3832 | I75: =H75+4*(1052-759) -> 5004
B76: % of sales | F76: =F75/F$14 -> 0.14412246 | G76: =G75/G$14 -> 0.14498751 | H76: =H75/H$14 -> 0.2052051 | I76: =I75/I$14 -> 0.16077064
B78: Connectivity CapEx | F78: 2455 | G78: 3498 | H78: 4178 | I78: =H78+4*(1332-814) -> 6250
B79: % of sales | F79: =F78/F$14 -> 0.23635313 | G79: =G78/G$14 -> 0.24958973 | H79: =H78/H$14 -> 0.22373353 | I79: =I78/I$14 -> 0.20080265
B81: AI CapEx | F81: 463 | G81: 5633 | H81: 12727 | I81: =H81+4*(7723-2567) -> 33351
B82: % of sales | F82: =F81/F$14 -> 0.044574949 | G82: =G81/G$14 -> 0.40192651 | H82: =H81/H$14 -> 0.68153583 | I82: =I81/I$14 -> 1.0715151
